Workbook
Name ADEnq: [1]Sheet4!$A$2:$A$3
Name Adstat: [1]Sheet4!$A$5:$A$8
Name Approval: [1]Sheet2!$A$11:$A$13
Name BCSTATUS: [1]Sheet2!$E$7:$E$12
Name Beg_Bal: '[2] Loan schedule - Term 1'!$C$18:$C$497
Name COLLATERAL: [1]Sheet2!$A$20:$A$78
Name COLLATORDSTA: [1]Sheet2!$E$17:$E$18
Name COMMAPP: [1]Sheet4!$B$21:$B$31
Name COMMSTAT: [1]Sheet4!$A$31:$A$36
Name Commtype: [1]Sheet4!$A$15:$A$20
Name End_Bal: '[2] Loan schedule - Term 1'!$I$18:$I$497
Name Extra_Pay: '[2] Loan schedule - Term 1'!$E$18:$E$497
Name Full_Print: '[2] Loan schedule - Term 1'!$A$1:$J$497
Name Header_Row: ROW('[2] Loan schedule - Term 1'!$17:$17)
Name Int: '[2] Loan schedule - Term 1'!$H$18:$H$497
Name Interest_Rate: '[2] Loan schedule - Term 1'!$D$6
Name Last_Row: IF(Values_Entered,Header_Row+Number_of_Payments,Header_Row)
Name Loan_Amount: '[2] Loan schedule - Term 1'!$D$5
Name Loan_Start: '[2] Loan schedule - Term 1'!$D$9
Name Loan_Years: '[2] Loan schedule - Term 1'!$D$7
Name NamedRange1: [1]Sheet2!$A$1:$A$9
Name Num_Pmt_Per_Year: '[2] Loan schedule - Term 1'!$D$8
Name Number_of_Payments: MATCH(0.01,End_Bal,-1)+1
Name Pay_Num: '[2] Loan schedule - Term 1'!$A$18:$A$497
Name Payment_Date: DATE(YEAR(Loan_Start),MONTH(Loan_Start)+Payment_Number,DAY(Loan_Start))
Name Princ: '[2] Loan schedule - Term 1'!$G$18:$G$497
Name Print_Area_Reset: OFFSET(Full_Print,0,0,Last_Row)
Name Role: [1]Sheet2!$E$22:$E$29
Name Sched_Pay: '[2] Loan schedule - Term 1'!$D$18:$D$497
Name Scheduled_Extra_Payments: '[2] Loan schedule - Term 1'!$D$10
Name Scheduled_Monthly_Payment: '[2] Loan schedule - Term 1'!$J$5
Name STATUS1: [1]Sheet2!$C$1:$C$5
Name Total_Pay: '[2] Loan schedule - Term 1'!$F$18:$F$497
Name Values_Entered: IF(Loan_Amount*Interest_Rate*Loan_Years*Loan_Start>0,1,0)
Name yesno: [1]Sheet4!$A$10:$A$11
Name YNNA: [1]Sheet4!$A$10:$A$12
Name ZeePhotoFIle: [1]Sheet2!$A$11:$A$12

Sheet Scorecard matrix
A1: Franchise | B1: Franchisee Name | C1: State | D1: Profile | E1: Tenure | F1: Expiry Date | G1: Ultimate Expiry Date (Including FY18 release) | H1: FY22 unlimited term candidates | I1: Unlimted Term | J1: Annual Turnover (1 Feb 2020 - 31 Jan 2021) | K1: Sales team engagement score | L1: Digisitation | M1: Not in attendance at Roadshow | N1: Workshop Attendance | O1: Reading weekly bulletins(After final reminder) | P1: Customer Nomination | Q1: MPEX allocation | R1: MPEX Usage % (as @ 08102019) | S1: Late with completion of monthly invoicing | T1: Approved vehicle | U1: Vehicle signage (Past 4 years) | V1: Uniform (ordered in past 12months) | W1: HO Insurances | X1: 30th Sept action email (Feedback) | Y1: Engagement with sales team | Z1: Terminated (mutually or otherwise) | AA1: Breach notice served | AB1: Written warning issued | AC1: commentary | AD1: Vaccine | AE1: Booster | AF1: Medical Exemption | AG1: Contingency engaged
A2: Yatala | B2: Michael Mikits | C2: QLD | D2: Investor | E2: 10 | F2: 45323 | G2: 48976 | I2: =VLOOKUP(A2,'Scorecard summary'!A:AB,10,0) -> Yes | J2: =VLOOKUP(A2,'Revenue @ Feb 2021'!A:B,2,0) -> #N/A | K2: =VLOOKUP(A2,'Sales team engagament review'!A:H,2,0) -> 4 | L2: YES | M2: YES | N2: YES | O2: YES | P2: NO | Q2: YES | S2: NO | T2: ? | U2: ? | V2: ? | W2: YES | Y2: =VLOOKUP(A:A,'Sales team engagament review'!$A:$H,2,0) -> 4 | AD2: 2 + cert
A3: Wyong | B3: Dennis Kinchela | C3: NSW | D3: Owner operator | E3: 4 | F3: 44311 | G3: 47963 | I3: =VLOOKUP(A3,'Scorecard summary'!A:AB,10,0) -> Yes | J3: =VLOOKUP(A3,'Revenue @ Feb 2021'!A:B,2,0) -> 64243.24 | K3: =VLOOKUP(A3,'Sales team engagament review'!A:H,2,0) -> 2 | L3: YES | M3: YES | N3: YES | O3: YES | P3: NO | Q3: YES | R3: =VLOOKUP(A3,'Franchisee Ranking'!B:G,6,0) -> 0 | S3: NO | T3: YES | U3: YES | V3: ? | W3: YES | X3: Had some personal relationship issues but motivated to get MPEX into his customers | Y3: =VLOOKUP(A:A,'Sales team engagament review'!$A:$H,2,0) -> 2 | AD3: 2 + cert
A4: Willoughby | B4: Peter Hayes | C4: NSW | D4: Owner operator | E4: =VLOOKUP(A4,[3]ActiveFranchiseesResults465!$C:$AA,25,0) -> 11 | F4: 43586 | G4: 45413 | I4: =VLOOKUP(A4,'Scorecard summary'!A:AB,10,0) -> Yes | J4: =VLOOKUP(A4,'Revenue @ Feb 2021'!A:B,2,0) -> 167507.73 | K4: =VLOOKUP(A4,'Sales team engagament review'!A:H,2,0) -> 5 | L4: YES | M4: YES | N4: YES | O4: YES | P4: YES | Q4: YES | R4: =VLOOKUP(A4,'Franchisee Ranking'!B:H,6,0) -> 0.23611111 | S4: NO | T4: YES | U4: YES | V4: ? | W4: YES | Y4: =VLOOKUP(A:A,'Sales team engagament review'!$A:$H,2,0) -> 5 | AD4: 2 + cert
A5: Wetherill Park | B5: Madhukar Prasad | C5: NSW | D5: Owner operator | E5: =VLOOKUP(A5,[3]ActiveFranchiseesResults465!$C:$AA,25,0) -> 19 | F5: 45455 | G5: 45820 | I5: =VLOOKUP(A5,'Scorecard summary'!A:AB,10,0) -> Yes | J5: =VLOOKUP(A5,'Revenue @ Feb 2021'!A:B,2,0) -> 168688.02 | K5: =VLOOKUP(A5,'Sales team engagament review'!A:H,2,0) -> 2 | L5: YES | M5: YES | N5: YES | O5: YES | P5: NO | Q5: YES | R5: =VLOOKUP(A5,'Franchisee Ranking'!B:G,6,0) -> 0 | S5: NO | T5: YES | U5: YES | V5: ? | W5: YES | X5: Waiting on Stacey to provide feedback on his migration call down…. | Y5: =VLOOKUP(A:A,'Sales team engagament review'!$A:$H,2,0) -> 2 | AD5: 2 + cert
A6: West Perth | B6: Jobin Mathew Parthickal | C6: WA | D6: Owner operator | E6: =VLOOKUP(A6,[3]ActiveFranchiseesResults465!$C:$AA,25,0) -> 3 | F6: 43709 | G6: 47362 | I6: =VLOOKUP(A6,'Scorecard summary'!A:AB,10,0) -> Yes | J6: =VLOOKUP(A6,'Revenue @ Feb 2021'!A:B,2,0) -> 40896.48 | K6: =VLOOKUP(A6,'Sales team engagament review'!A:H,2,0) -> 3 | L6: NO | M6: YES | N6: YES | O6: YES | P6: NO | Q6: NO | R6: =VLOOKUP(A6,'Franchisee Ranking'!B:G,6,0) -> 0 | S6: NO | T6: ? | U6: ? | V6: Yes | W6: YES | X6: Will allocate to customers ASAP | Y6: =VLOOKUP(A:A,'Sales team engagament review'!$A:$H,2,0) -> 3 | AB6: Yes
A7: Welshpool | B7: Roque Bautista | C7: WA | D7: Owner operator | E7: =VLOOKUP(A7,[3]ActiveFranchiseesResults465!$C:$AA,25,0) -> 5 | F7: 44652 | G7: 48305 | I7: =VLOOKUP(A7,'Scorecard summary'!A:AB,10,0) -> Yes | J7: =VLOOKUP(A7,'Revenue @ Feb 2021'!A:B,2,0) -> 77895.59 | K7: =VLOOKUP(A7,'Sales team engagament review'!A:H,2,0) -> 4 | L7: YES | M7: YES | N7: YES | O7: YES | P7: NO | Q7: YES | R7: =VLOOKUP(A7,'Franchisee Ranking'!B:G,6,0) -> 0.23076923 | S7: NO | T7: ? | U7: ? | V7: ? | W7: YES | Y7: =VLOOKUP(A:A,'Sales team engagament review'!$A:$H,2,0) -> 4 | AD7: 2 + cert
A8: Waterloo | B8: MailPlus Head Office | C8: NSW | D8: N/A | E8: N/A | F8: 44408 | G8: 48060 | I8: HEAD OFFICE | J8: =VLOOKUP(A8,'Revenue @ Feb 2021'!A:B,2,0) -> 65479.59 | K8: =VLOOKUP(A8,'Sales team engagament review'!A:H,2,0) -> #N/A | L8: YES | M8: YES | N8: YES | O8: YES | P8: NO | Q8: YES | R8: =VLOOKUP(A8,'Franchisee Ranking'!B:H,6,0) -> 0.44736842 | S8: NO | T8: ? | U8: ? | V8: ? | W8: NO | Y8: =VLOOKUP(A:A,'Sales team engagament review'!$A:$H,2,0) -> #N/A
A9: Trinh TRINH | B9: Quan Trin | C9: QLD | D9: Owner operator | E9: =VLOOKUP(A9,[3]ActiveFranchiseesResults465!$C:$AA,25,0) -> 16 | F9: 43709 | G9: 46997 | H9: Yes on exit | I9: =VLOOKUP(A9,'Scorecard summary'!A:AB,10,0) -> NO | J9: =VLOOKUP(A9,'Revenue @ Feb 2021'!A:B,2,0) -> 110576.14 | K9: =VLOOKUP(A9,'Sales team engagament review'!A:H,2,0) -> 1 | L9: YES | M9: YES | N9: YES | O9: YES | P9: YES | Q9: YES | R9: =VLOOKUP(A9,'Franchisee Ranking'!B:G,6,0) -> 0 | S9: NO | T9: ? | U9: ? | V9: ? | W9: YES | Y9: =VLOOKUP(A:A,'Sales team engagament review'!$A:$H,2,0) -> 1 | AD9: 2 + cert
A10: Townsville (HO Owned) | B10: MailPlus Head Office | C10: QLD | D10: N/A | E10: N/A | F10: N/A | G10: N/A | I10: =VLOOKUP(A10,'Scorecard summary'!A:AB,10,0) -> HEAD OFFICE | J10: =VLOOKUP(A10,'Revenue @ Feb 2021'!A:B,2,0) -> #N/A | K10: =VLOOKUP(A10,'Sales team engagament review'!A:H,2,0) -> 5 | L10: YES | M10: YES | N10: YES | O10: YES | P10: NO | Q10: NO | S10: NO | T10: ? | U10: ? | V10: ? | W10: NO | Y10: =VLOOKUP(A:A,'Sales team engagament review'!$A:$H,2,0) -> 5
A11: Toowoomba | B11: Kiely Prendergast | C11: QLD | D11: Investor | E11: =VLOOKUP(A11,[3]ActiveFranchiseesResults465!$C:$AA,25,0) -> 3 | F11: 44805 | G11: 46661 | I11: yes | J11: =VLOOKUP(A11,'Revenue @ Feb 2021'!A:B,2,0) -> 149881.33 | K11: =VLOOKUP(A11,'Sales team engagament review'!A:H,2,0) -> 3 | L11: YES | M11: YES | N11: YES | O11: YES | P11: YES | Q11: YES | R11: =VLOOKUP(A11,'Franchisee Ranking'!B:H,6,0) -> 0.13513514 | S11: NO | T11: YES | U11: YES | V11: Yes | W11: NO | Y11: =VLOOKUP(A:A,'Sales team engagament review'!$A:$H,2,0) -> 3 | AD11: 1 + cert
A12: Taren Point | B12: Miljenko Ivanic | C12: NSW | D12: Owner operator | E12: =VLOOKUP(A12,[3]ActiveFranchiseesResults465!$C:$AA,25,0) -> 10 | F12: 43891 | G12: 46447 | I12: =VLOOKUP(A12,'Scorecard summary'!A:AB,10,0) -> yes | J12: =VLOOKUP(A12,'Revenue @ Feb 2021'!A:B,2,0) -> 99485.92 | K12: =VLOOKUP(A12,'Sales team engagament review'!A:H,2,0) -> 4 | L12: YES | M12: YES | N12: YES | O12: YES | P12: YES | Q12: YES | R12: =VLOOKUP(A12,'Franchisee Ranking'!B:H,6,0) -> 0.33333333 | S12: NO | T12: ? | U12: ? | V12: ? | W12: YES | Y12: =VLOOKUP(A:A,'Sales team engagament review'!$A:$H,2,0) -> 4 | AD12: 2 + cert
A13: Tappenden Tappenden | B13: Allison Tappenden | C13: QLD | D13: Owner operator | E13: =VLOOKUP(A13,[3]ActiveFranchiseesResults465!$C:$AA,25,0) -> 16 | F13: 43709 | G13: 46997 | I13: =VLOOKUP(A13,'Scorecard summary'!A:AB,10,0) -> Yes | J13: =VLOOKUP(A13,'Revenue @ Feb 2021'!A:B,2,0) -> 195336.58 | K13: =VLOOKUP(A13,'Sales team engagament review'!A:H,2,0) -> 3 | L13: NO | M13: YES | N13: NO | O13: YES | P13: NO | Q13: NO | R13: =VLOOKUP(A13,'Franchisee Ranking'!B:G,6,0) -> 0 | S13: NO | T13: yES | U13: yES | V13: yes | W13: YES | X13: Hostile reply - blaming anyone & everyone | Y13: =VLOOKUP(A:A,'Sales team engagament review'!$A:$H,2,0) -> 3 | AD13: 2 + cert
A14: Sydney - South East B Sydney - South East B | B14: Ali Gasham | C14: NSW | D14: Investor | E14: =VLOOKUP(A14,[3]ActiveFranchiseesResults465!$C:$AA,25,0) -> 9 | F14: 44470 | G14: 46296 | H14: =I14 -> Yes | I14: =I13 -> Yes | J14: =VLOOKUP(A14,'Revenue @ Feb 2021'!A:B,2,0) -> 208210.4 | K14: =VLOOKUP(A14,'Sales team engagament review'!A:H,2,0) -> 5 | L14: YES | M14: YES | N14: YES | O14: YES | P14: NO | Q14: YES | R14: =VLOOKUP(A14,'Franchisee Ranking'!B:G,6,0) -> 0.074626866 | S14: NO | T14: ? | U14: ? | V14: Yes | W14: YES | X14: Never had big product sales in CBD with AP | Y14: =VLOOKUP(A:A,'Sales team engagament review'!$A:$H,2,0) -> 5 | AD14: 2 + cert
A15: Sydney - South East A Sydney - South East A | B15: Ali Gasham | C15: NSW | D15: Investor | E15: =VLOOKUP(A15,[3]ActiveFranchiseesResults465!$C:$AA,25,0) -> 8 | F15: 42916 | G15: 46568 | H15: =I15 -> Yes payment still O/S | I15: Yes payment still O/S | J15: =VLOOKUP(A15,'Revenue @ Feb 2021'!A:B,2,0) -> 186746.07 | K15: =VLOOKUP(A15,'Sales team engagament review'!A:H,2,0) -> 5 | L15: YES | M15: YES | N15: YES | O15: YES | P15: NO | Q15: YES | R15: =VLOOKUP(A15,'Franchisee Ranking'!B:G,6,0) -> 0.028985507 | S15: NO | T15: ? | U15: ? | V15: Yes | W15: YES | X15: Never had big product sales in CBD with AP | Y15: =VLOOKUP(A:A,'Sales team engagament review'!$A:$H,2,0) -> 5 | AD15: 2 + cert
A16: Sydney - North West | B16: Jason Yang | C16: NSW | D16: Investor | E16: =VLOOKUP(A16,[3]ActiveFranchiseesResults465!$C:$AA,25,0) -> 1 | F16: 44470 | G16: 46296 | I16: =VLOOKUP(A16,'Scorecard summary'!A:AB,10,0) -> Yes | J16: =VLOOKUP(A16,'Revenue @ Feb 2021'!A:B,2,0) -> 273657.43 | K16: =VLOOKUP(A16,'Sales team engagament review'!A:H,2,0) -> 3 | L16: NO | M16: YES | N16: YES | O16: YES | P16: NO | Q16: YES | R16: =VLOOKUP(A16,'Franchisee Ranking'!B:G,6,0) -> 0.03125 | S16: Yes | T16: ? | U16: ? | V16: Yes | W16: YES | X16: Now that LPO margins have been slashed he will embrace | Y16: =VLOOKUP(A:A,'Sales team engagament review'!$A:$H,2,0) -> 3 | AD16: 2 + Cert
A17: Sydney - 2N3 | B17: Gavin Ye | C17: NSW | D17: Investor | E17: =VLOOKUP(A17,[3]ActiveFranchiseesResults465!$C:$AA,25,0) -> 3 | F17: 44470 | G17: 48580 | H17: Yes | I17: =VLOOKUP(A17,'Scorecard summary'!A:AB,10,0) -> NO | J17: =VLOOKUP(A17,'Revenue @ Feb 2021'!A:B,2,0) -> 332842.65 | K17: =VLOOKUP(A17,'Sales team engagament review'!A:H,2,0) -> 4 | L17: YES | M17: NO | N17: YES | O17: YES | P17: NO | Q17: YES | R17: =VLOOKUP(A17,'Franchisee Ranking'!B:G,6,0) -> 0.062068966 | S17: Yes | T17: ? | U17: ? | V17: Yes | W17: YES | X17: Overseas & not readings comms. | Y17: =VLOOKUP(A:A,'Sales team engagament review'!$A:$H,2,0) -> 4 | AA17: Yes | AB17: Yes | AC17: Statutory contractor obligations not being met | AD17: 2 + Cert
A18: Surry Hills | B18: Rodney Eastment | C18: NSW | D18: Owner operator | E18: =VLOOKUP(A18,[3]ActiveFranchiseesResults465!$C:$AA,25,0) -> 11 | F18: 43617 | G18: 46905 | I18: =VLOOKUP(A18,'Scorecard summary'!A:AB,10,0) -> Yes | J18: =VLOOKUP(A18,'Revenue @ Feb 2021'!A:B,2,0) -> 98271.42 | K18: =VLOOKUP(A18,'Sales team engagament review'!A:H,2,0) -> 5 | L18: YES | M18: YES | N18: YES | O18: YES | P18: YES | Q18: NO | R18: =VLOOKUP(A18,'Franchisee Ranking'!B:H,6,0) -> 0.021276596 | S18: NO | T18: YES | U18: YES | V18: ? | W18: YES | Y18: =VLOOKUP(A:A,'Sales team engagament review'!$A:$H,2,0) -> 5 | AD18: 2 + cert
A19: Sunshine Coast | B19: Kiely Prendergast | C19: QLD | D19: Investor | E19: =VLOOKUP(A19,[3]ActiveFranchiseesResults465!$C:$AA,25,0) -> 2 | F19: 45078 | G19: 46843 | I19: yes | J19: =VLOOKUP(A19,'Revenue @ Feb 2021'!A:B,2,0) -> 147084 | K19: =VLOOKUP(A19,'Sales team engagament review'!A:H,2,0) -> 2 | L19: YES | M19: YES | N19: YES | O19: YES | P19: YES | Q19: YES | R19: =VLOOKUP(A19,'Franchisee Ranking'!B:H,6,0) -> 0 | S19: NO | T19: YES | U19: YES | V19: Yes | W19: NO | Y19: =VLOOKUP(A:A,'Sales team engagament review'!$A:$H,2,0) -> 2 | AD19: 2 + Cert
A20: Sunshine | B20: Peter Bournouisouzis | C20: VIC | D20: Owner operator | E20: =VLOOKUP(A20,[3]ActiveFranchiseesResults465!$C:$AA,25,0) -> 10 | F20: 43951 | G20: 46873 | H20: NO | I20: =VLOOKUP(A20,'Scorecard summary'!A:AB,10,0) -> NO | J20: =VLOOKUP(A20,'Revenue @ Feb 2021'!A:B,2,0) -> 51169.69 | K20: =VLOOKUP(A20,'Sales team engagament review'!A:H,2,0) -> 4 | L20: YES | M20: YES | N20: YES | O20: NO | P20: NO | Q20: YES | R20: =VLOOKUP(A20,'Franchisee Ranking'!B:G,6,0) -> 0.096774194 | S20: NO | T20: ? | U20: ? | V20: ? | W20: YES | Y20: =VLOOKUP(A:A,'Sales team engagament review'!$A:$H,2,0) -> 4 | AD20: 2 + cert
A21: Stafford | B21: Michael Mikits | C21: QLD | D21: Investor | E21: 10 | F21: 44256 | G21: 48611 | I21: =VLOOKUP(A21,'Scorecard summary'!A:AB,10,0) -> Yes | J21: =VLOOKUP(A21,'Revenue @ Feb 2021'!A:B,2,0) -> #N/A | K21: =VLOOKUP(A21,'Sales team engagament review'!A:H,2,0) -> 4 | L21: NO | M21: YES | N21: YES | O21: YES | P21: NO | Q21: YES | S21: NO | T21: ? | U21: ? | V21: ? | W21: NO | Y21: =VLOOKUP(A:A,'Sales team engagament review'!$A:$H,2,0) -> 4 | AD21: 2 + cert
A22: St Marys | B22: Jeshnil Prasad | C22: NSW | D22: Owner operator | E22: =VLOOKUP(A22,[3]ActiveFranchiseesResults465!$C:$AA,25,0) -> 11 | F22: 43866 | G22: 45693 | I22: =VLOOKUP(A22,'Scorecard summary'!A:AB,10,0) -> Yes | J22: =VLOOKUP(A22,'Revenue @ Feb 2021'!A:B,2,0) -> 124192.48 | K22: =VLOOKUP(A22,'Sales team engagament review'!A:H,2,0) -> 2 | L22: YES | M22: YES | N22: YES | O22: NO | P22: NO | Q22: YES | R22: =VLOOKUP(A22,'Franchisee Ranking'!B:G,6,0) -> 0.015384615 | S22: NO | T22: ? | U22: ? | V22: ? | W22: YES | X22: Looking to exit - postive about MPEX though | Y22: =VLOOKUP(A:A,'Sales team engagament review'!$A:$H,2,0) -> 2
A23: St Kilda Road | B23: Zhao Yang Lin | C23: VIC | D23: Owner operator | E23: =VLOOKUP(A23,[3]ActiveFranchiseesResults465!$C:$AA,25,0) -> 16 | F23: 43847 | G23: 46769 | I23: =VLOOKUP(A23,'Scorecard summary'!A:AB,10,0) -> Yes | J23: =VLOOKUP(A23,'Revenue @ Feb 2021'!A:B,2,0) -> 91613.22 | K23: =VLOOKUP(A23,'Sales team engagament review'!A:H,2,0) -> 4 | L23: YES | M23: YES | N23: YES | O23: YES | P23: YES | Q23: YES | R23: =VLOOKUP(A23,'Franchisee Ranking'!B:H,6,0) -> 0.22222222 | S23: NO | T23: ? | U23: ? | V23: Yes | W23: YES | Y23: =VLOOKUP(A:A,'Sales team engagament review'!$A:$H,2,0) -> 4 | AD23: 2 + cert
A24: Springwood | B24: Rick Zammit | C24: QLD | D24: Owner operator | E24: =VLOOKUP(A24,[3]ActiveFranchiseesResults465!$C:$AA,25,0) -> 12 | F24: 45139 | G24: 46966 | I24: =VLOOKUP(A24,'Scorecard summary'!A:AB,10,0) -> yes | J24: =VLOOKUP(A24,'Revenue @ Feb 2021'!A:B,2,0) -> 113282.92 | K24: =VLOOKUP(A24,'Sales team engagament review'!A:H,2,0) -> 5 | L24: YES | M24: YES | N24: YES | O24: YES | P24: NO | Q24: NO | R24: =VLOOKUP(A24,'Franchisee Ranking'!B:G,6,0) -> 0 | S24: NO | T24: ? | U24: ? | V24: ? | W24: YES | Y24: =VLOOKUP(A:A,'Sales team engagament review'!$A:$H,2,0) -> 5 | AD24: Still pending
A25: Spring Hill | B25: Michael Mikits | C25: QLD | D25: Investor | E25: 10 | F25: 44621 | G25: 48611 | I25: =VLOOKUP(A25,'Scorecard summary'!A:AB,10,0) -> Yes | J25: =VLOOKUP(A25,'Revenue @ Feb 2021'!A:B,2,0) -> #N/A | K25: =VLOOKUP(A25,'Sales team engagament review'!A:H,2,0) -> 4 | L25: NO | M25: YES | N25: YES | O25: YES | P25: NO | Q25: YES | S25: NO | T25: ? | U25: ? | V25: Yes | W25: NO | Y25: =VLOOKUP(A:A,'Sales team engagament review'!$A:$H,2,0) -> 4 | AD25: 2 + cert
A26: South Melbourne | B26: Dane McGreevy | C26: VIC | D26: Owner operator | E26: =VLOOKUP(A26,[3]ActiveFranchiseesResults465!$C:$AA,25,0) -> 8 | F26: 43738 | G26: 45534 | H26: Yes on exit | I26: =VLOOKUP(A26,'Scorecard summary'!A:AB,10,0) -> NO | J26: =VLOOKUP(A26,'Revenue @ Feb 2021'!A:B,2,0) -> 89442.62 | K26: =VLOOKUP(A26,'Sales team engagament review'!A:H,2,0) -> 5 | L26: YES | M26: YES | N26: YES | O26: YES | P26: NO | Q26: YES | R26: =VLOOKUP(A26,'Franchisee Ranking'!B:G,6,0) -> 0.054545455 | S26: NO | T26: ? | U26: ? | V26: ? | W26: YES | Y26: =VLOOKUP(A:A,'Sales team engagament review'!$A:$H,2,0) -> 5 | AD26: Yes no cert provided
A27: South Bank | B27: Jason Baldwin | C27: QLD | D27: Owner operator | E27: =VLOOKUP(A27,[3]ActiveFranchiseesResults465!$C:$AA,25,0) -> 13 | F27: 44774 | G27: 45870 | I27: =VLOOKUP(A27,'Scorecard summary'!A:AB,10,0) -> Yes | J27: =VLOOKUP(A27,'Revenue @ Feb 2021'!A:B,2,0) -> 175332.66 | K27: =VLOOKUP(A27,'Sales team engagament review'!A:H,2,0) -> 2 | L27: NO | M27: YES | N27: NO | O27: YES | P27: YES | Q27: YES | R27: =VLOOKUP(A27,'Franchisee Ranking'!B:G,6,0) -> 0.056818182 | S27: Yes | T27: YES | U27: yES | V27: ? | W27: YES | X27: No reply | Y27: =VLOOKUP(A:A,'Sales team engagament review'!$A:$H,2,0) -> 2 | AC27: Issue over QLD X-ray, now solved! | AD27: 2 + cert
A28: Silverwater | B28: Paul Harrison | C28: NSW | D28: Investor | E28: =VLOOKUP(A28,[3]ActiveFranchiseesResults465!$C:$AA,25,0) -> 9 | F28: 43994 | G28: 45820 | I28: =VLOOKUP(A28,'Scorecard summary'!A:AB,10,0) -> Yes | J28: =VLOOKUP(A28,'Revenue @ Feb 2021'!A:B,2,0) -> 90340.22 | K28: =VLOOKUP(A28,'Sales team engagament review'!A:H,2,0) -> 3 | L28: YES | M28: YES | N28: YES | O28: YES | P28: NO | Q28: YES | R28: =VLOOKUP(A28,'Franchisee Ranking'!B:G,6,0) -> 0.13333333 | S28: NO | T28: ? | U28: ? | V28: ? | W28: YES | X28: Been waiting on sales support…..... | Y28: =VLOOKUP(A:A,'Sales team engagament review'!$A:$H,2,0) -> 3 | AD28: 2 + cert
A29: Seven Hills | B29: Nhi (David) Lam | C29: NSW | D29: Owner operator | E29: =VLOOKUP(A29,[3]ActiveFranchiseesResults465!$C:$AA,25,0) -> 5 | F29: 44470 | G29: 48122 | I29: =VLOOKUP(A29,'Scorecard summary'!A:AB,10,0) -> Yes | J29: =VLOOKUP(A29,'Revenue @ Feb 2021'!A:B,2,0) -> 68161.14 | K29: =VLOOKUP(A29,'Sales team engagament review'!A:H,2,0) -> 3 | L29: YES | M29: NO | N29: YES | O29: NO | P29: NO | Q29: YES | R29: =VLOOKUP(A29,'Franchisee Ranking'!B:G,6,0) -> 0.1025641 | S29: NO | T29: ? | U29: ? | V29: Yes | W29: YES | Y29: =VLOOKUP(A:A,'Sales team engagament review'!$A:$H,2,0) -> 3 | AD29: 2 + cert
A30: Seaford | B30: Ian Kenna | C30: VIC | D30: Owner operator | E30: 2 | F30: 45020 | G30: 46847 | I30: =VLOOKUP(A30,'Scorecard summary'!A:AB,10,0) -> Yes | J30: =VLOOKUP(A30,'Revenue @ Feb 2021'!A:B,2,0) -> 81796.28 | K30: =VLOOKUP(A30,'Sales team engagament review'!A:H,2,0) -> 4 | L30: YES | M30: YES | N30: YES | O30: YES | P30: YES | Q30: YES | R30: =VLOOKUP(A30,'Franchisee Ranking'!B:H,6,0) -> 0.19607843 | S30: NO | T30: ? | U30: ? | V30: Yes | W30: YES | Y30: =VLOOKUP(A:A,'Sales team engagament review'!$A:$H,2,0) -> 4 | AD30: 2 + cert
A31: Scoresby | B31: David Kosky | C31: VIC | D31: Owner operator | E31: =VLOOKUP(A31,[3]ActiveFranchiseesResults465!$C:$AA,25,0) -> 15 | F31: 43692 | G31: 45519 | I31: =VLOOKUP(A31,'Scorecard summary'!A:AB,10,0) -> Yes | J31: =VLOOKUP(A31,'Revenue @ Feb 2021'!A:B,2,0) -> 96589.66 | K31: =VLOOKUP(A31,'Sales team engagament review'!A:H,2,0) -> 5 | L31: YES | M31: YES | N31: YES | O31: YES | P31: NO | Q31: YES | R31: =VLOOKUP(A31,'Franchisee Ranking'!B:G,6,0) -> 0.60465116 | S31: NO | T31: YES | U31: YES | V31: Yes | W31: NO | Y31: =VLOOKUP(A:A,'Sales team engagament review'!$A:$H,2,0) -> 5 | AD31: Representation given
A32: Salisbury | B32: James Ng | C32: QLD | D32: Owner operator | E32: =VLOOKUP(A32,[3]ActiveFranchiseesResults465!$C:$AA,25,0) -> 3 | F32: 45152 | G32: 46979 | I32: =VLOOKUP(A32,'Scorecard summary'!A:AB,10,0) -> Yes | J32: =VLOOKUP(A32,'Revenue @ Feb 2021'!A:B,2,0) -> 65584.96 | K32: =VLOOKUP(A32,'Sales team engagament review'!A:H,2,0) -> 3 | L32: YES | M32: YES | N32: YES | O32: YES | P32: YES | Q32: YES | R32: =VLOOKUP(A32,'Franchisee Ranking'!B:H,6,0) -> 0.085714286 | S32: NO | T32: YES | U32: YES | V32: ? | W32: YES | X32: No reply | Y32: =VLOOKUP(A:A,'Sales team engagament review'!$A:$H,2,0) -> 3
A33: Ryde | B33: John Chan | C33: NSW | D33: Owner operator | E33: =VLOOKUP(A33,[3]ActiveFranchiseesResults465!$C:$AA,25,0) -> 9 | F33: 43909 | G33: 46831 | I33: =VLOOKUP(A33,'Scorecard summary'!A:AB,10,0) -> yes | J33: =VLOOKUP(A33,'Revenue @ Feb 2021'!A:B,2,0) -> 212340.88 | K33: =VLOOKUP(A33,'Sales team engagament review'!A:H,2,0) -> 4 | L33: YES | M33: YES | N33: YES | O33: YES | P33: NO | Q33: YES | R33: =VLOOKUP(A33,'Franchisee Ranking'!B:G,6,0) -> 0.24210526 | S33: NO | T33: ? | U33: ? | V33: ? | W33: YES | Y33: =VLOOKUP(A:A,'Sales team engagament review'!$A:$H,2,0) -> 4 | AD33: 2 + cert
A34: Rouse Hill | B34: Animesh Castgir | C34: NSW | D34: Owner operator | E34: =VLOOKUP(A34,[3]ActiveFranchiseesResults465!$C:$AA,25,0) -> 2 | F34: 45597 | G34: 45169 | H34: NO | I34: =VLOOKUP(A34,'Scorecard summary'!A:AB,10,0) -> NO | J34: =VLOOKUP(A34,'Revenue @ Feb 2021'!A:B,2,0) -> 42093.45 | K34: =VLOOKUP(A34,'Sales team engagament review'!A:H,2,0) -> 4 | L34: YES | M34: YES | N34: YES | O34: YES | P34: NO | Q34: YES | R34: =VLOOKUP(A34,'Franchisee Ranking'!B:G,6,0) -> 0.23809524 | S34: NO | T34: ? | U34: ? | V34: Yes | W34: YES | Y34: =VLOOKUP(A:A,'Sales team engagament review'!$A:$H,2,0) -> 4 | AD34: 2 + cert
A35: Rosebery | B35: MailPlus Head Office | C35: NSW | D35: N/A | E35: N/A | F35: 44276 | G35: 47928 | I35: HEAD OFFICE | J35: =VLOOKUP(A35,'Revenue @ Feb 2021'!A:B,2,0) -> 40915.75 | K35: =VLOOKUP(A35,'Sales team engagament review'!A:H,2,0) -> 0 | L35: YES | M35: YES | N35: YES | O35: YES | P35: NO | Q35: YES | R35: =VLOOKUP(A35,'Franchisee Ranking'!B:G,6,0) -> 0.16666667 | S35: NO | T35: ? | U35: ? | V35: ? | W35: YES | Y35: =VLOOKUP(A:A,'Sales team engagament review'!$A:$H,2,0) -> 0
A36: Rocklea | B36: Matthew Smith | C36: QLD | D36: Owner operator | E36: =VLOOKUP(A36,[3]ActiveFranchiseesResults465!$C:$AA,25,0) -> 13 | F36: 44803 | G36: 46629 | I36: =VLOOKUP(A36,'Scorecard summary'!A:AB,10,0) -> Yes | J36: =VLOOKUP(A36,'Revenue @ Feb 2021'!A:B,2,0) -> 90218.85 | K36: =VLOOKUP(A36,'Sales team engagament review'!A:H,2,0) -> 5 | L36: YES | M36: YES | N36: YES | O36: YES | P36: NO | Q36: YES | R36: =VLOOKUP(A36,'Franchisee Ranking'!B:G,6,0) -> 0.17073171 | S36: NO | T36: ? | U36: ? | V36: Yes | W36: YES | Y36: =VLOOKUP(A:A,'Sales team engagament review'!$A:$H,2,0) -> 5 | AD36: 2 + cert
A37: Rockhampton (HO Operated/owned) | B37: MailPlus Head Office | C37: QLD | D37: N/A | E37: N/A | F37: N/A | G37: N/A | I37: =VLOOKUP(A37,'Scorecard summary'!A:AB,10,0) -> HEAD OFFICE | J37: =VLOOKUP(A37,'Revenue @ Feb 2021'!A:B,2,0) -> #N/A | K37: =VLOOKUP(A37,'Sales team engagament review'!A:H,2,0) -> 2 | L37: NO | M37: YES | N37: YES | O37: YES | P37: NO | Q37: NO | S37: NO | T37: ? | U37: ? | V37: ? | W37: YES | Y37: =VLOOKUP(A:A,'Sales team engagament review'!$A:$H,2,0) -> 2
A38: Riverside | B38: Gary Jakubowicz | C38: VIC | D38: Owner operator | E38: =VLOOKUP(A38,[3]ActiveFranchiseesResults465!$C:$AA,25,0) -> 8 | F38: 44572 | G38: 44562 | I38: =VLOOKUP(A38,'Scorecard summary'!A:AB,10,0) -> Yes | J38: =VLOOKUP(A38,'Revenue @ Feb 2021'!A:B,2,0) -> 76344.03 | K38: =VLOOKUP(A38,'Sales team engagament review'!A:H,2,0) -> 2 | L38: YES | M38: YES | N38: YES | O38: YES | P38: NO | Q38: YES | R38: =VLOOKUP(A38,'Franchisee Ranking'!B:G,6,0) -> 0.27906977 | S38: NO | T38: ? | U38: ? | V38: ? | W38: YES | Y38: =VLOOKUP(A:A,'Sales team engagament review'!$A:$H,2,0) -> 2 | AD38: 2 + cert
A39: Regency | B39: Ken Smith / Liz Smith | C39: SA | D39: Owner operator | E39: =VLOOKUP(A39,[3]ActiveFranchiseesResults465!$C:$AA,25,0) -> 10 | F39: 43952 | G39: 43952 | I39: =VLOOKUP(A39,'Scorecard summary'!A:AB,10,0) -> Yes | J39: =VLOOKUP(A39,'Revenue @ Feb 2021'!A:B,2,0) -> 55950.5 | K39: =VLOOKUP(A39,'Sales team engagament review'!A:H,2,0) -> 0 | L39: YES | M39: NO | N39: YES | O39: NO | P39: NO | Q39: NO | R39: =VLOOKUP(A39,'Franchisee Ranking'!B:G,6,0) -> 0 | S39: NO | T39: ? | U39: ? | V39: Yes | W39: YES | Y39: =VLOOKUP(A:A,'Sales team engagament review'!$A:$H,2,0) -> 0 | AD39: 2 + cert
A40: Pyrmont | B40: Budi Nagi | C40: NSW | D40: Investor | E40: =VLOOKUP(A40,[3]ActiveFranchiseesResults465!$C:$AA,25,0) -> 14 | F40: 44442 | G40: 46268 | I40: =VLOOKUP(A40,'Scorecard summary'!A:AB,10,0) -> Yes | J40: =VLOOKUP(A40,'Revenue @ Feb 2021'!A:B,2,0) -> 176495.12 | K40: =VLOOKUP(A40,'Sales team engagament review'!A:H,2,0) -> 4 | L40: NO | M40: YES | N40: YES | O40: YES | P40: YES | Q40: YES | R40: =VLOOKUP(A40,'Franchisee Ranking'!B:G,6,0) -> 0 | S40: NO | T40: ? | U40: ? | V40: ? | W40: YES | X40: No reply | Y40: =VLOOKUP(A:A,'Sales team engagament review'!$A:$H,2,0) -> 4 | AA40: Yes | AB40: Yes | AC40: non completion of digitization task | AD40: 2 + cert
A41: Preston | B41: Michael Debnam | C41: VIC | D41: Owner operator | E41: =VLOOKUP(A41,[3]ActiveFranchiseesResults465!$C:$AA,25,0) -> 4 | F41: 45017 | G41: 47209 | I41: =VLOOKUP(A41,'Scorecard summary'!A:AB,10,0) -> Yes | J41: =VLOOKUP(A41,'Revenue @ Feb 2021'!A:B,2,0) -> 82793.06 | K41: =VLOOKUP(A41,'Sales team engagament review'!A:H,2,0) -> 5 | L41: YES | M41: YES | N41: YES | O41: YES | P41: NO | Q41: YES | R41: =VLOOKUP(A41,'Franchisee Ranking'!B:G,6,0) -> 0.081632653 | S41: NO | T41: ? | U41: ? | V41: ? | W41: YES | Y41: =VLOOKUP(A:A,'Sales team engagament review'!$A:$H,2,0) -> 5 | AD41: Yes no cert provided
A42: Port Melbourne Port Melbourne | B42: Jonathan Mawer | C42: VIC | D42: Investor | E42: =VLOOKUP(A42,[3]ActiveFranchiseesResults465!$C:$AA,25,0) -> 8 | F42: 43707 | G42: 45534 | I42: =VLOOKUP(A42,'Scorecard summary'!A:AB,10,0) -> Yes | J42: =VLOOKUP(A42,'Revenue @ Feb 2021'!A:B,2,0) -> 248966.93 | K42: =VLOOKUP(A42,'Sales team engagament review'!A:H,2,0) -> 5 | L42: NO | M42: YES | N42: YES | O42: NO | P42: NO | Q42: YES | R42: =VLOOKUP(A42,'Franchisee Ranking'!B:G,6,0) -> 0.22807018 | S42: NO | T42: YES | U42: YES | V42: ? | W42: YES | Y42: =VLOOKUP(A:A,'Sales team engagament review'!$A:$H,2,0) -> 5
A43: Perth CBD | B43: Jobin Mathew Parthickal | C43: WA | D43: Owner operator | E43: =VLOOKUP(A43,[3]ActiveFranchiseesResults465!$C:$AA,25,0) -> 3 | F43: 43709 | G43: 47362 | I43: =VLOOKUP(A43,'Scorecard summary'!A:AB,10,0) -> Yes | J43: =VLOOKUP(A43,'Revenue @ Feb 2021'!A:B,2,0) -> 48888.7 | K43: =VLOOKUP(A43,'Sales team engagament review'!A:H,2,0) -> 3 | L43: NO | M43: YES | N43: YES | O43: YES | P43: NO | Q43: NO | R43: =VLOOKUP(A43,'Franchisee Ranking'!B:G,6,0) -> 0 | S43: NO | T43: ? | U43: ? | V43: Yes | W43: YES | X43: Will allocate to customers ASAP | Y43: =VLOOKUP(A:A,'Sales team engagament review'!$A:$H,2,0) -> 3 | AB43: Yes | AC43: Not servicing customer demand during Covid
A44: Penrith | B44: Robert Marlow | C44: NSW | D44: Owner operator | E44: =VLOOKUP(A44,[3]ActiveFranchiseesResults465!$C:$AA,25,0) -> 7 | F44: 43891 | G44: 45717 | H44: NO | I44: =VLOOKUP(A44,'Scorecard summary'!A:AB,10,0) -> NO | J44: =VLOOKUP(A44,'Revenue @ Feb 2021'!A:B,2,0) -> 95429.23 | K44: =VLOOKUP(A44,'Sales team engagament review'!A:H,2,0) -> 3 | L44: YES | M44: YES | N44: YES | O44: YES | P44: YES | Q44: YES | R44: =VLOOKUP(A44,'Franchisee Ranking'!B:G,6,0) -> 0.013513514 | S44: NO | T44: YES | U44: YES | V44: ? | W44: YES | X44: Done all the right things but can't get usage | Y44: =VLOOKUP(A:A,'Sales team engagament review'!$A:$H,2,0) -> 3 | AD44: 1
A45: Peninsula | B45: Roger Turner | C45: NSW | D45: Owner operator | E45: =VLOOKUP(A45,[3]ActiveFranchiseesResults465!$C:$AA,25,0) -> 13 | F45: 43647 | G45: 46935 | I45: =VLOOKUP(A45,'Scorecard summary'!A:AB,10,0) -> Yes | J45: =VLOOKUP(A45,'Revenue @ Feb 2021'!A:B,2,0) -> 29012.58 | K45: =VLOOKUP(A45,'Sales team engagament review'!A:H,2,0) -> 3 | L45: YES | M45: YES | N45: YES | O45: YES | P45: NO | Q45: YES | R45: =VLOOKUP(A45,'Franchisee Ranking'!B:G,6,0) -> 0.27272727 | S45: NO | T45: YES | U45: YES | V45: ? | W45: YES | Y45: =VLOOKUP(A:A,'Sales team engagament review'!$A:$H,2,0) -> 3 | AD45: 2 + cert
A46: Parramatta | B46: Simon Hoatson | C46: NSW | D46: Investor | E46: =VLOOKUP(A46,[3]ActiveFranchiseesResults465!$C:$AA,25,0) -> 18 | F46: 43738 | G46: 47026 | I46: =VLOOKUP(A46,'Scorecard summary'!A:AB,10,0) -> Yes | J46: =VLOOKUP(A46,'Revenue @ Feb 2021'!A:B,2,0) -> 271059.75 | K46: =VLOOKUP(A46,'Sales team engagament review'!A:H,2,0) -> 5 | L46: YES | M46: YES | N46: YES | O46: YES | P46: YES | Q46: YES | R46: =VLOOKUP(A46,'Franchisee Ranking'!B:H,6,0) -> 0.21176471 | S46: NO | T46: ? | U46: ? | V46: ? | W46: YES | Y46: =VLOOKUP(A:A,'Sales team engagament review'!$A:$H,2,0) -> 5 | AD46: 2 + Cert
A47: Osborne Park | B47: Nick Fahie | C47: WA | D47: Owner operator | E47: =VLOOKUP(A47,[3]ActiveFranchiseesResults465!$C:$AA,25,0) -> 11 | F47: 43800 | G47: 45627 | I47: =VLOOKUP(A47,'Scorecard summary'!A:AB,10,0) -> Yes | J47: =VLOOKUP(A47,'Revenue @ Feb 2021'!A:B,2,0) -> 141260.31 | K47: =VLOOKUP(A47,'Sales team engagament review'!A:H,2,0) -> 5 | L47: YES | M47: YES | N47: YES | O47: YES | P47: YES | Q47: YES | R47: =VLOOKUP(A47,'Franchisee Ranking'!B:H,6,0) -> 0 | S47: NO | T47: ? | U47: ? | V47: ? | W47: YES | Y47: =VLOOKUP(A:A,'Sales team engagament review'!$A:$H,2,0) -> 5 | AD47: 2 + cert
A48: Northern Beaches | B48: Roger Turner | C48: NSW | D48: Owner operator | E48: =VLOOKUP(A48,[3]ActiveFranchiseesResults465!$C:$AA,25,0) -> 14 | F48: 43647 | G48: 46935 | I48: No | J48: =VLOOKUP(A48,'Revenue @ Feb 2021'!A:B,2,0) -> 132551.44 | K48: =VLOOKUP(A48,'Sales team engagament review'!A:H,2,0) -> 3 | L48: YES | M48: YES | N48: YES | O48: YES | P48: YES | Q48: YES | R48: =VLOOKUP(A48,'Franchisee Ranking'!B:H,6,0) -> 0.35849057 | S48: NO | T48: YES | U48: YES | V48: Yes | W48: YES | Y48: =VLOOKUP(A:A,'Sales team engagament review'!$A:$H,2,0) -> 3 | AD48: 2 + cert
A49: North Sydney | B49: Jason Yang | C49: NSW | D49: Investor | E49: 2 | F49: 43994 | G49: 45820 | I49: =VLOOKUP(A49,'Scorecard summary'!A:AB,10,0) -> Yes | J49: =VLOOKUP(A49,'Revenue @ Feb 2021'!A:B,2,0) -> 261669.46 | K49: =VLOOKUP(A49,'Sales team engagament review'!A:H,2,0) -> 3 | L49: NO | M49: YES | N49: YES | O49: YES | P49: NO | Q49: YES | R49: =VLOOKUP(A49,'Franchisee Ranking'!B:G,6,0) -> 0.045045045 | S49: Yes | T49: ? | U49: ? | V49: Yes | W49: YES | X49: Now that LPO margins have been slashed he will embrace | Y49: =VLOOKUP(A:A,'Sales team engagament review'!$A:$H,2,0) -> 3 | AD49: 2 + cert
A50: North Melbourne | B50: Peter Rafferty | C50: VIC | D50: Owner operator | E50: =VLOOKUP(A50,[3]ActiveFranchiseesResults465!$C:$AA,25,0) -> 1 | F50: 43922 | G50: 45748 | I50: =VLOOKUP(A50,'Scorecard summary'!A:AB,10,0) -> Yes | J50: =VLOOKUP(A50,'Revenue @ Feb 2021'!A:B,2,0) -> 108964.22 | K50: =VLOOKUP(A50,'Sales team engagament review'!A:H,2,0) -> 5 | L50: YES | M50: YES | N50: YES | O50: YES | P50: NO | Q50: YES | R50: =VLOOKUP(A50,'Franchisee Ranking'!B:G,6,0) -> 0.16 | S50: NO | T50: ? | U50: ? | V50: Yes | W50: YES | Y50: =VLOOKUP(A:A,'Sales team engagament review'!$A:$H,2,0) -> 5 | AD50: 1 + cert
A51: North Lakes | B51: Mohinder | C51: QLD | D51: Owner operator | E51: =VLOOKUP(A51,[3]ActiveFranchiseesResults465!$C:$AA,25,0) -> 1 | F51: 43770 | G51: 49249 | I51: =VLOOKUP(A51,'Scorecard summary'!A:AB,10,0) -> Yes | J51: =VLOOKUP(A51,'Revenue @ Feb 2021'!A:B,2,0) -> 164396.2 | K51: =VLOOKUP(A51,'Sales team engagament review'!A:H,2,0) -> 4 | L51: NO | M51: YES | N51: YES | O51: YES | P51: YES | Q51: YES | R51: =VLOOKUP(A51,'Franchisee Ranking'!B:H,6,0) -> 0.011494253 | S51: NO | T51: ? | U51: ? | V51: Yes | W51: YES | Y51: =VLOOKUP(A:A,'Sales team engagament review'!$A:$H,2,0) -> 4
A52: Newcastle | B52: Craig Goodsir | C52: NSW | D52: Owner operator | E52: =VLOOKUP(A52,[3]ActiveFranchiseesResults465!$C:$AA,25,0) -> 7 | F52: 43830 | G52: 47483 | I52: =VLOOKUP(A52,'Scorecard summary'!A:AB,10,0) -> yes | J52: =VLOOKUP(A52,'Revenue @ Feb 2021'!A:B,2,0) -> 273830.42 | K52: =VLOOKUP(A52,'Sales team engagament review'!A:H,2,0) -> 3 | L52: NO | M52: NO | N52: YES | O52: NO | P52: NO | Q52: YES | R52: =VLOOKUP(A52,'Franchisee Ranking'!B:G,6,0) -> 0.0097087379 | S52: NO | T52: ? | U52: ? | V52: Yes | W52: YES | X52: Not postive on MPEX may have a side arrangment we are not aware of. | Y52: =VLOOKUP(A:A,'Sales team engagament review'!$A:$H,2,0) -> 3 | AA52: Drafted but not served | AB52: Yes | AC52: Lack of engagment on MPEX rollout | AD52: 2 + cert
A53: Nerang | B53: =B55 -> Jason Knight | C53: =C55 -> VIC | D53: =D55 -> Owner operator | E53: =E56 -> 15 | F53: 46082 | G53: Ultimate | I53: Yes | K53: =VLOOKUP(A53,'Sales team engagament review'!A:H,2,0) -> 4 | L53: NO | M53: YES | N53: YES | O53: YES | P53: NO | Q53: YES | AD53: 1 + cert
A54: Murarrie | B54: Colin Paynter | C54: QLD | D54: Owner operator | E54: 3 | F54: 43844 | G54: 45671 | I54: =VLOOKUP(A54,'Scorecard summary'!A:AB,10,0) -> yes | J54: =VLOOKUP(A54,'Revenue @ Feb 2021'!A:B,2,0) -> 88605.04 | K54: =VLOOKUP(A54,'Sales team engagament review'!A:H,2,0) -> 4 | L54: YES | M54: YES | N54: YES | O54: YES | P54: NO | Q54: YES | R54: =VLOOKUP(A54,'Franchisee Ranking'!B:G,6,0) -> 0.24390244 | S54: NO | T54: ? | U54: ? | V54: ? | W54: YES | X54: Wants a face to face with CB & GH | Y54: =VLOOKUP(A:A,'Sales team engagament review'!$A:$H,2,0) -> 4 | AD54: 1 waiting on cert
A55: Mulgrave | B55: Jason Knight | C55: VIC | D55: Owner operator | E55: =VLOOKUP(A55,[3]ActiveFranchiseesResults465!$C:$AA,25,0) -> 7 | F55: 44166 | G55: 44166 | I55: =VLOOKUP(A55,'Scorecard summary'!A:AB,10,0) -> Yes | J55: =VLOOKUP(A55,'Revenue @ Feb 2021'!A:B,2,0) -> 86459.09 | K55: =VLOOKUP(A55,'Sales team engagament review'!A:H,2,0) -> 5 | L55: YES | M55: YES | N55: YES | O55: YES | P55: NO | Q55: YES | R55: =VLOOKUP(A55,'Franchisee Ranking'!B:G,6,0) -> 0.46 | S55: NO | T55: YES | U55: YES | V55: ? | W55: YES | Y55: =VLOOKUP(A:A,'Sales team engagament review'!$A:$H,2,0) -> 5 | AD55: 1 + cert
A56: Mount Waverley | B56: Erik Kusnadi | C56: VIC | D56: Owner operator | E56: =VLOOKUP(A56,[3]ActiveFranchiseesResults465!$C:$AA,25,0) -> 15 | F56: 43897 | G56: 45723 | I56: =VLOOKUP(A56,'Scorecard summary'!A:AB,10,0) -> Yes | J56: =VLOOKUP(A56,'Revenue @ Feb 2021'!A:B,2,0) -> 43450.17 | K56: =VLOOKUP(A56,'Sales team engagament review'!A:H,2,0) -> 4 | L56: YES | M56: YES | N56: YES | O56: YES | P56: YES | Q56: NO | R56: =VLOOKUP(A56,'Franchisee Ranking'!B:H,6,0) -> 0.40909091 | S56: NO | T56: ? | U56: ? | V56: ? | W56: YES | Y56: =VLOOKUP(A:A,'Sales team engagament review'!$A:$H,2,0) -> 4 | AD56: 2 + cert
A57: Mount Gravatt | B57: Rick Zammit | C57: QLD | D57: Owner operator | E57: =VLOOKUP(A57,[3]ActiveFranchiseesResults465!$C:$AA,25,0) -> 14 | F57: 45139 | G57: 46977 | I57: =VLOOKUP(A57,'Scorecard summary'!A:AB,10,0) -> yes | J57: =VLOOKUP(A57,'Revenue @ Feb 2021'!A:B,2,0) -> 139063.89 | K57: =VLOOKUP(A57,'Sales team engagament review'!A:H,2,0) -> 5 | L57: YES | M57: YES | N57: YES | O57: YES | P57: NO | Q57: NO | R57: =VLOOKUP(A57,'Franchisee Ranking'!B:G,6,0) -> 0.15151515 | S57: NO | T57: ? | U57: ? | V57: Yes | W57: NO | Y57: =VLOOKUP(A:A,'Sales team engagament review'!$A:$H,2,0) -> 5 | AD57: 1 + cert
A58: Morningside | B58: Greg Hart | C58: QLD | D58: Investor | E58: =VLOOKUP(A58,[3]ActiveFranchiseesResults465!$C:$AA,25,0) -> 3 | F58: 43783 | G58: 50358 | I58: yes | J58: =VLOOKUP(A58,'Revenue @ Feb 2021'!A:B,2,0) -> 96883.89 | K58: =VLOOKUP(A58,'Sales team engagament review'!A:H,2,0) -> 4 | L58: YES | M58: YES | N58: YES | O58: YES | P58: YES | Q58: YES | R58: =VLOOKUP(A58,'Franchisee Ranking'!B:H,6,0) -> 0.04 | S58: NO | T58: ? | U58: ? | V58: ? | W58: YES | Y58: =VLOOKUP(A:A,'Sales team engagament review'!$A:$H,2,0) -> 4
A59: Moorebank | B59: Giuseppe Filippello | C59: NSW | D59: Owner operator | E59: =VLOOKUP(A59,[3]ActiveFranchiseesResults465!$C:$AA,25,0) -> 3 | F59: 43693 | G59: 45520 | I59: =VLOOKUP(A59,'Scorecard summary'!A:AB,10,0) -> yes | J59: =VLOOKUP(A59,'Revenue @ Feb 2021'!A:B,2,0) -> 122287.92 | K59: =VLOOKUP(A59,'Sales team engagament review'!A:H,2,0) -> 4 | L59: YES | M59: YES | N59: YES | O59: YES | P59: YES | Q59: YES | R59: =VLOOKUP(A59,'Franchisee Ranking'!B:H,6,0) -> 0.22222222 | S59: NO | T59: ? | U59: ? | V59: ? | W59: YES | Y59: =VLOOKUP(A:A,'Sales team engagament review'!$A:$H,2,0) -> 4 | AD59: Confirmed but no cert
A60: Moorabbin | B60: David Hicks | C60: VIC | D60: Owner operator | E60: =VLOOKUP(A60,[3]ActiveFranchiseesResults465!$C:$AA,25,0) -> 6 | F60: 43889 | G60: 46081 | I60: =VLOOKUP(A60,'Scorecard summary'!A:AB,10,0) -> Yes | J60: =VLOOKUP(A60,'Revenue @ Feb 2021'!A:B,2,0) -> 80744.45 | K60: =VLOOKUP(A60,'Sales team engagament review'!A:H,2,0) -> 5 | L60: YES | M60: YES | N60: YES | O60: NO | P60: NO | Q60: YES | R60: =VLOOKUP(A60,'Franchisee Ranking'!B:G,6,0) -> 0.34883721 | S60: NO | T60: YES | U60: YES | V60: Yes | W60: YES | Y60: =VLOOKUP(A:A,'Sales team engagament review'!$A:$H,2,0) -> 5 | AD60: 2 + cert
A61: Milperra | B61: Sam Li | C61: NSW | D61: Owner operator | E61: =VLOOKUP(A61,[3]ActiveFranchiseesResults465!$C:$AA,25,0) -> 8 | F61: 44835 | G61: 47026 | H61: Yes | I61: =VLOOKUP(A61,'Scorecard summary'!A:AB,10,0) -> NO | J61: =VLOOKUP(A61,'Revenue @ Feb 2021'!A:B,2,0) -> 127034.64 | K61: =VLOOKUP(A61,'Sales team engagament review'!A:H,2,0) -> 4 | L61: YES | M61: YES | N61: YES | O61: YES | P61: NO | Q61: YES | R61: =VLOOKUP(A61,'Franchisee Ranking'!B:G,6,0) -> 0.13043478 | S61: NO | T61: ? | U61: ? | V61: Yes | W61: YES | Y61: =VLOOKUP(A:A,'Sales team engagament review'!$A:$H,2,0) -> 4 | AD61: 2 + cert
A62: Melbourne CBD | B62: Alistair Wright | C62: VIC | D62: Investor | E62: =VLOOKUP(A62,[3]ActiveFranchiseesResults465!$C:$AA,25,0) -> 6 | F62: 43709 | G62: 46631 | I62: =VLOOKUP(A62,'Scorecard summary'!A:AB,10,0) -> Yes | J62: =VLOOKUP(A62,'Revenue @ Feb 2021'!A:B,2,0) -> 546410.96 | K62: =VLOOKUP(A62,'Sales team engagament review'!A:H,2,0) -> 5 | L62: YES | M62: YES | N62: YES | O62: YES | P62: NO | Q62: YES | R62: =VLOOKUP(A62,'Franchisee Ranking'!B:G,6,0) -> 0.14375 | S62: NO | T62: ? | U62: ? | V62: Yes | W62: YES | Y62: =VLOOKUP(A:A,'Sales team engagament review'!$A:$H,2,0) -> 5
A63: Mascot | B63: Rohit Hegde | C63: NSW | D63: Owner operator | E63: =VLOOKUP(A63,[3]ActiveFranchiseesResults465!$C:$AA,25,0) -> 17 | F63: 44276 | G63: 47928 | H63: Yes | I63: =VLOOKUP(A63,'Scorecard summary'!A:AB,10,0) -> NO | J63: =VLOOKUP(A63,'Revenue @ Feb 2021'!A:B,2,0) -> 120118.77 | K63: =VLOOKUP(A63,'Sales team engagament review'!A:H,2,0) -> 1 | L63: YES | M63: YES | N63: YES | O63: YES | P63: NO | Q63: YES | R63: =VLOOKUP(A63,'Franchisee Ranking'!B:G,6,0) -> 0.27118644 | S63: Yes | T63: YES | U63: YES | V63: ? | W63: NO | Y63: =VLOOKUP(A:A,'Sales team engagament review'!$A:$H,2,0) -> 1
A64: Macquarie Park | B64: Sleiman Aoukar | C64: NSW | D64: Owner operator | E64: =VLOOKUP(A64,[3]ActiveFranchiseesResults465!$C:$AA,25,0) -> 16 | F64: 43862 | G64: 45689 | I64: =VLOOKUP(A64,'Scorecard summary'!A:AB,10,0) -> yes | J64: =VLOOKUP(A64,'Revenue @ Feb 2021'!A:B,2,0) -> 167098.57 | K64: =VLOOKUP(A64,'Sales team engagament review'!A:H,2,0) -> 4 | L64: YES | M64: YES | N64: YES | O64: YES | P64: YES | Q64: YES | R64: =VLOOKUP(A64,'Franchisee Ranking'!B:H,6,0) -> 0.34285714 | S64: NO | T64: ? | U64: ? | V64: Yes | W64: YES | Y64: =VLOOKUP(A:A,'Sales team engagament review'!$A:$H,2,0) -> 4 | AD64: 2 + cert
A65: Mackay (HO Owned) | B65: MailPlus Head Office | C65: QLD | D65: N/A | E65: N/A | F65: N/A | G65: N/A | I65: =VLOOKUP(A65,'Scorecard summary'!A:AB,10,0) -> HEAD OFFICE | J65: =VLOOKUP(A65,'Revenue @ Feb 2021'!A:B,2,0) -> #N/A | K65: =VLOOKUP(A65,'Sales team engagament review'!A:H,2,0) -> 2 | L65: YES | M65: YES | N65: YES | O65: YES | P65: NO | Q65: NO | S65: NO | T65: ? | U65: ? | V65: ? | W65: NO | Y65: =VLOOKUP(A:A,'Sales team engagament review'!$A:$H,2,0) -> 2
A66: Liverpool | B66: Abbas Abou Abdallah | C66: NSW | D66: Owner operator | E66: =VLOOKUP(A66,[3]ActiveFranchiseesResults465!$C:$AA,25,0) -> 16 | F66: 43693 | G66: 45520 | I66: =VLOOKUP(A66,'Scorecard summary'!A:AB,10,0) -> Yes | J66: =VLOOKUP(A66,'Revenue @ Feb 2021'!A:B,2,0) -> 72390.06 | K66: =VLOOKUP(A66,'Sales team engagament review'!A:H,2,0) -> 3 | L66: YES | M66: YES | N66: YES | O66: YES | P66: NO | Q66: YES | R66: =VLOOKUP(A66,'Franchisee Ranking'!B:G,6,0) -> 0.3125 | S66: NO | T66: YES | U66: YES | V66: ? | W66: YES | X66: 75% of customers have MPEX - usage still low | Y66: =VLOOKUP(A:A,'Sales team engagament review'!$A:$H,2,0) -> 3 | AD66: 2 + cert
A67: Launceston | B67: Brett Young | C67: TAS | D67: Owner operator | E67: =VLOOKUP(A67,[3]ActiveFranchiseesResults465!$C:$AA,25,0) -> 13 | G67: 44838 | I67: =VLOOKUP(A67,'Scorecard summary'!A:AB,10,0) -> Yes | J67: =VLOOKUP(A67,'Revenue @ Feb 2021'!A:B,2,0) -> 52617.36 | K67: =VLOOKUP(A67,'Sales team engagament review'!A:H,2,0) -> 0 | L67: YES | M67: YES | N67: YES | O67: YES | P67: YES | Q67: YES | R67: =VLOOKUP(A67,'Franchisee Ranking'!B:H,6,0) -> 0.058823529 | S67: NO | T67: ? | U67: ? | V67: ? | W67: YES | Y67: =VLOOKUP(A:A,'Sales team engagament review'!$A:$H,2,0) -> 0
A68: Lane Lane | B68: Philip Lane | C68: QLD | D68: Owner operator | E68: =VLOOKUP(A68,[3]ActiveFranchiseesResults465!$C:$AA,25,0) -> 16 | F68: 44865 | G68: 45961 | I68: =VLOOKUP(A68,'Scorecard summary'!A:AB,10,0) -> yes | J68: =VLOOKUP(A68,'Revenue @ Feb 2021'!A:B,2,0) -> 194972 | K68: =VLOOKUP(A68,'Sales team engagament review'!A:H,2,0) -> 5 | L68: YES | M68: YES | N68: NO | O68: YES | P68: YES | Q68: YES | R68: =VLOOKUP(A68,'Franchisee Ranking'!B:G,6,0) -> 0.02739726 | S68: NO | T68: ? | U68: ? | V68: ? | W68: YES | X68: Very difficult to manage - knocked back multiple DX points | Y68: =VLOOKUP(A:A,'Sales team engagament review'!$A:$H,2,0) -> 5 | AD68: 2 + cert
A69: Lane Cove | B69: Jason Yang | C69: NSW | D69: Investor | E69: =VLOOKUP(A69,[3]ActiveFranchiseesResults465!$C:$AA,25,0) -> 3 | F69: 43786 | G69: 45613 | I69: =VLOOKUP(A69,'Scorecard summary'!A:AB,10,0) -> Yes | J69: =VLOOKUP(A69,'Revenue @ Feb 2021'!A:B,2,0) -> 151223.83 | K69: =VLOOKUP(A69,'Sales team engagament review'!A:H,2,0) -> 4 | L69: NO | M69: YES | N69: NO | O69: YES | P69: NO | Q69: YES | R69: =VLOOKUP(A69,'Franchisee Ranking'!B:G,6,0) -> 0.051948052 | S69: Yes | T69: ? | U69: ? | V69: Yes | W69: NO | X69: Now that LPO margins have been slashed he will embrace | Y69: =VLOOKUP(A:A,'Sales team engagament review'!$A:$H,2,0) -> 4 | AD69: 2 + Cert
A70: Lalor | B70: Chris Sarbin | C70: VIC | D70: Owner operator | E70: =VLOOKUP(A70,[3]ActiveFranchiseesResults465!$C:$AA,25,0) -> 13 | F70: 44743 | G70: 46569 | I70: =VLOOKUP(A70,'Scorecard summary'!A:AB,10,0) -> Yes | J70: =VLOOKUP(A70,'Revenue @ Feb 2021'!A:B,2,0) -> 92733.17 | K70: =VLOOKUP(A70,'Sales team engagament review'!A:H,2,0) -> 4 | L70: YES | M70: YES | N70: YES | O70: YES | P70: NO | Q70: YES | R70: =VLOOKUP(A70,'Franchisee Ranking'!B:G,6,0) -> 0.18367347 | S70: NO | T70: ? | U70: ? | V70: ? | W70: NO | Y70: =VLOOKUP(A:A,'Sales team engagament review'!$A:$H,2,0) -> 4 | AC70: Lack of engagement re Sendel pilot - Having issues with personell at the bundoora AP centre | AD70: Confirmed still waiting on certs
A71: Kewdale | B71: Roque Bautista | C71: WA | D71: Owner operator | E71: =VLOOKUP(A71,[3]ActiveFranchiseesResults465!$C:$AA,25,0) -> 3 | F71: 44621 | G71: 48274 | I71: =VLOOKUP(A71,'Scorecard summary'!A:AB,10,0) -> Yes | J71: =VLOOKUP(A71,'Revenue @ Feb 2021'!A:B,2,0) -> 119163.39 | K71: =VLOOKUP(A71,'Sales team engagament review'!A:H,2,0) -> 0 | L71: YES | M71: YES | N71: YES | O71: YES | P71: NO | Q71: YES | R71: =VLOOKUP(A71,'Franchisee Ranking'!B:G,6,0) -> 0.1372549 | S71: NO | T71: ? | U71: ? | V71: ? | W71: YES | Y71: =VLOOKUP(A:A,'Sales team engagament review'!$A:$H,2,0) -> 0 | AD71: 2 + cert
A72: Jones Jones | B72: Ellen Jones / Allan Jones | C72: QLD | D72: Owner operator | E72: =VLOOKUP(A72,[3]ActiveFranchiseesResults465!$C:$AA,25,0) -> 16 | F72: 43830 | G72: 47118 | I72: =VLOOKUP(A72,'Scorecard summary'!A:AB,10,0) -> Yes | J72: =VLOOKUP(A72,'Revenue @ Feb 2021'!A:B,2,0) -> 148284.51 | K72: =VLOOKUP(A72,'Sales team engagament review'!A:H,2,0) -> 2 | L72: YES | M72: NO | N72: YES | O72: YES | P72: NO | Q72: YES | R72: =VLOOKUP(A72,'Franchisee Ranking'!B:G,6,0) -> 0.0125 | S72: NO | T72: ? | U72: ? | V72: ? | W72: YES | X72: Sales rep never called back to arrange customer call down | Y72: =VLOOKUP(A:A,'Sales team engagament review'!$A:$H,2,0) -> 2
A73: Ipswich (HO Owned) | B73: MailPlus Head Office | C73: QLD | D73: N/A | E73: N/A | F73: N/A | G73: N/A | I73: =VLOOKUP(A73,'Scorecard summary'!A:AB,10,0) -> HEAD OFFICE | J73: =VLOOKUP(A73,'Revenue @ Feb 2021'!A:B,2,0) -> #N/A | K73: =VLOOKUP(A73,'Sales team engagament review'!A:H,2,0) -> 3 | L73: YES | M73: YES | N73: YES | O73: YES | P73: NO | Q73: NO | S73: NO | T73: ? | U73: ? | V73: ? | W73: NO | Y73: =VLOOKUP(A:A,'Sales team engagament review'!$A:$H,2,0) -> 3
A74: Illawarra | B74: Mathew Barnes | C74: NSW | D74: Owner operator | E74: =VLOOKUP(A74,[3]ActiveFranchiseesResults465!$C:$AA,25,0) -> 1 | F74: 45137 | G74: 45137 | I74: =VLOOKUP(A74,'Scorecard summary'!A:AB,10,0) -> Yes | J74: =VLOOKUP(A74,'Revenue @ Feb 2021'!A:B,2,0) -> 118544.82 | K74: =VLOOKUP(A74,'Sales team engagament review'!A:H,2,0) -> 5 | L74: NO | M74: NO | N74: YES | O74: YES | P74: YES | Q74: YES | R74: =VLOOKUP(A74,'Franchisee Ranking'!B:H,6,0) -> 0.071428571 | S74: NO | T74: YES | U74: YES | V74: Yes | W74: YES | Y74: =VLOOKUP(A:A,'Sales team engagament review'!$A:$H,2,0) -> 5 | AD74: 2 + cert
A75: Hunter Valley | B75: Jason Doricott | C75: NSW | D75: Owner operator | E75: =VLOOKUP(A75,[3]ActiveFranchiseesResults465!$C:$AA,25,0) -> 8 | F75: 42978 | G75: 44786 | H75: NO | I75: =VLOOKUP(A75,'Scorecard summary'!A:AB,10,0) -> NO | J75: =VLOOKUP(A75,'Revenue @ Feb 2021'!A:B,2,0) -> 70946.17 | K75: =VLOOKUP(A75,'Sales team engagament review'!A:H,2,0) -> 0 | L75: YES | M75: NO | N75: NO | O75: YES | P75: YES | Q75: YES | R75: =VLOOKUP(A75,'Franchisee Ranking'!B:G,6,0) -> 0.021276596 | S75: NO | T75: ? | U75: ? | V75: ? | W75: NO | X75: Positive response but does not have many product purchasing customers | Y75: =VLOOKUP(A:A,'Sales team engagament review'!$A:$H,2,0) -> 0 | AD75: 2 + cert
A76: Hoppers Crossing | B76: Meral Murgoski | C76: VIC | D76: Owner operator | E76: =VLOOKUP(A76,[3]ActiveFranchiseesResults465!$C:$AA,25,0) -> 5 | F76: 44013 | G76: 45839 | I76: =VLOOKUP(A76,'Scorecard summary'!A:AB,10,0) -> Yes | J76: =VLOOKUP(A76,'Revenue @ Feb 2021'!A:B,2,0) -> 60110.11 | K76: =VLOOKUP(A76,'Sales team engagament review'!A:H,2,0) -> 4 | L76: YES | M76: YES | N76: YES | O76: YES | P76: NO | Q76: YES | R76: =VLOOKUP(A76,'Franchisee Ranking'!B:G,6,0) -> 0.2195122 | S76: NO | T76: ? | U76: ? | V76: ? | W76: YES | Y76: =VLOOKUP(A:A,'Sales team engagament review'!$A:$H,2,0) -> 4 | AD76: 2 + cert
A77: Homebush | B77: Ken Sealey | C77: NSW | D77: Investor | E77: =VLOOKUP(A77,[3]ActiveFranchiseesResults465!$C:$AA,25,0) -> 13 | F77: 43844 | G77: 45671 | I77: =VLOOKUP(A77,'Scorecard summary'!A:AB,10,0) -> Yes | J77: =VLOOKUP(A77,'Revenue @ Feb 2021'!A:B,2,0) -> 152472.22 | K77: =VLOOKUP(A77,'Sales team engagament review'!A:H,2,0) -> 4 | L77: YES | M77: YES | N77: YES | O77: YES | P77: YES | Q77: YES | R77: =VLOOKUP(A77,'Franchisee Ranking'!B:G,6,0) -> 0.016666667 | S77: NO | T77: YES | U77: YES | V77: ? | W77: YES | X77: Didn't reply - seems very disengaged since selling his other franchises | Y77: =VLOOKUP(A:A,'Sales team engagament review'!$A:$H,2,0) -> 4
A78: Hobart | B78: Greg Wells | C78: TAS | D78: Owner operator | E78: =VLOOKUP(A78,[3]ActiveFranchiseesResults465!$C:$AA,25,0) -> 13 | G78: 44774 | I78: =VLOOKUP(A78,'Scorecard summary'!A:AB,10,0) -> Yes | J78: =VLOOKUP(A78,'Revenue @ Feb 2021'!A:B,2,0) -> 67417.5 | K78: =VLOOKUP(A78,'Sales team engagament review'!A:H,2,0) -> 0 | L78: NO | M78: NO | N78: YES | O78: YES | P78: NO | Q78: YES | R78: =VLOOKUP(A78,'Franchisee Ranking'!B:G,6,0) -> 0.024390244 | S78: NO | T78: ? | U78: ? | V78: ? | W78: NO | X78: Had van issues which delayed roll out but appears to be positive | Y78: =VLOOKUP(A:A,'Sales team engagament review'!$A:$H,2,0) -> 0 | AD78: 1 waiting on cert
A79: Hemmant | B79: Greg Hart | C79: QLD | D79: Investor | E79: =VLOOKUP(A79,[3]ActiveFranchiseesResults465!$C:$AA,25,0) -> 2 | F79: 45200 | G79: 48853 | I79: yes | J79: =VLOOKUP(A79,'Revenue @ Feb 2021'!A:B,2,0) -> 78308.37 | K79: =VLOOKUP(A79,'Sales team engagament review'!A:H,2,0) -> 4 | L79: YES | M79: YES | N79: YES | O79: YES | P79: YES | Q79: YES | R79: =VLOOKUP(A79,'Franchisee Ranking'!B:H,6,0) -> 0.057142857 | S79: NO | T79: ? | U79: ? | V79: Yes | W79: YES | Y79: =VLOOKUP(A:A,'Sales team engagament review'!$A:$H,2,0) -> 4
A80: Hawthorn | B80: Jeff Hall | C80: VIC | D80: Owner operator | E80: =VLOOKUP(A80,[3]ActiveFranchiseesResults465!$C:$AA,25,0) -> 6 | F80: 45018 | G80: 45018 | I80: =VLOOKUP(A80,'Scorecard summary'!A:AB,10,0) -> Yes | J80: =VLOOKUP(A80,'Revenue @ Feb 2021'!A:B,2,0) -> 59941.75 | K80: =VLOOKUP(A80,'Sales team engagament review'!A:H,2,0) -> 5 | L80: YES | M80: YES | N80: YES | O80: NO | P80: NO | Q80: YES | R80: =VLOOKUP(A80,'Franchisee Ranking'!B:G,6,0) -> 0.4047619 | S80: NO | T80: ? | U80: ? | V80: ? | W80: YES | Y80: =VLOOKUP(A:A,'Sales team engagament review'!$A:$H,2,0) -> 5 | AD80: 2 + cert
A81: Hamilton | B81: Michael Mikits | C81: QLD | D81: Investor | E81: 10 | F81: 44256 | G81: 48611 | I81: =VLOOKUP(A81,'Scorecard summary'!A:AB,10,0) -> Yes | J81: =VLOOKUP(A81,'Revenue @ Feb 2021'!A:B,2,0) -> #N/A | K81: =VLOOKUP(A81,'Sales team engagament review'!A:H,2,0) -> 4 | L81: NO | M81: YES | N81: YES | O81: YES | P81: NO | Q81: YES | S81: NO | T81: ? | U81: ? | V81: ? | W81: NO | Y81: =VLOOKUP(A:A,'Sales team engagament review'!$A:$H,2,0) -> 4 | AD81: 2 + cert
A82: Hallam | B82: Stan Cichorski | C82: VIC | D82: Owner operator | E82: =VLOOKUP(A82,[3]ActiveFranchiseesResults465!$C:$AA,25,0) -> 6 | F82: 43769 | G82: 45596 | I82: =VLOOKUP(A82,'Scorecard summary'!A:AB,10,0) -> Yes | J82: =VLOOKUP(A82,'Revenue @ Feb 2021'!A:B,2,0) -> 66244.34 | K82: =VLOOKUP(A82,'Sales team engagament review'!A:H,2,0) -> 2 | L82: YES | M82: YES | N82: YES | O82: YES | P82: YES | Q82: YES | R82: =VLOOKUP(A82,'Franchisee Ranking'!B:H,6,0) -> 0.11111111 | S82: NO | T82: ? | U82: ? | V82: ? | W82: YES | Y82: =VLOOKUP(A:A,'Sales team engagament review'!$A:$H,2,0) -> 2 | AD82: 2 + cert
A83: Gosford Shire | B83: Scott Mercer | C83: NSW | D83: Owner operator | E83: =VLOOKUP(A83,[3]ActiveFranchiseesResults465!$C:$AA,25,0) -> 14 | F83: 44440 | G83: 44440 | I83: =VLOOKUP(A83,'Scorecard summary'!A:AB,10,0) -> Yes | J83: =VLOOKUP(A83,'Revenue @ Feb 2021'!A:B,2,0) -> 138522.06 | K83: =VLOOKUP(A83,'Sales team engagament review'!A:H,2,0) -> 2 | L83: YES | M83: YES | N83: YES | O83: NO | P83: NO | Q83: YES | R83: =VLOOKUP(A83,'Franchisee Ranking'!B:G,6,0) -> 0.17910448 | S83: NO | T83: YES | U83: YES | V83: ? | W83: YES | Y83: =VLOOKUP(A:A,'Sales team engagament review'!$A:$H,2,0) -> 2 | AD83: 2 + cert
A84: Gold Coast | B84: Naz sofatzis | C84: QLD | D84: Owner operator | E84: =VLOOKUP(A84,[3]ActiveFranchiseesResults465!$C:$AA,25,0) -> 2 | F84: 44380 | G84: 44380 | I84: =VLOOKUP(A84,'Scorecard summary'!A:AB,10,0) -> Yes | J84: =VLOOKUP(A84,'Revenue @ Feb 2021'!A:B,2,0) -> 145330.53 | K84: =VLOOKUP(A84,'Sales team engagament review'!A:H,2,0) -> 4 | L84: YES | M84: YES | N84: YES | O84: NO | P84: NO | Q84: YES | R84: =VLOOKUP(A84,'Franchisee Ranking'!B:G,6,0) -> 0.21212121 | S84: NO | T84: ? | U84: ? | V84: Yes | W84: YES | Y84: =VLOOKUP(A:A,'Sales team engagament review'!$A:$H,2,0) -> 4
A85: Geelong | B85: Trevor Nicol | C85: VIC | D85: Owner operator | E85: =VLOOKUP(A85,[3]ActiveFranchiseesResults465!$C:$AA,25,0) -> 13 | F85: 44695 | G85: 46521 | I85: =VLOOKUP(A85,'Scorecard summary'!A:AB,10,0) -> Yes | J85: =VLOOKUP(A85,'Revenue @ Feb 2021'!A:B,2,0) -> 110751.73 | K85: =VLOOKUP(A85,'Sales team engagament review'!A:H,2,0) -> 5 | L85: YES | M85: YES | N85: YES | O85: YES | P85: NO | Q85: YES | R85: =VLOOKUP(A85,'Franchisee Ranking'!B:G,6,0) -> 0.016129032 | S85: NO | T85: ? | U85: ? | V85: ? | W85: YES | X85: Family health issues & APP dowload problems were reasons for delay | Y85: =VLOOKUP(A:A,'Sales team engagament review'!$A:$H,2,0) -> 5 | AD85: 2 + cert
A86: Geebung | B86: Michael Mikits | C86: QLD | D86: Investor | E86: 10 | F86: 44256 | G86: 48611 | I86: =VLOOKUP(A86,'Scorecard summary'!A:AB,10,0) -> Yes | J86: =VLOOKUP(A86,'Revenue @ Feb 2021'!A:B,2,0) -> #N/A | K86: =VLOOKUP(A86,'Sales team engagament review'!A:H,2,0) -> 4 | L86: NO | M86: YES | N86: YES | O86: YES | P86: NO | Q86: YES | S86: NO | T86: ? | U86: ? | V86: ? | W86: NO | Y86: =VLOOKUP(A:A,'Sales team engagament review'!$A:$H,2,0) -> 4 | AD86: 2 + cert
A87: Fairfield | B87: Francis Bautista | C87: NSW | D87: Owner operator | E87: =VLOOKUP(A87,[3]ActiveFranchiseesResults465!$C:$AA,25,0) -> 4 | F87: 44803 | G87: 45901 | I87: =VLOOKUP(A87,'Scorecard summary'!A:AB,10,0) -> Yes | J87: =VLOOKUP(A87,'Revenue @ Feb 2021'!A:B,2,0) -> 105834.83 | K87: =VLOOKUP(A87,'Sales team engagament review'!A:H,2,0) -> 3 | L87: YES | M87: YES | N87: YES | O87: YES | P87: NO | Q87: YES | R87: =VLOOKUP(A87,'Franchisee Ranking'!B:G,6,0) -> 0.18181818 | S87: NO | T87: YES | U87: YES | V87: ? | W87: YES | Y87: =VLOOKUP(A:A,'Sales team engagament review'!$A:$H,2,0) -> 3 | AD87: 2 + Cert
A88: Ermington | B88: Adel Chowna | C88: NSW | D88: Owner operator | E88: =VLOOKUP(A88,[3]ActiveFranchiseesResults465!$C:$AA,25,0) -> 7 | F88: 44852 | G88: 44851 | H88: NO | I88: =VLOOKUP(A88,'Scorecard summary'!A:AB,10,0) -> NO | J88: =VLOOKUP(A88,'Revenue @ Feb 2021'!A:B,2,0) -> 61776.63 | K88: =VLOOKUP(A88,'Sales team engagament review'!A:H,2,0) -> 3 | L88: YES | M88: YES | N88: YES | O88: YES | P88: NO | Q88: YES | R88: =VLOOKUP(A88,'Franchisee Ranking'!B:G,6,0) -> 0.27272727 | S88: NO | T88: ? | U88: ? | V88: ? | W88: YES | Y88: =VLOOKUP(A:A,'Sales team engagament review'!$A:$H,2,0) -> 3 | AD88: 2 + Cert
A89: Epping (HO Owned) | B89: MailPlus Head Office | C89: NSW | D89: N/A | E89: N/A | F89: N/A | G89: N/A | I89: =VLOOKUP(A89,'Scorecard summary'!A:AB,10,0) -> HEAD OFFICE | J89: =VLOOKUP(A89,'Revenue @ Feb 2021'!A:B,2,0) -> #N/A | K89: =VLOOKUP(A89,'Sales team engagament review'!A:H,2,0) -> 0 | L89: YES | M89: YES | N89: YES | O89: YES | P89: NO | Q89: NO | S89: NO | T89: ? | U89: ? | V89: ? | W89: NO | Y89: =VLOOKUP(A:A,'Sales team engagament review'!$A:$H,2,0) -> 0
A90: Eagle Farm | B90: Michael Mikits | C90: QLD | D90: Investor | E90: 10 | F90: 44805 | G90: 48611 | I90: =VLOOKUP(A90,'Scorecard summary'!A:AB,10,0) -> Yes | J90: =VLOOKUP(A90,'Revenue @ Feb 2021'!A:B,2,0) -> #N/A | K90: =VLOOKUP(A90,'Sales team engagament review'!A:H,2,0) -> 4 | L90: NO | M90: YES | N90: YES | O90: YES | P90: NO | Q90: YES | S90: NO | T90: ? | U90: ? | V90: ? | W90: NO | Y90: =VLOOKUP(A:A,'Sales team engagament review'!$A:$H,2,0) -> 4 | AD90: 2 + cert
A91: Devonport (HO Owned) | B91: MailPlus Head Office | C91: TAS | D91: N/A | E91: N/A | F91: N/A | G91: N/A | I91: =VLOOKUP(A91,'Scorecard summary'!A:AB,10,0) -> HEAD OFFICE | J91: =VLOOKUP(A91,'Revenue @ Feb 2021'!A:B,2,0) -> #N/A | K91: =VLOOKUP(A91,'Sales team engagament review'!A:H,2,0) -> 0 | L91: YES | M91: YES | N91: YES | O91: YES | P91: NO | Q91: NO | S91: NO | T91: ? | U91: ? | V91: ? | W91: NO | Y91: =VLOOKUP(A:A,'Sales team engagament review'!$A:$H,2,0) -> 0
A92: Darwin | B92: Roman Kabir | C92: NT | D92: Owner operator | E92: 1 | F92: 44470 | G92: 48122 | I92: =VLOOKUP(A92,'Scorecard summary'!A:AB,10,0) -> Yes | J92: =VLOOKUP(A92,'Revenue @ Feb 2021'!A:B,2,0) -> 37554.5 | K92: =VLOOKUP(A92,'Sales team engagament review'!A:H,2,0) -> 4 | L92: YES | M92: NO | N92: YES | O92: YES | P92: YES | Q92: NO | R92: =VLOOKUP(A92,'Franchisee Ranking'!B:G,6,0) -> 0 | S92: NO | T92: ? | U92: ? | V92: ? | W92: YES | Y92: =VLOOKUP(A:A,'Sales team engagament review'!$A:$H,2,0) -> 4
A93: Darlinghurst | B93: John Rodao | C93: NSW | D93: Owner operator | E93: =VLOOKUP(A93,[3]ActiveFranchiseesResults465!$C:$AA,25,0) -> 6 | F93: 43800 | G93: 47453 | H93: Yes | I93: =VLOOKUP(A93,'Scorecard summary'!A:AB,10,0) -> NO | J93: =VLOOKUP(A93,'Revenue @ Feb 2021'!A:B,2,0) -> 72543.24 | K93: =VLOOKUP(A93,'Sales team engagament review'!A:H,2,0) -> 2 | L93: YES | M93: NO | N93: YES | O93: NO | P93: NO | Q93: YES | R93: =VLOOKUP(A93,'Franchisee Ranking'!B:G,6,0) -> 0.125 | S93: Yes | T93: ? | U93: ? | V93: ? | W93: YES | X93: No reply | Y93: =VLOOKUP(A:A,'Sales team engagament review'!$A:$H,2,0) -> 2
A94: Dandenong | B94: Peter Sherer | C94: VIC | D94: Owner operator | E94: =VLOOKUP(A94,[3]ActiveFranchiseesResults465!$C:$AA,25,0) -> 16 | F94: 43897 | G94: 45723 | I94: =VLOOKUP(A94,'Scorecard summary'!A:AB,10,0) -> Yes | J94: =VLOOKUP(A94,'Revenue @ Feb 2021'!A:B,2,0) -> 174421.39 | K94: =VLOOKUP(A94,'Sales team engagament review'!A:H,2,0) -> 3 | L94: YES | M94: YES | N94: YES | O94: YES | P94: YES | Q94: YES | R94: =VLOOKUP(A94,'Franchisee Ranking'!B:H,6,0) -> 0.14285714 | S94: NO | T94: YES | U94: YES | V94: ? | W94: YES | Y94: =VLOOKUP(A:A,'Sales team engagament review'!$A:$H,2,0) -> 3 | AD94: 2 + cert
A95: Coffs (HO Owned) | B95: MailPlus Head Office | C95: NSW | D95: N/A | E95: N/A | F95: N/A | G95: N/A | I95: =VLOOKUP(A95,'Scorecard summary'!A:AB,10,0) -> HEAD OFFICE | J95: =VLOOKUP(A95,'Revenue @ Feb 2021'!A:B,2,0) -> #N/A | K95: =VLOOKUP(A95,'Sales team engagament review'!A:H,2,0) -> 1 | L95: YES | M95: YES | N95: YES | O95: YES | P95: NO | Q95: NO | S95: NO | T95: ? | U95: ? | V95: ? | W95: NO | Y95: =VLOOKUP(A:A,'Sales team engagament review'!$A:$H,2,0) -> 1
A96: Clayton | B96: Devinder Singh | C96: VIC | D96: Owner operator | E96: =VLOOKUP(A96,[3]ActiveFranchiseesResults465!$C:$AA,25,0) -> 5 | F96: 43719 | G96: 45546 | I96: =VLOOKUP(A96,'Scorecard summary'!A:AB,10,0) -> Yes | J96: =VLOOKUP(A96,'Revenue @ Feb 2021'!A:B,2,0) -> 112186.73 | K96: =VLOOKUP(A96,'Sales team engagament review'!A:H,2,0) -> 5 | L96: YES | M96: YES | N96: YES | O96: YES | P96: NO | Q96: YES | R96: =VLOOKUP(A96,'Franchisee Ranking'!B:G,6,0) -> 0.3125 | S96: NO | T96: ? | U96: ? | V96: ? | W96: YES | Y96: =VLOOKUP(A:A,'Sales team engagament review'!$A:$H,2,0) -> 5 | AD96: 2 + cert
A97: Canning Vale | B97: Todd Ingram | C97: WA | D97: Owner operator | E97: =VLOOKUP(A97,[3]ActiveFranchiseesResults465!$C:$AA,25,0) -> 6 | F97: 44639 | G97: 45352 | H97: NO | I97: =VLOOKUP(A97,'Scorecard summary'!A:AB,10,0) -> NO | J97: =VLOOKUP(A97,'Revenue @ Feb 2021'!A:B,2,0) -> 76747.09 | K97: =VLOOKUP(A97,'Sales team engagament review'!A:H,2,0) -> 3 | L97: YES | M97: YES | N97: YES | O97: YES | P97: NO | Q97: NO | R97: =VLOOKUP(A97,'Franchisee Ranking'!B:G,6,0) -> 0 | S97: NO | T97: ? | U97: ? | V97: ? | W97: YES | X97: No reply | Y97: =VLOOKUP(A:A,'Sales team engagament review'!$A:$H,2,0) -> 3 | AD97: 2 + cert
A98: Canberra CBD | B98: MailPlus Head Office | C98: ACT | D98: N/A | E98: N/A | F98: 43864 | G98: 45691 | I98: =VLOOKUP(A98,'Scorecard summary'!A:AB,10,0) -> Yes | J98: =VLOOKUP(A98,'Revenue @ Feb 2021'!A:B,2,0) -> 81771.37 | K98: =VLOOKUP(A98,'Sales team engagament review'!A:H,2,0) -> 0 | L98: YES | M98: NO | N98: YES | O98: YES | P98: NO | Q98: YES | R98: =VLOOKUP(A98,'Franchisee Ranking'!B:G,6,0) -> 0 | S98: NO | T98: ? | U98: ? | V98: ? | W98: YES | Y98: =VLOOKUP(A:A,'Sales team engagament review'!$A:$H,2,0) -> 0 | AD98: 2 + Cert
A99: Canberra Airport | B99: Abul Hassan Syed | C99: ACT | D99: Owner operator | E99: 2 | F99: 43862 | G99: 47515 | I99: =VLOOKUP(A99,'Scorecard summary'!A:AB,10,0) -> Yes | J99: =VLOOKUP(A99,'Revenue @ Feb 2021'!A:B,2,0) -> 53015.22 | K99: =VLOOKUP(A99,'Sales team engagament review'!A:H,2,0) -> 0 | L99: YES | M99: NO | N99: YES | O99: YES | P99: YES | Q99: YES | R99: =VLOOKUP(A99,'Franchisee Ranking'!B:G,6,0) -> 0 | S99: Yes | T99: ? | U99: ? | V99: ? | W99: YES | X99: Simply hasn't understood any HO comms - language barrier is a major concern | Y99: =VLOOKUP(A:A,'Sales team engagament review'!$A:$H,2,0) -> 0
A100: Campbelltown | B100: Paresh Davaria | C100: NSW | D100: Owner operator | E100: 1 | F100: 43929 | G100: 45755 | I100: =VLOOKUP(A100,'Scorecard summary'!A:AB,10,0) -> Yes | J100: ='Revenue @ Feb 2021'!B82 -> 160362.12 | K100: =VLOOKUP(A100,'Sales team engagament review'!A:H,2,0) -> 4 | L100: YES | M100: YES | N100: YES | O100: YES | P100: YES | Q100: YES | R100: =VLOOKUP(A100,'Franchisee Ranking'!B:H,6,0) -> 0.25806452 | S100: NO | T100: ? | U100: ? | V100: ? | W100: YES | Y100: =VLOOKUP(A:A,'Sales team engagament review'!$A:$H,2,0) -> 4 | AA100: Yes | AB100: Written warning issued, breach notice issued August 2021 | AC100: Customer complaints, Rude towards customers, no committing to service on agreed times | AD100: 2 + cert
...

Sheet Sheet8
A1: MP Nerang – Service Summary - week ending 2nd Jan 2026
A3: Customer | B3: Service Days | C3: Service Type | D3: Timing Notes | E3: Additional Notes
A4: Department of Transport & Main Roads | B4: Friday | C4: Po Box Mail Delivery | D4: Anytime | E4: N/A
A5: Allambe(Funeral) | B5: Tue, Wed & Fri | C5: PO Box Mail delivery & outgoing collection at same time | D5: =D4 -> Anytime | E5: Antonnete doesn't typically arrive until late aternoon
A6: Community Housing | B6: Friday | C6: Mail | D6: =D5 -> Anytime
A7: Stratco | B7: Wednesday & Friday | C7: Banking – Westpac | D7: Anytime | E7: May require change order
A8: Rodd & Gunn (Harbour Town) | B8: Wednesday & Friday | C8: Banking – ANZ | D8: Anytime | E8: May require change order

Sheet Sheet7
A1: Franchise Location | B1: Key Date(s) | C1: Action Taken | D1: Amount Paid / Received | E1: Status / Outcome
A2: MP Penrith | B2: 45717 | C2: Deed of surrender – became HO owned & operated | D2: N/A | E2: Sold 1 Jul 2025 for $100,000
A3: MP Riverside | B3: 45382 | C3: Deed of release – payment to exiting franchisee | D3: Paid $65,000 | E3: HO owned & operated until sold 1 Jul 2024 for $150,000

Sheet Sheet4
A1: Coolum Beach Christian College - Sunshine Coast
A2: Coolum Beach Christian College - Sunshine Coast
A3: Coolum Beach Christian College - Sunshine Coast
A4: Coolum Beach Christian College - Sunshine Coast
A5: WSP Australia Pty Limited - Maroochydore
A6: Toowoomba Garden of Remembrance - Invocare

Sheet Sheet3
A1: Franchise | B1: Ultimate Expiry Date (Including FY18 release)
A2: Sydney - 2N3 | B2: 48580
A3: Sunshine | B3: 46873
A4: Penrith | B4: 45717
A5: Northern Beaches | B5: 46935
A6: Milperra | B6: 47026
A7: Mascot | B7: 47928
A8: Hunter Valley | B8: 44786
A9: Campbellfield | B9: 47604
A10: Braeside | B10: 49217
A11: Bowen Hills | B11: 50345
A12: Barton | B12: 47514
A13: Arncliffe | B13: 48274
A14: Altona | B14: 45505

Sheet Sheet2
A1: Sunshine | B1: 46873
A2: Penrith | B2: 45717
A3: Northern Beaches | B3: 46935
A4: Milperra | B4: 47026
A5: Hunter Valley | B5: 44786
A6: Darlinghurst | B6: 47453

Sheet Covid Summary
A3: Row Labels | B3: Count of Franchise | C3: Count of Vaccine
A4: ACT | B4: 3 | C4: 1 | D4: =B4-C4 -> 2 | E4: =D4/B4 -> 0.66666667
A5: NSW | B5: 48 | C5: 39 | D5: =B5-C5 -> 9 | E5: =D5/B5 -> 0.1875
A6: NT | B6: 1 | D6: =B6-C6 -> 1 | E6: =D6/B6 -> 1
A7: QLD | B7: 36 | C7: 24 | D7: =B7-C7 -> 12 | E7: =D7/B7 -> 0.33333333
A8: SA | B8: 2 | C8: 2 | D8: =B8-C8 -> 0 | E8: =D8/B8 -> 0
A9: TAS | B9: 3 | C9: 1 | D9: =B9-C9 -> 2 | E9: =D9/B9 -> 0.66666667
A10: VIC | B10: 26 | C10: 23 | D10: =B10-C10 -> 3 | E10: =D10/B10 -> 0.11538462
A11: WA | B11: 7 | C11: 5 | D11: =B11-C11 -> 2 | E11: =D11/B11 -> 0.28571429
A12: (blank) | D12: =B12-C12 -> 0 | E12: =C12/B12 -> #DIV/0!
A13: Grand Total | B13: 126 | C13: 95 | D13: =B13-C13 -> 31 | E13: =C13/B13 -> 0.75396825

Sheet Operator Vehicle Log
A1: Franchisee | B1: Vehicle Model | C1: Vehicle Year | D1: Vehicle Colour | E1: Signage | F1: Ownership | G1: Rego | H1: Carrier Bargo | I1: Toll Depot Induction | J1: Operator inducted
A2: Acacia Ridge | B2: Suzuki APV | C2: 2014 | D2: white | E2: no | F2: Franchisee | G2: 740TTK
A3: Adelaide | B3: TBC | C3: TBC | D3: TBC | E3: TBC | F3: TBC | G3: TBC
A4: Adelaide CBD | B4: Fiat Doblo | C4: 2018 | D4: Silver | E4: Yes | F4: Franchisee | G4: SO25CAF
A5: Adelaide CBD | B5: subaru XV | C5: 2015 | D5: Silver | E5: no | F5: Driver | G5: S888BAL
A6: Airport West | C6: 2016 | D6: Silver | E6: No | F6: Franchisee | G6: ALA999
A7: Alexandria | B7: VW Transporter | C7: 2008 | D7: Silver | E7: Yes | F7: Franchisee | G7: BGP04Z | H7: N0 | I7: Pending | J7: Steven Maharjan
A8: Alexandria | C8: 2015 | D8: Silver | E8: Yes | F8: Franchisee | G8: CE42MH | H8: N0 | I8: Yes | J8: Hendry Kifa
A9: Altona | B9: caddy | C9: 2016 | D9: Silver | E9: no | F9: Franchisee | G9: 1GX8QY
A10: Arncliffe | C10: 2015 | D10: silver | E10: Yes | F10: Driver | G10: CG63LT | H10: Yes | I10: Yes | J10: Koda
A11: Arncliffe | C11: 2014 | D11: silver | E11: No | F11: Driver | G11: CQI01F | I11: Yes | J11: Natem
A12: Banyo | B12: Hyundai iLoad | C12: 2010 | D12: Silver | E12: Yes | F12: Driver | G12: 022RHB | H12: Yes
A13: Barton
A14: Baulkham Hills | C14: 2014 | D14: Silver | E14: Yes | F14: Driver | G14: JA0057
A15: Bayswater | B15: Honda CRV | C15: 2015 | D15: Grey | E15: no | F15: Franchisee | G15: 1DZ8VA
A16: Bayswater | B16: Corolla | C16: 2009 | D16: Silver | E16: no | F16: Driver | G16: YDH590
A17: Belmont | B17: hyundai Tucson | C17: 2016 | D17: silver | E17: no | F17: Franchisee | H17: Yes
A18: Blacktown | C18: 2017 | D18: Silver Metalic | E18: No | F18: Driver | G18: DQX94E | H18: N0 - Intends to install | I18: Yes
A19: Blacktown | C19: 2015 | D19: White | E19: No | F19: Driver | G19: VYJ67E | H19: N0 | I19: Yes
A20: Bondi Junction
A21: Booval | B21: VW Caddy Maxi | C21: 2014 | D21: Silver | E21: Yes | F21: Franchisee | G21: CG71VH
A22: Botany | B22: caddy | C22: 2018 | D22: silver | E22: yes | F22: Franchisee | I22: Yes | J22: Richard Chang
A23: Botany | B23: Toyota Prius | C23: 2018 | D23: white | E23: no | F23: Franchisee | I23: Yes | J23: Richard Chang
A24: Bowen Hills | B24: Caddy | C24: 2018 | D24: silver | E24: no | F24: Franchisee
A25: Box Hill
A26: Braeside
A27: Brendale | B27: Caddy | C27: 2017 | D27: Silver | E27: no | F27: Franchisee | G27: 762 XJI
A28: Brisbane | B28: VW Caddy | D28: Silver | E28: Yes | F28: Franchisee | G28: 687WAG
A29: Brisbane | B29: VW Caddy | D29: Silver | E29: Yes | F29: Franchisee | G29: 100YPU
A30: Brisbane | B30: VW Caddy | D30: Silver | E30: Yes | F30: Franchisee | G30: 343WFV
A31: Brisbane | B31: VW Caddy | D31: White | E31: Yes | F31: Franchisee | G31: 108ZKE
A32: Brisbane | B32: VW Transporter | D32: White | E32: Yes | F32: Franchisee | G32: 261BH2
A33: Brisbane | B33: VW Caddy | D33: Silver | E33: Yes | F33: Franchisee | G33: 377XTZ
A34: Brisbane | B34: VW Caddy | D34: Silver | E34: Yes | F34: Franchisee | G34: 994WLS
A35: Brisbane | B35: VW Caddy | D35: Silver | E35: Yes | F35: Franchisee | G35: 399ZXG
A36: Brisbane | B36: Hyundai i30 | D36: Silver | E36: Yes | F36: Franchisee | G36: 167WFU
A37: Brisbane | B37: VW Caddy | D37: White | E37: Yes | F37: Franchisee | G37: 835AE2
A38: Brisbane | B38: VW Caddy | D38: White | E38: Yes | F38: Franchisee | G38: 834AE2
A39: Brisbane | B39: VW Caddy | D39: Silver | E39: Yes | F39: Franchisee | G39: 885XGP
A40: Brookvale | B40: Mercede Vitto | C40: 2020 | D40: white | E40: no | F40: Franchisee | G40: EJX90D
A41: Brookvale | B41: Mits Outlander | C41: 2018 | D41: Grey | E41: no | F41: Driver | G41: DWW52H
A42: Browns Plains | B42: LDV G10 | C42: 2018 | D42: Silver | E42: Yes | F42: Franchisee | G42: 062YKB
A43: Burleigh | B43: Caddy | C43: 2013 | D43: Silver | E43: Yes | F43: Franchisee | G43: 592 TQB
A44: Byron Bay | B44: Head Office | C44: Head Office | D44: Head Office | E44: Head Office | F44: Head Office | G44: Head Office
A45: Campbellfield | B45: Fiat Doblo | C45: 2019 | D45: white | E45: no | F45: Franchisee | G45: 1om8td | H45: Yes
A46: Campbelltown | B46: toyota Rukus | C46: 2015 | D46: white | E46: no | F46: Franchisee | G46: EHM95Z
A47: Canberra Airport | B47: Camry | C47: 2015 | D47: silver | E47: no | F47: Franchisee
A48: Canberra CBD | B48: Head Office | C48: Head Office | D48: Head Office | E48: Head Office | F48: Head Office | G48: Head Office
A49: Canning Vale | B49: Kia Sorento | C49: 2017 | D49: Black | E49: no | F49: Franchisee | G49: 1GIF341
A50: Canning Vale | B50: Holden Captiva | C50: 2015 | D50: Silver | E50: no | F50: Driver | G50: 1HDE718
A51: Clayton | B51: nissan Xtrail | C51: 2015 | D51: Grey | E51: no | F51: Franchisee | G51: JAGGIS
A52: Crows Nest | B52: LDV (G10) | C52: 2018 | D52: white | E52: no | F52: Driver
A53: Dandenong | B53: Caddy | C53: 2014 | D53: Silver | E53: Yes | F53: Franchisee | G53: 1DA8TW
A54: Dandenong | B54: Fiat Doblo | C54: 2019 | D54: Silver | E54: Yes | F54: Franchisee | G54: 1MH3ZC
A55: Darlinghurst | B55: iLoad | C55: 2014 | D55: Silver | E55: Yes | F55: Franchisee | G55: CC59YH
A56: Darwin | B56: VW Caddy | C56: 2014 | D56: Dark Grey | E56: Yes | F56: Franchisee
A57: Devonport | B57: Head Office | C57: Head Office | D57: Head Office | E57: Head Office | F57: Head Office | G57: Head Office
A58: Epping | B58: Head Office | C58: Head Office | D58: Head Office | E58: Head Office | F58: Head Office | G58: Head Office
A59: Ermington | B59: caddy Maxi | C59: 2017 | D59: Silver | E59: no | F59: Franchisee | G59: YDX73J
A60: Fairfield | B60: caddy | C60: 2008 | D60: Silver | E60: Yes | F60: Franchisee | G60: BGE 79Q
A61: Geelong | C61: 2015 | D61: silver | E61: Yes | F61: Franchisee | G61: 1ET7LM
A62: Geelong | C62: 2012 | D62: silver | E62: No | F62: Franchisee | G62: ZEQ087
A63: Gold Coast | B63: Caddy Maxi | C63: 2019 | D63: silver | E63: no | F63: Franchisee
A64: Gosford Shire
A65: Hallam | B65: Renault Kangoo | C65: 2019 | D65: Silver | E65: Yes | F65: Franchisee | G65: 1LR9TU
A66: Hawthorn | B66: subaru forester | C66: 2015 | D66: blue | E66: no | F66: Franchisee | G66: 1MZ7QQ
A67: Hemmant | B67: Caddy | C67: 2017 | D67: Silver | E67: no | F67: Franchisee | G67: TRU 926
A68: Hobart | C68: 2015 | D68: silver | E68: Yes | F68: Franchisee | G68: E42MC
A69: Homebush | B69: Hi ace | C69: 2012 | D69: white | E69: no | F69: Franchisee | G69: CO73FT
A70: Hoppers Crossing | C70: 2015 | D70: WHITE | E70: No | F70: Franchisee | G70: 1IQ7VR | H70: N0 will install prior to commencing SendlePlus
A71: Hunter Valley | B71: iLoad | C71: 2012 | D71: Silver | E71: Yes | F71: Franchisee | G71: CM0O8D
A72: Illawarra | B72: renault Traffic | C72: 2019 | D72: white | E72: no | F72: Franchisee
A73: Illawarra | B73: renault Kangoo | C73: 2012 | D73: white | E73: yes | F73: Franchisee
A74: Ipswich | B74: Head Office | C74: Head Office | D74: Head Office | E74: Head Office | F74: Head Office | G74: Head Office
A75: Jones | B75: caddy x2 | C75: 2016 | D75: silver | E75: no | F75: Franchisee | H75: Yes
A76: Kewdale | C76: 2011 | D76: METALLIC SILVER | E76: Yes | F76: Franchisee | G76: 1EJ1558 | H76: Yes
A77: Lalor | B77: Renault Kangoo | C77: 2020 | D77: Grey | E77: no | F77: Franchisee | G77: BHR 838
A78: Lane Cove | B78: LDV (G10) | C78: 2018 | D78: white | E78: no | F78: Driver
A79: Lane Lane | B79: iLoad | C79: 2019 | D79: Silver | E79: no | F79: Franchisee | G79: 568ZIC
A80: Launceston | C80: 2015 | D80: silver | E80: Yes | F80: Franchisee | G80: E29JQ
A81: Launceston | C81: 2020 | D81: white | E81: Yes | F81: Franchisee | G81: I 01 YS
A82: Liverpool | B82: iLoad | C82: 2021 | D82: Silver | E82: no | F82: Franchisee | G82: YKM 66S
A83: Mackay | B83: Head Office | C83: Head Office | D83: Head Office | E83: Head Office | F83: Head Office | G83: Head Office
A84: Macquarie Park
A85: Mascot | C85: 2015 | D85: SILVER | E85: Yes | F85: Franchisee | G85: CXV85F | I85: Yes | J85: Rohit Hedge
A86: Melbourne CBD | C86: 2015 | D86: Silver | E86: No | F86: Franchisee | G86: 1DC5OE
A87: Melbourne CBD | C87: 2015 | D87: Silver | E87: Yes | F87: Franchisee | G87: 1EH8RG
A88: Melbourne CBD | C88: 2016 | D88: Silver | E88: Yes | F88: Franchisee | G88: 1GJ8JA
A89: Milperra | B89: iLoad | C89: 2012 | D89: Silver | E89: Yes | F89: Driver | G89: BS90VU
A90: Moorabbin | C90: 2010 | D90: Silver Grey | E90: Yes | F90: Franchisee | G90: XWD238
A91: Moorebank | B91: LDV G10 | C91: 2017 | D91: Silver | E91: no | F91: Franchisee | G91: C000WT
A92: Morningside | B92: LDV G10 | C92: 2019 | D92: white | E92: no | F92: Franchisee | G92: 618YKA
A93: Mount Gravatt | B93: Suzuki APV | C93: 2014 | D93: white | E93: no | F93: Franchisee | G93: 152TXQ
A94: Mount Waverley | B94: caddy | C94: 2008 | D94: Silver | E94: no | F94: Franchisee | G94: WFZ207
A95: Mulgrave | B95: Caddy | C95: 2015 | D95: Silver | E95: Yes | F95: Franchisee | G95: AMY 332
A96: Murarrie | B96: caddy Maxi | C96: 2012 | D96: Silver | E96: no | F96: Franchisee | G96: 660WQO
A97: Nerang
A98: Newcastle | C98: 2015 | D98: SILVER | E98: Yes | F98: Franchisee | G98: CE07DL
A99: North Lakes | B99: iLoad | C99: 2014 | D99: Silver | E99: Yes | F99: Franchisee | G99: 973YXH
A100: North Melbourne | B100: Renault Kangoo | C100: 2019 | D100: white | E100: no | F100: Franchisee | G100: 1QU4OA
...

Sheet Sales team engagament review
A1: Franchise | B1: Score | C1: Prospects? | D1: Engaged / Communicates ? | E1: Follows Instructions ? | F1: Takes on new work? | G1: Embraces the MPEX and broader business visions? | H1: Rep
A3: Altona | B3: 3 | C3: 0 | D3: 0 | E3: 1 | F3: 1 | G3: 1 | H3: David
A4: Barton | B4: 0
A5: Bondi Junction | B5: 4 | C5: 0 | D5: 1 | E5: 1 | F5: 1 | G5: 1 | H5: Kerina
A6: Canberra CBD | B6: 0
A7: North Sydney | B7: 3 | C7: 0 | D7: 1 | E7: 0 | F7: 1 | G7: 1 | H7: Kerina
A8: Darlinghurst | B8: 2 | C8: 0 | D8: 0 | E8: 1 | F8: 1 | G8: 0 | H8: kerina
A9: Hunter Valley | B9: 0 | C9: 0 | D9: 0 | E9: 0 | F9: 0 | G9: 0 | H9: kerina
A10: Lane Cove | B10: 4 | C10: 0 | D10: 1 | E10: 1 | F10: 1 | G10: 1 | H10: kerina
A11: Nerang | B11: 4 | C11: 0 | D11: 1 | E11: 1 | F11: 1 | G11: 1 | H11: Lee
A12: Newcastle | B12: 3 | C12: 0 | D12: 1 | E12: 1 | F12: 1 | G12: 0 | H12: kerina
A13: Perth CBD | B13: 3 | C13: 0 | D13: 0 | E13: 1 | F13: 1 | G13: 1 | H13: Lee
A14: Pyrmont | B14: 4 | C14: 0 | D14: 1 | E14: 1 | F14: 1 | G14: 1 | H14: kerina
A15: Regency | B15: 0
A16: Seven Hills | B16: 3 | C16: 0 | D16: 1 | E16: 1 | F16: 1 | G16: 0 | H16: kerina
A17: South Bank | B17: 2 | C17: 0 | D17: 0 | E17: 1 | F17: 1 | G17: 0 | H17: Lee
A18: Sydney - 2N3 | B18: 4 | C18: 0 | D18: 1 | E18: 1 | F18: 1 | G18: 1 | H18: kerina
A19: Sydney - North West | B19: 3 | C19: 0 | D19: 1 | E19: 0 | F19: 1 | G19: 1 | H19: kerina
A20: Tappenden Tappenden | B20: 3 | C20: 0 | D20: 1 | E20: 1 | F20: 1 | G20: 0 | H20: Lee
A21: West Perth | B21: 3 | C21: 0 | D21: 0 | E21: 1 | F21: 1 | G21: 1 | H21: Lee
A22: Acacia Ridge | B22: 5 | C22: 1 | D22: 1 | E22: 1 | F22: 1 | G22: 1 | H22: Lee
A23: Canberra Airport | B23: 0
A24: Riverside | B24: 2 | C24: 0 | D24: 1 | E24: 1 | F24: 0 | G24: 0 | H24: David
A25: Cairns | B25: 2 | C25: 0 | D25: 0 | E25: 1 | F25: 1 | G25: 0 | H25: Lee
A26: Braeside | B26: 4 | C26: 0 | D26: 1 | E26: 1 | F26: 1 | G26: 1 | H26: David
A27: Brisbane CBD | B27: 4 | C27: 0 | D27: 1 | E27: 1 | F27: 1 | G27: 1 | H27: Lee
A28: Eagle Farm | B28: 4 | C28: 0 | D28: 1 | E28: 1 | F28: 1 | G28: 1 | H28: Lee
A29: Geebung | B29: 4 | C29: 0 | D29: 1 | E29: 1 | F29: 1 | G29: 1 | H29: Lee
A30: Hamilton | B30: 4 | C30: 0 | D30: 1 | E30: 1 | F30: 1 | G30: 1 | H30: Lee
A31: Illawarra | B31: 5 | C31: 1 | D31: 1 | E31: 1 | F31: 1 | G31: 1 | H31: kerina
A32: Spring Hill | B32: 4 | C32: 0 | D32: 1 | E32: 1 | F32: 1 | G32: 1 | H32: Lee
A33: Stafford | B33: 4 | C33: 0 | D33: 1 | E33: 1 | F33: 1 | G33: 1 | H33: Lee
A34: Yatala | B34: 4 | C34: 0 | D34: 1 | E34: 1 | F34: 1 | G34: 1 | H34: Lee
A35: Airport West | B35: 4 | C35: 0 | D35: 1 | E35: 1 | F35: 1 | G35: 1 | H35: David
... A40: Booval | B40: 2 | C40: 0 | D40: 0 | E40: 1 | F40: 0 | G40: 1 | H40: Lee
A41: Botany Botany | B41: 0 | C41: 0
A42: Bowen Hills | B42: 2 | C42: 0 | D42: 0 | E42: 1 | F42: 1 | G42: 0 | H42: Lee
A43: Box Hill | B43: 5 | C43: 1 | D43: 1 | E43: 1 | F43: 1 | G43: 1 | H43: David
A44: Brendale | B44: 4 | C44: 0 | D44: 1 | E44: 1 | F44: 1 | G44: 1 | H44: Lee
A45: Brookvale | B45: 3 | C45: 0 | D45: 1 | E45: 1 | F45: 1 | G45: 0 | H45: kerina
A46: Browns Plains | B46: 2 | C46: 0 | D46: 0 | E46: 1 | F46: 1 | G46: 0 | H46: Lee
A47: Campbelltown | B47: 4 | C47: 0 | D47: 1 | E47: 1 | F47: 1 | G47: 1 | H47: kerina
A48: Coffs (HO Owned) | B48: 1 | C48: 0 | D48: 0 | E48: 0 | F48: 1 | G48: 0 | H48: Lee
A49: Dandenong | B49: 3 | C49: 0 | D49: 0 | E49: 1 | F49: 1 | G49: 1 | H49: David
A50: Devonport (HO Owned) | B50: 0
A51: Epping (HO Owned) | B51: 0
A52: Hallam | B52: 2 | C52: 0 | D52: 0 | E52: 1 | F52: 0 | G52: 1 | H52: David
A53: Hemmant | B53: 4 | C53: 0 | D53: 1 | E53: 1 | F53: 1 | G53: 1 | H53: Lee
A54: Ipswich (HO Owned) | B54: 3 | C54: 0 | D54: 0 | E54: 1 | F54: 1 | G54: 1 | H54: Lee
A55: Launceston | B55: 0
A56: Mackay (HO Owned) | B56: 2 | C56: 0 | D56: 0 | E56: 1 | F56: 1 | G56: 0 | H56: Lee
A57: Macquarie Park | B57: 4 | C57: 0 | D57: 1 | E57: 1 | F57: 1 | G57: 1 | H57: kerina
A58: Moorebank | B58: 4 | C58: 0 | D58: 1 | E58: 1 | F58: 1 | G58: 1 | H58: kerina
A59: Morningside | B59: 4 | C59: 0 | D59: 1 | E59: 1 | F59: 1 | G59: 1 | H59: Lee
A60: Mount Waverley | B60: 4 | C60: 0 | D60: 1 | E60: 1 | F60: 1 | G60: 1 | H60: David
A61: North Lakes | B61: 4 | C61: 0 | D61: 1 | E61: 1 | F61: 1 | G61: 1 | H61: Lee
A62: Northern Beaches | B62: 3 | C62: 0 | D62: 0 | E62: 1 | F62: 1 | G62: 1 | H62: kerina
A63: Osborne Park | B63: 5 | C63: 1 | D63: 1 | E63: 1 | F63: 1 | G63: 1 | H63: Lee
A64: Parramatta | B64: 5 | C64: 1 | D64: 1 | E64: 1 | F64: 1 | G64: 1 | H64: kerina
A65: Salisbury | B65: 3 | C65: 0 | D65: 0 | E65: 1 | F65: 1 | G65: 1 | H65: Lee
A66: Seaford | B66: 4 | C66: 0 | D66: 1 | E66: 1 | F66: 1 | G66: 1 | H66: David
A67: St Kilda Road | B67: 4 | C67: 0 | D67: 1 | E67: 1 | F67: 1 | G67: 1 | H67: David
... A72: Townsville (HO Owned) | B72: 5 | C72: 1 | D72: 1 | E72: 1 | F72: 1 | G72: 1 | H72: Lee
A73: Waterloo (HO Owned) | B73: 0
A74: Willoughby | B74: 5 | C74: 1 | D74: 1 | E74: 1 | F74: 1 | G74: 1 | H74: kerina
A75: Brisbane Airport | B75: 4 | C75: 0 | D75: 1 | E75: 1 | F75: 1 | G75: 1 | H75: Lee
A76: Melbourne CBD | B76: 5 | C76: 1 | D76: 1 | E76: 1 | F76: 1 | G76: 1 | H76: David
A77: Rockhampton (HO Operated/owned) | B77: 2 | C77: 0 | D77: 0 | E77: 1 | F77: 1 | G77: 0 | H77: Lee
A78: Jones Jones | B78: 2 | C78: 0 | D78: 0 | E78: 1 | F78: 1 | G78: 0 | H78: Lee
A79: Darwin | B79: 4 | C79: 1 | D79: 1 | E79: 0 | F79: 1 | G79: 1 | H79: Lee
A80: Homebush | B80: 4 | C80: 0 | D80: 1 | E80: 1 | F80: 1 | G80: 1 | H80: kerina
A81: Penrith | B81: 3 | C81: 0 | D81: 1 | E81: 1 | F81: 1 | G81: 0 | H81: kerina
A82: Lane Lane | B82: 5 | C82: 1 | D82: 1 | E82: 1 | F82: 1 | G82: 1 | H82: Lee
A83: Adelaide CBD | B83: 5 | C83: 1 | D83: 1 | E83: 1 | F83: 1 | G83: 1
A84: Albury | B84: 0
A85: Alexandria | B85: 4 | C85: 0 | D85: 1 | E85: 1 | F85: 1 | G85: 1 | H85: kerina
A86: Baulkham Hills | B86: 4 | C86: 0 | D86: 1 | E86: 1 | F86: 1 | G86: 1 | H86: kerina
A87: Bayswater | B87: 4 | C87: 0 | D87: 1 | E87: 1 | F87: 1 | G87: 1 | H87: David
A88: Burleigh | B88: 5 | C88: 1 | D88: 1 | E88: 1 | F88: 1 | G88: 1 | H88: Lee
A89: Byron Bay | B89: 5 | C89: 1 | D89: 1 | E89: 1 | F89: 1 | G89: 1 | H89: kerina
A90: Campbellfield | B90: 4 | C90: 1 | D90: 1 | E90: 1 | F90: 0 | G90: 1 | H90: David
A91: Canning Vale | B91: 3 | C91: 0 | D91: 1 | E91: 1 | F91: 0 | G91: 1 | H91: Lee
A92: Clayton | B92: 5 | C92: 1 | D92: 1 | E92: 1 | F92: 1 | G92: 1 | H92: David
A93: Ermington | B93: 3 | C93: 0 | D93: 0 | E93: 1 | F93: 1 | G93: 1 | H93: kerina
A94: Fairfield | B94: 3 | C94: 0 | D94: 0 | E94: 1 | F94: 1 | G94: 1 | H94: kerina
A95: Geelong | B95: 5 | C95: 1 | D95: 1 | E95: 1 | F95: 1 | G95: 1 | H95: David
A96: Gold Coast | B96: 4 | C96: 0 | D96: 1 | E96: 1 | F96: 1 | G96: 1 | H96: Lee
... A98: Hawthorn | B98: 5 | C98: 1 | D98: 1 | E98: 1 | F98: 1 | G98: 1 | H98: David
A99: Hobart | B99: 0
A100: Hoppers Crossing | B100: 4 | C100: 0 | D100: 1 | E100: 1 | F100: 1 | G100: 1 | H100: David
A101: Kewdale | B101: 0
A102: Lalor | B102: 4 | C102: 0 | D102: 1 | E102: 1 | F102: 1 | G102: 1 | H102: David
A103: Liverpool | B103: 3 | C103: 0 | D103: 0 | E103: 1 | F103: 1 | G103: 1 | H103: kerina
A104: Mascot | B104: 1 | C104: 0 | D104: 0 | E104: 1 | F104: 0 | G104: 0 | H104: kerina
A105: Milperra | B105: 4 | C105: 0 | D105: 1 | E105: 1 | F105: 1 | G105: 1 | H105: kerina
A106: Moorabbin | B106: 5 | C106: 1 | D106: 1 | E106: 1 | F106: 1 | G106: 1 | H106: David
A107: Mount Gravatt | B107: 5 | C107: 1 | D107: 1 | E107: 1 | F107: 1 | G107: 1 | H107: Lee
A108: Mulgrave | B108: 5 | C108: 1 | D108: 1 | E108: 1 | F108: 1 | G108: 1 | H108: David
A109: Murarrie | B109: 4 | C109: 0 | D109: 1 | E109: 1 | F109: 1 | G109: 1 | H109: Lee
A110: North Melbourne | B110: 5 | C110: 1 | D110: 1 | E110: 1 | F110: 1 | G110: 1 | H110: David
...

Sheet Engaged v Signups
A1: Row Labels | B1: Count | C1: Score
A2: Geelong | B2: 26 | C2: =VLOOKUP(A2,'Sales team engagament review'!A:H,2,0) -> 5
A3: Brisbane | B3: 22 | C3: 5
A4: Melbourne CBD | B4: 21 | C4: =VLOOKUP(A4,'Sales team engagament review'!A:H,2,0) -> 5
A5: Adelaide CBD | B5: 18 | C5: =VLOOKUP(A5,'Sales team engagament review'!A:H,2,0) -> 5
A6: Mailplus Pty Ltd | B6: 11 | C6: HO
A7: Pyrmont | B7: 11 | C7: =VLOOKUP(A7,'Sales team engagament review'!A:H,2,0) -> 4
A8: Sunshine Coast | B8: 11 | C8: =VLOOKUP(A8,'Sales team engagament review'!A:H,2,0) -> 2
A9: Byron Bay | B9: 10 | C9: =VLOOKUP(A9,'Sales team engagament review'!A:H,2,0) -> 5
A10: Willoughby | B10: 10 | C10: =VLOOKUP(A10,'Sales team engagament review'!A:H,2,0) -> 5
A11: Osborne Park | B11: 9 | C11: =VLOOKUP(A11,'Sales team engagament review'!A:H,2,0) -> 5
A12: Gold Coast | B12: 8 | C12: =VLOOKUP(A12,'Sales team engagament review'!A:H,2,0) -> 4
A13: North Lakes | B13: 8 | C13: =VLOOKUP(A13,'Sales team engagament review'!A:H,2,0) -> 4
A14: Sydney - South East A Sydney - South East A | B14: 8 | C14: =VLOOKUP(A14,'Sales team engagament review'!A:H,2,0) -> 5
A15: Taren Point | B15: 8 | C15: =VLOOKUP(A15,'Sales team engagament review'!A:H,2,0) -> 4
A16: Hoppers Crossing | B16: 7 | C16: =VLOOKUP(A16,'Sales team engagament review'!A:H,2,0) -> 4
A17: Bondi Junction | B17: 6 | C17: =VLOOKUP(A17,'Sales team engagament review'!A:H,2,0) -> 4
A18: Box Hill | B18: 6 | C18: =VLOOKUP(A18,'Sales team engagament review'!A:H,2,0) -> 5
... A73: Fairfield | B73: 2 | C73: =VLOOKUP(A73,'Sales team engagament review'!A:H,2,0) -> 3
A74: Ipswich | B74: 2 | C74: HO
A75: Lalor | B75: 2 | C75: =VLOOKUP(A75,'Sales team engagament review'!A:H,2,0) -> 4
A76: Lane Cove | B76: 2 | C76: =VLOOKUP(A76,'Sales team engagament review'!A:H,2,0) -> 4
A77: Lane Lane | B77: 2 | C77: =VLOOKUP(A77,'Sales team engagament review'!A:H,2,0) -> 5
A78: Macquarie Park | B78: 2 | C78: =VLOOKUP(A78,'Sales team engagament review'!A:H,2,0) -> 4
A79: Mascot | B79: 2 | C79: =VLOOKUP(A79,'Sales team engagament review'!A:H,2,0) -> 1
A80: Moorebank | B80: 2 | C80: =VLOOKUP(A80,'Sales team engagament review'!A:H,2,0) -> 4
A81: Morningside | B81: 2 | C81: =VLOOKUP(A81,'Sales team engagament review'!A:H,2,0) -> 4
A82: Mount Gravatt | B82: 2 | C82: =VLOOKUP(A82,'Sales team engagament review'!A:H,2,0) -> 5
A83: Perth CBD | B83: 2 | C83: =VLOOKUP(A83,'Sales team engagament review'!A:H,2,0) -> 3
A84: Salisbury | B84: 2 | C84: =VLOOKUP(A84,'Sales team engagament review'!A:H,2,0) -> 3
A85: Seven Hills | B85: 2 | C85: =VLOOKUP(A85,'Sales team engagament review'!A:H,2,0) -> 3
A86: South Bank | B86: 2 | C86: =VLOOKUP(A86,'Sales team engagament review'!A:H,2,0) -> 2
... A93: Braeside | B93: 1 | C93: =VLOOKUP(A93,'Sales team engagament review'!A:H,2,0) -> 4
A94: Coffs Harbour | B94: 1 | C94: HO
A95: Dandenong | B95: 1 | C95: =VLOOKUP(A95,'Sales team engagament review'!A:H,2,0) -> 3
A96: Epping | B96: 1 | C96: HO
A97: Hallam | B97: 1 | C97: =VLOOKUP(A97,'Sales team engagament review'!A:H,2,0) -> 2
A98: Hobart | B98: 1 | C98: =VLOOKUP(A98,'Sales team engagament review'!A:H,2,0) -> 0
A99: Kewdale | B99: 1 | C99: =VLOOKUP(A99,'Sales team engagament review'!A:H,2,0) -> 0
A100: Liverpool | B100: 1 | C100: =VLOOKUP(A100,'Sales team engagament review'!A:H,2,0) -> 3
A101: Milperra | B101: 1 | C101: =VLOOKUP(A101,'Sales team engagament review'!A:H,2,0) -> 4
A102: Mount Waverley | B102: 1 | C102: =VLOOKUP(A102,'Sales team engagament review'!A:H,2,0) -> 4
A103: Northern Beaches | B103: 1 | C103: =VLOOKUP(A103,'Sales team engagament review'!A:H,2,0) -> 3
A104: Peninsula | B104: 1 | C104: =VLOOKUP(A104,'Sales team engagament review'!A:H,2,0) -> 3
A105: Rocklea | B105: 1 | C105: =VLOOKUP(A105,'Sales team engagament review'!A:H,2,0) -> 5
A106: Rosebery | B106: 1 | C106: =VLOOKUP(A106,'Sales team engagament review'!A:H,2,0) -> 0
A107: Scoresby | B107: 1 | C107: =VLOOKUP(A107,'Sales team engagament review'!A:H,2,0) -> 5
A108: Toowoomba | B108: 1 | C108: =VLOOKUP(A108,'Sales team engagament review'!A:H,2,0) -> 3
A109: Townsville | B109: 1 | C109: HO
A110: Trinh TRINH | B110: 1 | C110: =VLOOKUP(A110,'Sales team engagament review'!A:H,2,0) -> 1
A111: West Perth | B111: 1 | C111: =VLOOKUP(A111,'Sales team engagament review'!A:H,2,0) -> 3
A112: Wetherill Park | B112: 1 | C112: =VLOOKUP(A112,'Sales team engagament review'!A:H,2,0) -> 2
A113: Wyong | B113: 1 | C113: =VLOOKUP(A113,'Sales team engagament review'!A:H,2,0) -> 2

Sheet Tenure
A1: Internal ID | B1: State | C1: Name | D1: Franchisee | E1: Franchisee First Name | F1: Franchisee Last Name | G1: Billing Address 1 | H1: Billing Address 2 | I1: Billing City | J1: Billing State/Province | K1: Billing Zip | L1: Shipping City | M1: Shipping State/Province | N1: Shipping Zip | O1: Email | P1: Payment Cycle | Q1: Classification | R1: Franchisee Mobile No | S1: Minimum of Commencement Date | T1: Maximum of Cease Date | U1: Sum of Renewals | V1: Exclude From Batch Printing | W1: Company-Owned Territory | X1: ABN | Y1: 43871 | Z1: Duration
A2: 212 | B2: QLD | C2: Acacia Ridge | D2: Acacia Ridge | E2: Rick | F2: Zammit | G2: - None - | H2: 8 Pathfinder Rd | I2: Coomera | J2: QLD | K2: 4209 | L2: Coomera | M2: QLD | N2: 4209 | O2: AcaciaRidge@mailplus.com.au | P2: Weekly | Q2: Current | R2: 0404 314 375 | S2: 39114 | U2: 1 | V2: Yes | W2: No | X2: 78123031345 | Y2: =IF(S2="","",($Y$1-S2)/365) -> 13.032877 | Z2: 13.032877 | AA2: =IF(Z2="","",ROUNDUP(Z2,0)) -> 14
A3: 694179 | B3: SA | C3: Adelaide CBD | D3: Adelaide CBD | E3: Chentelle | F3: Garreffa | G3: - None - | H3: 19 John Ramsay Cct | I3: Hope Valley | J3: SA | K3: 5090 | L3: Hope Valley | M3: SA | N3: 5090 | O3: AdelaideCBD@mailplus.com.au | P3: Weekly | Q3: Current | R3: 405165103 | S3: 43617 | U3: 1 | V3: Yes | W3: No | X3: 62236853451 | Y3: =IF(S3="","",($Y$1-S3)/365) -> 0.69589041 | Z3: 0.69589041 | AA3: =IF(Z3="","",ROUNDUP(Z3,0)) -> 1
A4: 214 | B4: VIC | C4: Airport West | D4: Airport West | E4: Stephen | F4: Begeman | G4: Unit 1 | H4: 175 Bellevue Ave | I4: Rosanna | J4: VIC | K4: 3084 | L4: Rosanna | M4: VIC | N4: 3084 | O4: AirportWest@mailplus.com.au | P4: End of Month | Q4: Current | R4: 408108775 | S4: 38369 | T4: 43569 | U4: 4 | V4: Yes | W4: No | X4: 93446741190 | Y4: =IF(S4="","",($Y$1-S4)/365) -> 15.073973 | Z4: 15.073973 | AA4: =IF(Z4="","",ROUNDUP(Z4,0)) -> 16
A5: 480439 | B5: NSW | C5: Albury | D5: Albury | E5: Michael | F5: Waite | G5: - None - | H5: 10 Sutton Court | I5: Wodonga | J5: VIC | K5: 3690 | L5: Wodonga | M5: VIC | N5: 3690 | O5: albury@mailplus.com.au | P5: Weekly | Q5: Current | R5: 417421505 | S5: 42826 | U5: 1 | V5: Yes | W5: No | X5: 34176889478 | Y5: =IF(S5="","",($Y$1-S5)/365) -> 2.8630137 | Z5: 2.8630137 | AA5: =IF(Z5="","",ROUNDUP(Z5,0)) -> 3
A6: 215 | B6: NSW | C6: Alexandria | D6: Alexandria | E6: Hendry | F6: Kifa | G6: - None - | H6: 9 Culburra Rd | I6: Miranda | J6: NSW | K6: 2228 | L6: Miranda | M6: NSW | N6: 2228 | O6: Alexandria@mailplus.com.au | P6: Fortnightly | Q6: Current | R6: 421311727 | S6: 37271 | T6: 43569 | U6: 6 | V6: Yes | W6: No | X6: 69111538295 | Y6: =IF(S6="","",($Y$1-S6)/365) -> 18.082192 | Z6: 18.082192 | AA6: =IF(Z6="","",ROUNDUP(Z6,0)) -> 19
A7: 216 | B7: VIC | C7: Altona | D7: Altona | E7: Rhofel | F7: De La Cerna | G7: - None - | H7: 110 Bondi Parade | I7: Point Cook | J7: VIC | K7: 3030 | L7: Point Cook | M7: VIC | N7: 3030 | O7: Altona@mailplus.com.au | P7: Weekly | Q7: Current | R7: 0439 927 388 | S7: 38565 | T7: 39995 | U7: 3 | V7: Yes | W7: No | X7: 75288562937 | Y7: =IF(S7="","",($Y$1-S7)/365) -> 14.536986 | Z7: 14.536986 | AA7: =IF(Z7="","",ROUNDUP(Z7,0)) -> 15
A8: 5386 | B8: NSW | C8: Arncliffe | D8: Arncliffe | E8: Ali | F8: Gasham | G8: - None - | H8: 26 Lansdowne St | I8: Bardwell Valley | J8: NSW | K8: 2207 | L8: Bardwell Valley | M8: NSW | N8: 2207 | O8: Arncliffe@mailplus.com.au | P8: Weekly | Q8: Current | R8: 415775710 | S8: 40238 | T8: 42092 | U8: 4 | V8: Yes | W8: No | X8: 36112969007 | Y8: =IF(S8="","",($Y$1-S8)/365) -> 9.9534247 | Z8: 9.9534247 | AA8: =IF(Z8="","",ROUNDUP(Z8,0)) -> 10
A9: 64113 | B9: QLD | C9: Banyo | D9: Banyo | E9: Bob | F9: Schroeder | G9: 29 Stebbing St | H9: - None - | I9: Aspley | J9: QLD | K9: 4034 | L9: Aspley | M9: QLD | N9: 4034 | O9: banyo@mailplus.com.au | P9: Weekly | Q9: Current | R9: 412309686 | S9: 40513 | T9: 41365 | U9: 3 | V9: Yes | W9: No | X9: 81618161922 | Y9: =IF(S9="","",($Y$1-S9)/365) -> 9.2 | Z9: 9.2 | AA9: =IF(Z9="","",ROUNDUP(Z9,0)) -> 10
A10: 249910 | B10: ACT | C10: Barton | D10: Barton | E10: Saffat | F10: Riad | G10: 20/ | H10: 10 Ovens St | I10: Griffith | J10: ACT | K10: 2603 | L10: Griffith | M10: ACT | N10: 2603 | O10: barton@mailplus.com.au | P10: Weekly | Q10: Current | R10: 433168170 | S10: 42036 | U10: 1 | V10: Yes | W10: No | X10: 75151402845 | Y10: =IF(S10="","",($Y$1-S10)/365) -> 5.0273973 | Z10: 5.0273973 | AA10: =IF(Z10="","",ROUNDUP(Z10,0)) -> 6
A11: 143 | B11: NSW | C11: Baulkham Hills | D11: Baulkham Hills | E11: Paul | F11: Harrison | G11: - None - | H11: 6 Janet St | I11: Bass Hill | J11: NSW | K11: 2197 | L11: Bass Hill | M11: NSW | N11: 2197 | O11: BaulkhamHills@mailplus.com.au | P11: Weekly | Q11: Current | R11: 413691109 | S11: 37054 | T11: 43569 | U11: 5 | V11: Yes | W11: No | X11: 27120656833 | Y11: =IF(S11="","",($Y$1-S11)/365) -> 18.676712 | Z11: 18.676712 | AA11: =IF(Z11="","",ROUNDUP(Z11,0)) -> 19
A12: 404282 | B12: VIC | C12: Bayswater | D12: Bayswater | E12: Jayna | F12: Vakil | G12: - None - | H12: 40 Johnson Dr | I12: Ferntree Gully | J12: VIC | K12: 3156 | L12: Ferntree Gully | M12: VIC | N12: 3156 | O12: bayswater@mailplus.com.au | P12: Weekly | Q12: Current | R12: 451878366 | S12: 42583 | U12: 1 | V12: Yes | W12: No | X12: 62101675321 | Y12: =IF(S12="","",($Y$1-S12)/365) -> 3.5287671 | Z12: 3.5287671 | AA12: =IF(Z12="","",ROUNDUP(Z12,0)) -> 4
A13: 293029 | B13: ACT | C13: Belconnen | D13: Belconnen | E13: Raman | F13: Kumar | G13: 12/ | H13: 6 Antis St | I13: Phillip | J13: ACT | K13: 2606 | L13: Phillip | M13: ACT | N13: 2606 | O13: popie.popie@mailplus.com.au | P13: Weekly | Q13: Current | R13: 490234669 | S13: 42248 | U13: 1 | V13: Yes | W13: No | X13: - None - | Y13: =IF(S13="","",($Y$1-S13)/365) -> 4.4465753 | Z13: 4.4465753 | AA13: =IF(Z13="","",ROUNDUP(Z13,0)) -> 5
A14: 452187 | B14: WA | C14: Belmont | D14: Belmont | E14: Roberto | F14: Bautista | G14: - None - | H14: 91 St Kilda Road | I14: Rivervale | J14: WA | K14: 6103 | L14: Rivervale | M14: WA | N14: 6103 | O14: belmont@mailplus.com.au | P14: Weekly | Q14: Current | R14: 419920057 | S14: 42736 | T14: 43501 | U14: 2 | V14: Yes | W14: No | X14: 19934903153 | Y14: =IF(S14="","",($Y$1-S14)/365) -> 3.109589 | Z14: 3.109589 | AA14: =IF(Z14="","",ROUNDUP(Z14,0)) -> 4
A15: 218 | B15: NSW | C15: Blacktown | D15: Blacktown | E15: Rodney | F15: Eastment | G15: PO Box 537 | H15: - None - | I15: Blacktown | J15: NSW | K15: 2148 | L15: Pitt Town | M15: NSW | N15: 2756 | O15: Blacktown@mailplus.com.au | P15: Fortnightly | Q15: Current | R15: 414712661 | S15: 37291 | T15: 43569 | U15: 5 | V15: Yes | W15: No | X15: 98125713804 | Y15: =IF(S15="","",($Y$1-S15)/365) -> 18.027397 | Z15: 18.027397 | AA15: =IF(Z15="","",ROUNDUP(Z15,0)) -> 19
A16: 219 | B16: NSW | C16: Bondi Junction | D16: Bondi Junction | E16: Katy | F16: Brooks | G16: PO Box 1862 | H16: - None - | I16: Bondi Junction | J16: NSW | K16: 1355 | L16: Waverley | M16: NSW | N16: 2024 | O16: BondiJunction@mailplus.com.au | P16: Weekly | Q16: Current | R16: 409774451 | S16: 36941 | T16: 42081 | U16: 5 | V16: Yes | W16: No | X16: 83200463080 | Y16: =IF(S16="","",($Y$1-S16)/365) -> 18.986301 | Z16: 18.986301 | AA16: =IF(Z16="","",ROUNDUP(Z16,0)) -> 19
A17: 453361 | B17: QLD | C17: Booval | D17: Booval | E17: Kiely | F17: Prendergast | G17: - None - | H17: 22 Abbotsford Parade | I17: Abbottsford | J17: NSW | K17: 2046 | L17: Abbottsford | M17: NSW | N17: 2046 | O17: booval@mailplus.com.au | P17: Weekly | Q17: Current | R17: 432741482 | S17: 42370 | U17: 0 | V17: Yes | W17: No | X17: 99725813659 | Y17: =IF(S17="","",($Y$1-S17)/365) -> 4.1123288 | AA17: =IF(Z17="","",ROUNDUP(Z17,0))
A18: 280 | B18: NSW | C18: Botany Botany | D18: Botany | E18: Richard | F18: Chang | G18: - None - | H18: 45 Siandra Dr | I18: Kareela | J18: NSW | K18: 2232 | L18: Kareela | M18: NSW | N18: 2232 | O18: botany@mailplus.com.au | P18: Weekly | Q18: Current | R18: 0423 194 406 | S18: 39326 | T18: 41365 | U18: 4 | V18: Yes | W18: No | X18: 76206465451 | Y18: =IF(S18="","",($Y$1-S18)/365) -> 12.452055 | Z18: 12.452055 | AA18: =IF(Z18="","",ROUNDUP(Z18,0)) -> 13
A19: 575095 | B19: QLD | C19: Bowen Hills | D19: Bowen Hills | E19: Thomas | F19: Williams | G19: - None - | H19: 4/16 Emuglen Place | I19: Ferny Grove, | J19: QLD | K19: 4055 | L19: Ferny Grove, | M19: QLD | N19: 4055 | O19: bowenhills@mailplus.com.au | P19: Weekly | Q19: Current | R19: 412571657 | S19: 43191 | U19: 1 | V19: Yes | W19: No | X19: 89838503515 | Y19: =IF(S19="","",($Y$1-S19)/365) -> 1.8630137 | Z19: 1.8630137 | AA19: =IF(Z19="","",ROUNDUP(Z19,0)) -> 2
A20: 775289 | B20: VIC | C20: Box Hill | D20: Box Hill | E20: Michael | F20: Debnam | G20: - None - | H20: 164 STATION STREET | I20: ASTENDELE | J20: VIC | K20: 3195 | L20: ASTENDELE | M20: VIC | N20: 3195 | O20: boxhill@mailplus.com.au | P20: Weekly | Q20: Current | R20: 413303978 | S20: 42370 | U20: 0 | V20: Yes | W20: No | X20: 42611258354 | Y20: =IF(S20="","",($Y$1-S20)/365) -> 4.1123288 | AA20: =IF(Z20="","",ROUNDUP(Z20,0))
A21: 220 | B21: VIC | C21: Braeside | D21: Braeside | E21: Sally | F21: Skomrlj | G21: - None - | H21: 44 Harbour Dr | I21: Patterson Lakes | J21: VIC | K21: 3197 | L21: Patterson Lakes | M21: VIC | N21: 3197 | O21: Braeside@mailplus.com.au | P21: Fortnightly | Q21: Current | R21: 0400 456 445 | S21: 38261 | T21: 41912 | U21: 3 | V21: Yes | W21: No | X21: 27942103711 | Y21: =IF(S21="","",($Y$1-S21)/365) -> 15.369863 | Z21: 15.369863 | AA21: =IF(Z21="","",ROUNDUP(Z21,0)) -> 16
A22: 511931 | B22: QLD | C22: Brendale | D22: Brendale | E22: Gregory | F22: Hart | G22: - None - | H22: 2 Rafter Ave | I22: Albany Creek | J22: QLD | K22: 4035 | L22: Albany Creek | M22: QLD | N22: 4035 | O22: brendale@mailplus.com.au | P22: Weekly | Q22: Current | R22: 411417645 | S22: 42979 | U22: 1 | V22: Yes | W22: No | X22: 62664141816 | Y22: =IF(S22="","",($Y$1-S22)/365) -> 2.4438356 | Z22: 2.4438356 | AA22: =IF(Z22="","",ROUNDUP(Z22,0)) -> 3
A23: 696179 | B23: QLD | C23: Brisbane | D23: Brisbane | E23: Michael | F23: MIkits | G23: PO Box 221 | H23: - None - | I23: Surfers Paradise | J23: QLD | K23: 4217 | L23: Surfers Paradise | M23: QLD | N23: 4217 | O23: michael@mailplusbrisbane.com.au | P23: Weekly | Q23: Current | R23: 428224516 | S23: 42370 | U23: 0 | V23: Yes | W23: No | X23: 75226391808 | Y23: =IF(S23="","",($Y$1-S23)/365) -> 4.1123288 | AA23: =IF(Z23="","",ROUNDUP(Z23,0))
A24: 322523 | B24: NSW | C24: Brookvale | D24: Brookvale | E24: Zhi Min | F24: Huang | G24: 174 Terry Street | H24: - None - | I24: Connells Point | J24: NSW | K24: 2221 | L24: Connells Point | M24: NSW | N24: 2221 | O24: brookvale@mailplus.com.au | P24: Weekly | Q24: Current | R24: 415805448 | S24: 42339 | T24: 43569 | U24: 2 | V24: Yes | W24: No | X24: 89397691109 | Y24: =IF(S24="","",($Y$1-S24)/365) -> 4.1972603 | Z24: 4.1972603 | AA24: =IF(Z24="","",ROUNDUP(Z24,0)) -> 5
A25: 206118 | B25: QLD | C25: Browns Plains | D25: Browns Plains | E25: David | F25: Connor | G25: 8 Pendennis Place | H25: - None - | I25: Carindale | J25: QLD | K25: 4152 | L25: Carindale | M25: QLD | N25: 4152 | O25: brownsplains@mailplus.com.au | P25: Weekly | Q25: Current | R25: 0497 229 882 | S25: 41487 | T25: 43312 | U25: 3 | V25: Yes | W25: No | X25: 98819709082 | Y25: =IF(S25="","",($Y$1-S25)/365) -> 6.5315068 | Z25: 6.5315068 | AA25: =IF(Z25="","",ROUNDUP(Z25,0)) -> 7
A26: 219412 | B26: QLD | C26: Burleigh | D26: Burleigh | E26: Maria | F26: Hamilton | G26: PO Box 4851 | H26: - None - | I26: Robina Town Centre | J26: QLD | K26: 4230 | L26: Elanora | M26: QLD | N26: 4221 | O26: burleigh@mailplus.com.au | P26: Weekly | Q26: Current | R26: 409417000 | S26: 41708 | T26: 42622 | U26: 2 | V26: Yes | W26: No | X26: 74107357924 | Y26: =IF(S26="","",($Y$1-S26)/365) -> 5.9260274 | Z26: 5.9260274 | AA26: =IF(Z26="","",ROUNDUP(Z26,0)) -> 6
A27: 794958 | B27: NSW | C27: Byron Bay | D27: Byron Bay | E27: Ratu | F27: Clarke | G27: GPO Box 110 | H27: - None - | I27: Byron Bay | J27: NSW | K27: 2481 | L27: Byron Bay | M27: NSW | N27: 2481 | O27: ByronBay@mailplus.com.au | P27: - None - | Q27: Current | R27: 0405 842 669 | S27: 42370 | U27: 0 | V27: No | W27: Yes | X27: 45609801194 | Y27: =IF(S27="","",($Y$1-S27)/365) -> 4.1123288 | AA27: =IF(Z27="","",ROUNDUP(Z27,0))
A28: 404079 | B28: QLD | C28: Cairns | D28: Cairns | E28: Gary | F28: Chapman | G28: 3/ | H28: 95 Davidson St | I28: Port Douglas | J28: QLD | K28: 4877 | L28: Port Douglas | M28: QLD | N28: 4877 | O28: cairns@mailplus.com.au | P28: Weekly | Q28: Current | R28: 466889307 | S28: 42582 | U28: 1 | V28: Yes | W28: No | X28: 90936120329 | Y28: =IF(S28="","",($Y$1-S28)/365) -> 3.5315068 | Z28: 3.5315068 | AA28: =IF(Z28="","",ROUNDUP(Z28,0)) -> 4
A29: 574991 | B29: VIC | C29: Campbellfield | D29: Campbellfield | E29: Scott | F29: McKay | G29: - None - | H29: 3/11 Edmund Street | I29: Maidstone | J29: VIC | K29: 3012 | L29: Maidstone | M29: VIC | N29: 3012 | O29: campbellfield@mailplus.com.au | P29: Weekly | Q29: Current | R29: 423335131 | S29: 42370 | U29: 0 | V29: Yes | W29: No | X29: 19621840480 | Y29: =IF(S29="","",($Y$1-S29)/365) -> 4.1123288 | AA29: =IF(Z29="","",ROUNDUP(Z29,0))
A30: 1415222 | B30: NSW | C30: Campbelltown | D30: Campbelltown | E30: Khushbu P | F30: Davaria | G30: 1/32 Alfred Street | H30: - None - | I30: Granville | J30: NSW | K30: 2142 | L30: Granville | M30: NSW | N30: 2142 | O30: campbelltown@mailplus.com.au | P30: Weekly | Q30: Current | R30: 474707587 | S30: 42370 | U30: 0 | V30: Yes | W30: No | X30: 34643480577 | Y30: =IF(S30="","",($Y$1-S30)/365) -> 4.1123288 | AA30: =IF(Z30="","",ROUNDUP(Z30,0))
A31: 709359 | B31: ACT | C31: Canberra Airport | D31: Canberra Airport | E31: Syed Lutful | F31: Hakim | G31: - None - | H31: 85 Farran Street | I31: Gungahlin | J31: ACT | K31: 2912 | L31: Gungahlin | M31: ACT | N31: 2912 | O31: canberraairport@mailplus.com.au | P31: Weekly | Q31: Current | R31: 469794938 | S31: 42370 | U31: 0 | V31: Yes | W31: No | X31: 35632341818 | Y31: =IF(S31="","",($Y$1-S31)/365) -> 4.1123288 | AA31: =IF(Z31="","",ROUNDUP(Z31,0))
A32: 753283 | B32: ACT | C32: Canberra CBD | D32: Canberra CBD | E32: Michael | F32: McDaid | G32: GPO Box 586 | H32: - None - | I32: Sydney | J32: NSW | K32: 2000 | L32: Sydney | M32: NSW | N32: 2000 | O32: canberracbd@mailplus.com.au | P32: - None - | Q32: Current | R32: 0420 993 117 | S32: 42370 | U32: 0 | V32: No | W32: Yes | X32: 45609801194 | Y32: =IF(S32="","",($Y$1-S32)/365) -> 4.1123288 | AA32: =IF(Z32="","",ROUNDUP(Z32,0))
A33: 92250 | B33: WA | C33: Canning Vale | D33: Canning Vale | E33: Todd | F33: Ingram | G33: - None - | H33: Unit 3, 16 Coojong Link | I33: Success | J33: WA | K33: 6164 | L33: Success | M33: WA | N33: 6164 | O33: canningvale@mailplus.com.au | P33: Weekly | Q33: Current | R33: 412362537 | S33: 41699 | U33: 1 | V33: Yes | W33: No | X33: 28976700862 | Y33: =IF(S33="","",($Y$1-S33)/365) -> 5.9506849 | Z33: 5.9506849 | AA33: =IF(Z33="","",ROUNDUP(Z33,0)) -> 6
A34: 322524 | B34: VIC | C34: Clayton | D34: Clayton | E34: Devinder | F34: Singh | G34: - None - | H34: 23 Curzon Street | I34: Clyde North | J34: VIC | K34: 3978 | L34: Clyde North | M34: VIC | N34: 3978 | O34: clayton@mailplus.com.au | P34: Weekly | Q34: Current | R34: 433410006 | S34: 42309 | U34: 1 | V34: Yes | W34: No | X34: 45407520164 | Y34: =IF(S34="","",($Y$1-S34)/365) -> 4.2794521 | Z34: 4.2794521 | AA34: =IF(Z34="","",ROUNDUP(Z34,0)) -> 5
A35: 618658 | B35: QLD | C35: Cleveland | D35: Cleveland | E35: Michael | F35: McDaid | G35: GPO Box 586 | H35: - None - | I35: Sydney | J35: NSW | K35: 2000 | L35: Sydney | M35: NSW | N35: 2000 | O35: cleveland@mailplus.com.au | P35: Weekly | Q35: Current | R35: 1300656595 | S35: 42370 | U35: 0 | V35: No | W35: Yes | X35: 45609801194 | Y35: =IF(S35="","",($Y$1-S35)/365) -> 4.1123288 | AA35: =IF(Z35="","",ROUNDUP(Z35,0))
A36: 511913 | B36: NSW | C36: Coffs Harbour | D36: Coffs Harbour | E36: Julie | F36: Southam | G36: GPO Box 586 | H36: - None - | I36: Sydney | J36: NSW | K36: 2001 | L36: Sydney | M36: NSW | N36: 2001 | O36: coffsharbour@mailplus.com.au | P36: - None - | Q36: Current | R36: 416205346 | S36: 42370 | U36: 0 | V36: No | W36: Yes | X36: 45609801194 | Y36: =IF(S36="","",($Y$1-S36)/365) -> 4.1123288 | AA36: =IF(Z36="","",ROUNDUP(Z36,0))
A37: 671787 | B37: NSW | C37: Crows Nest | D37: Crows Nest | E37: Mark | F37: Phua | G37: - None - | H37: 32 Alexandra Street | I37: Hunters Hill | J37: NSW | K37: 2110 | L37: Hunters Hill | M37: NSW | N37: 2110 | O37: CrowsNest@mailplus.com.au | P37: Weekly | Q37: Current | R37: 422488988 | S37: 43556 | U37: 1 | V37: Yes | W37: No | X37: 98629003265 | Y37: =IF(S37="","",($Y$1-S37)/365) -> 0.8630137 | Z37: 0.8630137 | AA37: =IF(Z37="","",ROUNDUP(Z37,0)) -> 1
A38: 287 | B38: VIC | C38: Dandenong | D38: Dandenong | E38: Peter | F38: Sherer | G38: PO Box 5165 | H38: - None - | I38: Hallam | J38: VIC | K38: 3803 | L38: Upper Beaconsfield | M38: VIC | N38: 3808 | O38: dandenong@mailplus.com.au | P38: Weekly | Q38: Current | R38: 408557864 | S38: 38261 | T38: 43569 | U38: 4 | V38: Yes | W38: No | X38: 22006559244 | Y38: =IF(S38="","",($Y$1-S38)/365) -> 15.369863 | Z38: 15.369863 | AA38: =IF(Z38="","",ROUNDUP(Z38,0)) -> 16
A39: 228329 | B39: NSW | C39: Darlinghurst | D39: Darlinghurst | E39: John | F39: Rodao | G39: 8 Toplica Place | H39: - None - | I39: Canley Height | J39: NSW | K39: 2166 | L39: Canley Height | M39: NSW | N39: 2166 | O39: darlinghurst@mailplus.com.au | P39: Weekly | Q39: Current | R39: 414808031 | S39: 41901 | U39: 1 | V39: Yes | W39: No | X39: 79126483672 | Y39: =IF(S39="","",($Y$1-S39)/365) -> 5.3972603 | Z39: 5.3972603 | AA39: =IF(Z39="","",ROUNDUP(Z39,0)) -> 6
A40: 761281 | B40: NT | C40: Darwin | D40: Darwin | E40: S M Roman | F40: Kabir | G40: 82 Dripston Rd | H40: - None - | I40: Nakara | J40: NT | K40: 810 | L40: Nakara | M40: NT | N40: 810 | O40: darwin@mailplus.com.au | P40: Weekly | Q40: Current | R40: 426251103 | S40: 42370 | U40: 0 | V40: Yes | W40: No | X40: 70155020661 | Y40: =IF(S40="","",($Y$1-S40)/365) -> 4.1123288 | AA40: =IF(Z40="","",ROUNDUP(Z40,0))
A41: 546084 | B41: TAS | C41: Devonport | D41: Devonport | E41: Michael | F41: McDaid | G41: GPO Box 586 | H41: - None - | I41: Sydney | J41: NSW | K41: 2001 | L41: Sydney | M41: NSW | N41: 2001 | O41: devonport@mailplus.com.au | P41: - None - | Q41: Current | R41: 364253753 | S41: 42370 | U41: 0 | V41: No | W41: Yes | X41: 45609801194 | Y41: =IF(S41="","",($Y$1-S41)/365) -> 4.1123288 | AA41: =IF(Z41="","",ROUNDUP(Z41,0))
A42: 546083 | B42: NSW | C42: Epping | D42: Epping | E42: Michael | F42: McDaid | G42: GPO Box 586 | H42: - None - | I42: Sydney | J42: NSW | K42: 2001 | L42: Sydney | M42: NSW | N42: 2001 | O42: epping@mailplus.com.au | P42: - None - | Q42: Current | R42: 0426 665 993 | S42: 42370 | U42: 0 | V42: No | W42: Yes | X42: 45609801194 | Y42: =IF(S42="","",($Y$1-S42)/365) -> 4.1123288 | AA42: =IF(Z42="","",ROUNDUP(Z42,0))
A43: 194066 | B43: NSW | C43: Ermington | D43: Ermington | E43: Adel | F43: Chowna | G43: 3 Bittern Grove | H43: - None - | I43: Glenwood | J43: NSW | K43: 2768 | L43: Glenwood | M43: NSW | N43: 2768 | O43: ermington@mailplus.com.au | P43: Weekly | Q43: Current | R43: 421999991 | S43: 41365 | T43: 43025 | U43: 2 | V43: Yes | W43: No | X43: 31739727513 | Y43: =IF(S43="","",($Y$1-S43)/365) -> 6.8657534 | Z43: 6.8657534 | AA43: =IF(Z43="","",ROUNDUP(Z43,0)) -> 7
A44: 423833 | B44: NSW | C44: Fairfield | D44: Fairfield | E44: Francis | F44: Bautista | G44: - None - | H44: 224 Nottinghill Rd | I44: Regents Park | J44: NSW | K44: 2143 | L44: Regents Park | M44: NSW | N44: 2143 | O44: fairfield@mailplus.com.au | P44: Weekly | Q44: Current | R44: 415726350 | S44: 42644 | T44: 42977 | U44: 2 | V44: Yes | W44: No | X44: 42614527589 | Y44: =IF(S44="","",($Y$1-S44)/365) -> 3.3616438 | Z44: 3.3616438 | AA44: =IF(Z44="","",ROUNDUP(Z44,0)) -> 4
A45: 236 | B45: VIC | C45: Geelong | D45: Geelong | E45: Trevor | F45: Nicol | G45: - None - | H45: 182 Grove Rd | I45: Grovedale | J45: VIC | K45: 3216 | L45: Grovedale | M45: VIC | N45: 3216 | O45: Geelong@mailplus.com.au | P45: Weekly | Q45: Current | R45: 417118130 | S45: 39216 | T45: 42868 | U45: 4 | V45: Yes | W45: No | X45: 28598658402 | Y45: =IF(S45="","",($Y$1-S45)/365) -> 12.753425 | Z45: 12.753425 | AA45: =IF(Z45="","",ROUNDUP(Z45,0)) -> 13
A46: 621451 | B46: QLD | C46: Gold Coast | D46: Gold Coast | E46: Nassos | F46: Sofatzis | G46: - None - | H46: 157 Campbell St, | I46: Bundall | J46: QLD | K46: 4217 | L46: Bundall | M46: QLD | N46: 4217 | O46: goldcoast@mailplus.com.au | P46: Weekly | Q46: Current | R46: 437215030 | S46: 43374 | U46: 1 | V46: No | W46: No | X46: 88088348637 | Y46: =IF(S46="","",($Y$1-S46)/365) -> 1.3616438 | Z46: 1.3616438 | AA46: =IF(Z46="","",ROUNDUP(Z46,0)) -> 2
A47: 237 | B47: NSW | C47: Gosford Shire | D47: Gosford Shire | E47: Scott | F47: Mercer | G47: - None - | H47: 43 Kallaroo Rd | I47: Umina Beach | J47: NSW | K47: 2257 | L47: Umina Beach | M47: NSW | N47: 2257 | O47: GosfordShire@mailplus.com.au | P47: Weekly | Q47: Current | R47: 432580704 | S47: 38961 | T47: 42613 | U47: 3 | V47: Yes | W47: No | X47: 38299699742 | Y47: =IF(S47="","",($Y$1-S47)/365) -> 13.452055 | Z47: 13.452055 | AA47: =IF(Z47="","",ROUNDUP(Z47,0)) -> 14
A48: 236188 | B48: VIC | C48: Hallam | D48: Hallam | E48: Stan | F48: Cichorski | G48: 64 Lockwood Road | H48: - None - | I48: Belgrave South | J48: VIC | K48: 3160 | L48: Belgrave South | M48: VIC | N48: 3160 | O48: hallam@mailplus.com.au | P48: Weekly | Q48: Current | R48: 400732448 | S48: 41974 | U48: 1 | V48: Yes | W48: No | X48: 14187870430 | Y48: =IF(S48="","",($Y$1-S48)/365) -> 5.1972603 | Z48: 5.1972603 | AA48: =IF(Z48="","",ROUNDUP(Z48,0)) -> 6
A49: 224358 | B49: VIC | C49: Hawthorn | D49: Hawthorn | E49: Jeff | F49: Hall | G49: 2/ | H49: 48 Foch St | I49: Box Hill South | J49: VIC | K49: 3128 | L49: Box Hill South | M49: VIC | N49: 3128 | O49: hawthorn@mailplus.com.au | P49: Weekly | Q49: Current | R49: 467321696 | S49: 41852 | T49: 43192 | U49: 2 | V49: Yes | W49: No | X49: 12148044713 | Y49: =IF(S49="","",($Y$1-S49)/365) -> 5.5315068 | Z49: 5.5315068 | AA49: =IF(Z49="","",ROUNDUP(Z49,0)) -> 6
A50: 611563 | B50: QLD | C50: Hemmant | D50: Hemmant | E50: Greg | F50: Hart | G50: - None - | H50: 2 Rafter Ave | I50: Albany Creek | J50: QLD | K50: 4035 | L50: Albany Creek | M50: QLD | N50: 4035 | O50: hemmant@mailplus.com.au | P50: Weekly | Q50: Current | R50: 411417645 | S50: 43374 | U50: 1 | V50: No | W50: No | X50: 62664141816 | Y50: =IF(S50="","",($Y$1-S50)/365) -> 1.3616438 | Z50: 1.3616438 | AA50: =IF(Z50="","",ROUNDUP(Z50,0)) -> 2
A51: 243 | B51: TAS | C51: Hobart | D51: Hobart | E51: Greg | F51: Wells | G51: - None - | H51: 37 Joshua St | I51: Mornington | J51: TAS | K51: 7018 | L51: Mornington | M51: TAS | N51: 7018 | O51: Hobart@mailplus.com.au | P51: Weekly | Q51: Current | R51: 424630938 | S51: 39295 | T51: 43569 | U51: 3 | V51: Yes | W51: No | X51: 46198674774 | Y51: =IF(S51="","",($Y$1-S51)/365) -> 12.536986 | Z51: 12.536986 | AA51: =IF(Z51="","",ROUNDUP(Z51,0)) -> 13
A52: 244 | B52: NSW | C52: Homebush | D52: Homebush | E52: Ken | F52: Sealey | G52: - None - | H52: 7 Wendy Ave | I52: Georges Hall | J52: NSW | K52: 2198 | L52: Georges Hall | M52: NSW | N52: 2198 | O52: homebush@mailplus.com.au | P52: Weekly | Q52: Current | R52: 0417 062 490 | S52: 39461 | T52: 43569 | U52: 4 | V52: Yes | W52: No | X52: 45986078751 | Y52: =IF(S52="","",($Y$1-S52)/365) -> 12.082192 | Z52: 12.082192 | AA52: =IF(Z52="","",ROUNDUP(Z52,0)) -> 13
A53: 322525 | B53: VIC | C53: Hoppers Crossing | D53: Hoppers Crossing | E53: Meral | F53: Murgoski | G53: - None - | H53: 25 Redcliffe Terrace | I53: Taylors Hill | J53: VIC | K53: 3037 | L53: Taylors Hill | M53: VIC | N53: 3037 | O53: hopperscrossing@mailplus.com.au | P53: Weekly | Q53: Current | R53: 0413 766 473 | S53: 42370 | T53: 42704 | U53: 2 | V53: Yes | W53: No | X53: 51810073311 | Y53: =IF(S53="","",($Y$1-S53)/365) -> 4.1123288 | Z53: 4.1123288 | AA53: =IF(Z53="","",ROUNDUP(Z53,0)) -> 5
A54: 186329 | B54: NSW | C54: Hunter Valley | D54: Hunter Valley | E54: Jason | F54: Dorricott | G54: - None - | H54: 34 Kahibah Rd | I54: Waratah | J54: NSW | K54: 2298 | L54: Waratah | M54: NSW | N54: 2298 | O54: huntervalley@mailplus.com.au | P54: Weekly | Q54: Current | R54: 0419 262 149 | S54: 41153 | U54: 1 | V54: Yes | W54: No | X54: 95158213426 | Y54: =IF(S54="","",($Y$1-S54)/365) -> 7.4465753 | Z54: 7.4465753 | AA54: =IF(Z54="","",ROUNDUP(Z54,0)) -> 8
A55: 713275 | B55: NSW | C55: Illawarra | D55: Illawarra | E55: Mathew | F55: Barnes | G55: - None - | H55: 10 Pleasant View Cl | I55: Albion Park | J55: NSW | K55: 2527 | L55: Albion Park | M55: NSW | N55: 2527 | O55: Illawarra@mailplus.com.au | P55: Weekly | Q55: Current | R55: 423657492 | S55: 43709 | U55: 1 | V55: Yes | W55: No | X55: 50113864109 | Y55: =IF(S55="","",($Y$1-S55)/365) -> 0.44383562 | Z55: 0.44383562 | AA55: =IF(Z55="","",ROUNDUP(Z55,0)) -> 1
A56: 575773 | B56: QLD | C56: Ipswich | D56: Ipswich | E56: Michael | F56: McDaid | G56: GPO Box 586 | H56: - None - | I56: Sydney | J56: NSW | K56: 2001 | L56: Sydney | M56: NSW | N56: 2001 | O56: Ipswich@mailplus.com.au | P56: - None - | Q56: Current | R56: 1300656594 | S56: 42370 | U56: 0 | V56: No | W56: Yes | X56: 45609801194 | Y56: =IF(S56="","",($Y$1-S56)/365) -> 4.1123288 | AA56: =IF(Z56="","",ROUNDUP(Z56,0))
A57: 246 | B57: QLD | C57: Jones Jones | D57: Jones | E57: Ellen | F57: Jones | G57: PO Box 822 | H57: - None - | I57: Albany Creek | J57: QLD | K57: 4035 | L57: Albany Creek | M57: QLD | N57: 4035 | O57: Jones@mailplus.com.au | P57: Weekly | Q57: Current | R57: 412910493 | S57: 38261 | T57: 43069 | U57: 5 | V57: Yes | W57: No | X57: 50821366100 | Y57: =IF(S57="","",($Y$1-S57)/365) -> 15.369863 | Z57: 15.369863 | AA57: =IF(Z57="","",ROUNDUP(Z57,0)) -> 16
A58: 433571 | B58: WA | C58: Kewdale | D58: Kewdale | E58: Roque | F58: Bautista | G58: - None - | H58: 91 St Kilda Rd | I58: Rivervale | J58: WA | K58: 6103 | L58: Rivervale | M58: WA | N58: 6103 | O58: kewdale@mailplus.com.au | P58: Weekly | Q58: Current | R58: 455269367 | S58: 43039 | U58: 1 | V58: Yes | W58: No | X58: 68167013523 | Y58: =IF(S58="","",($Y$1-S58)/365) -> 2.2794521 | Z58: 2.2794521 | AA58: =IF(Z58="","",ROUNDUP(Z58,0)) -> 3
A59: 247 | B59: VIC | C59: Lalor | D59: Lalor | E59: Chris | F59: Sarbin | G59: - None - | H59: 4 Corvette Cl | I59: South Morang | J59: VIC | K59: 3752 | L59: South Morang | M59: VIC | N59: 3752 | O59: Lalor@mailplus.com.au | P59: Weekly | Q59: Current | R59: 0417 128 665 | S59: 39264 | T59: 42916 | U59: 5 | V59: Yes | W59: No | X59: 46022856217 | Y59: =IF(S59="","",($Y$1-S59)/365) -> 12.621918 | Z59: 12.621918 | AA59: =IF(Z59="","",ROUNDUP(Z59,0)) -> 13
A60: 554481 | B60: NSW | C60: Lane Cove | D60: Lane Cove | E60: Jason | F60: Yang | G60: - None - | H60: 32 Alexandra St | I60: Hunters Hill | J60: NSW | K60: 2110 | L60: Hunters Hill | M60: NSW | N60: 2110 | O60: lanecove@mailplus.com.au | P60: Weekly | Q60: Current | R60: 422488988 | S60: 43132 | T60: 43569 | U60: 3 | V60: Yes | W60: No | X60: 97617518788 | Y60: =IF(S60="","",($Y$1-S60)/365) -> 2.0246575 | Z60: 2.0246575 | AA60: =IF(Z60="","",ROUNDUP(Z60,0)) -> 3
A61: 261 | B61: QLD | C61: Lane Lane | D61: Lane | E61: Phillip | F61: Lane | G61: - None - | H61: 4 Shiral Ct | I61: Camira | J61: QLD | K61: 4300 | L61: Camira | M61: QLD | N61: 4300 | O61: Lane@mailplus.com.au | P61: Weekly | Q61: Current | R61: 404089155 | S61: 38261 | T61: 43039 | U61: 4 | V61: Yes | W61: No | X61: 75627453998 | Y61: =IF(S61="","",($Y$1-S61)/365) -> 15.369863 | Z61: 15.369863 | AA61: =IF(Z61="","",ROUNDUP(Z61,0)) -> 16
A62: 249 | B62: TAS | C62: Launceston | D62: Launceston | E62: Brett | F62: Young | G62: - None - | H62: 22 Button St | I62: Mowbray | J62: TAS | K62: 7248 | L62: Mowbray | M62: TAS | N62: 7248 | O62: Launceston@mailplus.com.au | P62: Weekly | Q62: Current | R62: 0438 265 809 | S62: 39359 | T62: 41186 | U62: 2 | V62: Yes | W62: No | X62: 52265018779 | Y62: =IF(S62="","",($Y$1-S62)/365) -> 12.361644 | Z62: 12.361644 | AA62: =IF(Z62="","",ROUNDUP(Z62,0)) -> 13
A63: 250 | B63: NSW | C63: Liverpool | D63: Liverpool | E63: Abbas | F63: Abdallah | G63: - None - | H63: 6 Alt St | I63: Smithfield | J63: NSW | K63: 2164 | L63: Smithfield | M63: NSW | N63: 2164 | O63: Liverpool@mailplus.com.au | P63: Weekly | Q63: Current | R63: 405193600 | S63: 38215 | T63: 39995 | U63: 4 | V63: Yes | W63: No | X63: 58611344275 | Y63: =IF(S63="","",($Y$1-S63)/365) -> 15.49589 | Z63: 15.49589 | AA63: =IF(Z63="","",ROUNDUP(Z63,0)) -> 16
A64: 512991 | B64: QLD | C64: Mackay | D64: Mackay | E64: Michael | F64: Wainscott | G64: GPO Box 586 | H64: - None - | I64: Sydney | J64: NSW | K64: 2001 | L64: Sydney | M64: NSW | N64: 2001 | O64: mackay@mailplus.com.au | P64: - None - | Q64: Current | R64: 1300656595 | S64: 42370 | U64: 0 | V64: No | W64: Yes | X64: 45609801194 | Y64: =IF(S64="","",($Y$1-S64)/365) -> 4.1123288 | AA64: =IF(Z64="","",ROUNDUP(Z64,0))
A65: 251 | B65: NSW | C65: Macquarie Park | D65: Macquarie Park | E65: Sleiman (Simon) | F65: Aoukar | G65: - None - | H65: 2 Morotai Cres | I65: Castlecrag | J65: NSW | K65: 2068 | L65: Castlecrag | M65: NSW | N65: 2068 | O65: MacquariePark@mailplus.com.au | P65: Weekly | Q65: Current | R65: 0404 042 759 | S65: 38384 | T65: 40210 | U65: 3 | V65: Yes | W65: No | X65: 95180369836 | Y65: =IF(S65="","",($Y$1-S65)/365) -> 15.032877 | Z65: 15.032877 | AA65: =IF(Z65="","",ROUNDUP(Z65,0)) -> 16
A66: 435 | B66: NSW | C66: Mailplus Pty Ltd | D66: Mailplus Pty Ltd | E66: Mail | F66: Plus | G66: - None - | H66: - None - | I66: Sydney | J66: NSW | K66: 2001 | L66: Sydney | M66: NSW | N66: 2001 | O66: MailPlusPtyLtd@mailplus.com.au | P66: Weekly | Q66: Current | R66: 0414 899 089 | S66: 42370 | U66: 0 | V66: No | W66: Yes | X66: 45609801194 | Y66: =IF(S66="","",($Y$1-S66)/365) -> 4.1123288 | AA66: =IF(Z66="","",ROUNDUP(Z66,0))
A67: 253 | B67: NSW | C67: Mascot | D67: Mascot | E67: Rohit | F67: Hegde | G67: 3 CLOVER PLACE | H67: 3 Clover Pl | I67: The Ponds | J67: NSW | K67: 2769 | L67: The Ponds | M67: NSW | N67: 2769 | O67: mascot@mailplus.com.au | P67: End of Month | Q67: Current | R67: 0400 223 883 | S67: 37910 | T67: 39995 | U67: 3 | V67: Yes | W67: No | X67: 11449611014 | Y67: =IF(S67="","",($Y$1-S67)/365) -> 16.331507 | Z67: 16.331507 | AA67: =IF(Z67="","",ROUNDUP(Z67,0)) -> 17
A68: 228330 | B68: VIC | C68: Melbourne CBD | D68: Melbourne CBD | E68: Alistair | F68: Wright | G68: 284 Esplanade East | H68: - None - | I68: Port Melbourne | J68: VIC | K68: 3207 | L68: Port Melbourne | M68: VIC | N68: 3207 | O68: melbournecbd@mailplus.com.au | P68: Weekly | Q68: Current | R68: 430742003 | S68: 41886 | U68: 1 | V68: Yes | W68: No | X68: 61749602449 | Y68: =IF(S68="","",($Y$1-S68)/365) -> 5.4383562 | Z68: 5.4383562 | AA68: =IF(Z68="","",ROUNDUP(Z68,0)) -> 6
A69: 186104 | B69: NSW | C69: Milperra | D69: Milperra | E69: Sam | F69: Li | G69: - None - | H69: 31 Demaine Ave | I69: Bexley North | J69: NSW | K69: 2207 | L69: Bexley North | M69: NSW | N69: 2207 | O69: milperra@mailplus.com.au | P69: Weekly | Q69: Current | R69: 468796995 | S69: 41183 | T69: 41365 | U69: 4 | V69: Yes | W69: No | X69: 33940189103 | Y69: =IF(S69="","",($Y$1-S69)/365) -> 7.3643836 | Z69: 7.3643836 | AA69: =IF(Z69="","",ROUNDUP(Z69,0)) -> 8
A70: 216885 | B70: VIC | C70: Moorabbin | D70: Moorabbin | E70: David | F70: Hicks | G70: Unit 1 | H70: 26 Service St | I70: Hampton | J70: VIC | K70: 3188 | L70: Hampton | M70: VIC | N70: 3188 | O70: Moorabbin@mailplus.com.au | P70: Weekly | Q70: Current | R70: 0421 388 529 | S70: 41699 | U70: 1 | V70: Yes | W70: No | X70: 90972843283 | Y70: =IF(S70="","",($Y$1-S70)/365) -> 5.9506849 | Z70: 5.9506849 | AA70: =IF(Z70="","",ROUNDUP(Z70,0)) -> 6
A71: 503764 | B71: NSW | C71: Moorebank | D71: Moorebank | E71: Giuseppe | F71: Filippello | G71: G. & M. TRANSPORT CO. PTY. LTD | H71: 51A Lovoni St | I71: Cabramatta | J71: NSW | K71: 2166 | L71: Cabramatta | M71: NSW | N71: 2166 | O71: moorebank@mailplus.com.au | P71: Weekly | Q71: Current | R71: 423202749 | S71: 42948 | U71: 2 | V71: Yes | W71: No | X71: 81620034479 | Y71: =IF(S71="","",($Y$1-S71)/365) -> 2.5287671 | Z71: 2.5287671 | AA71: =IF(Z71="","",ROUNDUP(Z71,0)) -> 3
A72: 499036 | B72: QLD | C72: Morningside | D72: Morningside | E72: Greg | F72: Hart | G72: - None - | H72: 2 Rafter Ave | I72: Albany Creek | J72: QLD | K72: 4035 | L72: Albany Creek | M72: QLD | N72: 4035 | O72: morningside@mailplus.com.au | P72: Weekly | Q72: Current | R72: 411417645 | S72: 42948 | U72: 1 | V72: Yes | W72: No | X72: 62664141816 | Y72: =IF(S72="","",($Y$1-S72)/365) -> 2.5287671 | Z72: 2.5287671 | AA72: =IF(Z72="","",ROUNDUP(Z72,0)) -> 3
A73: 264 | B73: QLD | C73: Mount Gravatt | D73: Mount Gravatt | E73: Rick | F73: Zammit | G73: 8 Pathfinder Road | H73: 31 Dreamworld Pkwy | I73: Coomera | J73: QLD | K73: 4209 | L73: Coomera | M73: QLD | N73: 4209 | O73: AcaciaRidge@mailplus.com.au | P73: Weekly | Q73: Current | R73: 0404 314 375 | S73: 39114 | T73: 41498 | U73: 3 | V73: Yes | W73: No | X73: 78123031345 | Y73: =IF(S73="","",($Y$1-S73)/365) -> 13.032877 | Z73: 13.032877 | AA73: =IF(Z73="","",ROUNDUP(Z73,0)) -> 14
A74: 259 | B74: VIC | C74: Mount Waverley | D74: Mount Waverley | E74: Erik | F74: Kusnadi | G74: PO Box 159 | H74: - None - | I74: Glen Waverley | J74: VIC | K74: 3150 | L74: Glen Waverley | M74: VIC | N74: 3150 | O74: MountWaverley@mailplus.com.au | P74: Weekly | Q74: Current | R74: 411277162 | S74: 38418 | T74: 43569 | U74: 4 | V74: Yes | W74: No | X74: 87341485653 | Y74: =IF(S74="","",($Y$1-S74)/365) -> 14.939726 | Z74: 14.939726 | AA74: =IF(Z74="","",ROUNDUP(Z74,0)) -> 15
A75: 194183 | B75: VIC | C75: Mulgrave | D75: Mulgrave | E75: Jason | F75: Knight | G75: - None - | H75: Unit 207, 1A Finch Street | I75: Malvern East | J75: VIC | K75: 3145 | L75: Malvern East | M75: VIC | N75: 3145 | O75: mulgrave@mailplus.com.au | P75: Weekly | Q75: Current | R75: 448252766 | S75: 41365 | T75: 43569 | U75: 3 | V75: Yes | W75: No | X75: 89392175829 | Y75: =IF(S75="","",($Y$1-S75)/365) -> 6.8657534 | Z75: 6.8657534 | AA75: =IF(Z75="","",ROUNDUP(Z75,0)) -> 7
A76: 518791 | B76: QLD | C76: Murarrie | D76: Murarrie | E76: Colin | F76: Paynter | G76: Unit 1 | H76: 180-182 Thorneside | I76: Thorneside | J76: QLD | K76: 4158 | L76: Thorneside | M76: QLD | N76: 4158 | O76: murarrie@mailplus.com.au | P76: Weekly | Q76: Current | R76: 402402354 | S76: 42370 | U76: 0 | V76: Yes | W76: No | X76: 22621304694 | Y76: =IF(S76="","",($Y$1-S76)/365) -> 4.1123288 | AA76: =IF(Z76="","",ROUNDUP(Z76,0))
A77: 1257846 | B77: QLD | C77: Nerang | D77: Nerang | E77: Greg | F77: Hart | G77: GPO Box 586 | H77: - None - | I77: Sydney | J77: NSW | K77: 2001 | L77: Sydney | M77: NSW | N77: 2001 | O77: greg.hart@mailplus.com.au | P77: - None - | Q77: Current | R77: 411417645 | S77: 42370 | U77: 0 | V77: No | W77: Yes | X77: 45609801194 | Y77: =IF(S77="","",($Y$1-S77)/365) -> 4.1123288 | AA77: =IF(Z77="","",ROUNDUP(Z77,0))
A78: 192117 | B78: NSW | C78: Newcastle | D78: Newcastle | E78: Craig | F78: Goodsir | G78: 4 Gillian St | H78: - None - | I78: Kotora South | J78: NSW | K78: 2289 | L78: Kotara South | M78: NSW | N78: 2289 | O78: newcastle@mailplus.com.au | P78: Weekly | Q78: Current | R78: 418115649 | S78: 41334 | U78: 3 | V78: Yes | W78: No | X78: 50161504696 | Y78: =IF(S78="","",($Y$1-S78)/365) -> 6.9506849 | Z78: 6.9506849 | AA78: =IF(Z78="","",ROUNDUP(Z78,0)) -> 7
A79: 696173 | B79: QLD | C79: North Lakes | D79: North Lakes | E79: Mohinder Kumar | F79: Yadav | G79: 214/1 Bass Court | H79: North Lakes | I79: - None - | J79: QLD | K79: 4509 | L79: - None - | M79: QLD | N79: 4509 | O79: northlakes@mailplus.com.au | P79: Weekly | Q79: Current | R79: 405934299 | S79: 43647 | U79: 1 | V79: Yes | W79: No | X79: 58631099888 | Y79: =IF(S79="","",($Y$1-S79)/365) -> 0.61369863 | Z79: 0.61369863 | AA79: =IF(Z79="","",ROUNDUP(Z79,0)) -> 1
A80: 679437 | B80: VIC | C80: North Melbourne | D80: North Melbourne | E80: Roger John | F80: Smith | G80: - None - | H80: 7 Beachley St | I80: Braybrook | J80: VIC | K80: 3019 | L80: Braybrook | M80: VIC | N80: 3019 | O80: NorthMelbourne@mailplus.com.au | P80: Weekly | Q80: Current | R80: 431118857 | S80: 43586 | U80: 1 | V80: Yes | W80: No | X80: 14151268106 | Y80: =IF(S80="","",($Y$1-S80)/365) -> 0.78082192 | Z80: 0.78082192 | AA80: =IF(Z80="","",ROUNDUP(Z80,0)) -> 1
A81: 671776 | B81: NSW | C81: North Sydney | D81: North Sydney | E81: Jason | F81: Young | G81: - None - | H81: 32 Alexandra Street | I81: Hunters Hill | J81: NSW | K81: 2110 | L81: Hunters Hill | M81: NSW | N81: 2110 | O81: northsydney@mailplus.com.au | P81: Weekly | Q81: Current | R81: 0422 488 988 | S81: 42370 | U81: 0 | V81: Yes | W81: No | X81: 98629003265 | Y81: =IF(S81="","",($Y$1-S81)/365) -> 4.1123288 | AA81: =IF(Z81="","",ROUNDUP(Z81,0))
A82: 270 | B82: NSW | C82: Northern Beaches | D82: Northern Beaches | E82: Roger | F82: Turner | G82: - None - | H82: 1 Ocean Rd | I82: Manly | J82: NSW | K82: 2095 | L82: Manly | M82: NSW | N82: 2095 | O82: NorthernBeaches@mailplus.com.au | P82: Weekly | Q82: Current | R82: 422946966 | S82: 38899 | T82: 41365 | U82: 4 | V82: Yes | W82: No | X82: 57321954069 | Y82: =IF(S82="","",($Y$1-S82)/365) -> 13.621918 | Z82: 13.621918 | AA82: =IF(Z82="","",ROUNDUP(Z82,0)) -> 14
A83: 5377 | B83: WA | C83: Osborne Park | D83: Osborne Park | E83: Nick | F83: Fahie | G83: PO Box 17 | H83: - None - | I83: West Perth | J83: WA | K83: 6872 | L83: Bedford | M83: WA | N83: 6052 | O83: OsbornePark@mailplus.com.au | P83: Weekly | Q83: Current | R83: 409775680 | S83: 40148 | U83: 3 | V83: Yes | W83: No | X83: 54144568883 | Y83: =IF(S83="","",($Y$1-S83)/365) -> 10.2 | Z83: 10.2 | AA83: =IF(Z83="","",ROUNDUP(Z83,0)) -> 11
A84: 271 | B84: NSW | C84: Parramatta | D84: Parramatta | E84: Simon | F84: Hoatson | G84: PO Box 600 | H84: - None - | I84: Parramatta | J84: NSW | K84: 2124 | L84: Leichhardt | M84: NSW | N84: 2040 | O84: Parramatta@mailplus.com.au | P84: Weekly | Q84: Current | R84: 412055023 | S84: 37529 | T84: 41365 | U84: 5 | V84: Yes | W84: No | X84: 97101929391 | Y84: =IF(S84="","",($Y$1-S84)/365) -> 17.375342 | Z84: 17.375342 | AA84: =IF(Z84="","",ROUNDUP(Z84,0)) -> 18
A85: 273 | B85: NSW | C85: Peninsula | D85: Peninsula | E85: Christina | F85: Turner | G85: 1 Ocean Road | H85: - None - | I85: Manly | J85: NSW | K85: 2095 | L85: Manly | M85: NSW | N85: 2095 | O85: NorthernBeaches@mailplus.com.au | P85: Weekly | Q85: Current | R85: 422946966 | S85: 39264 | T85: 43569 | U85: 5 | V85: Yes | W85: No | X85: 17871819479 | Y85: =IF(S85="","",($Y$1-S85)/365) -> 12.621918 | Z85: 12.621918 | AA85: =IF(Z85="","",ROUNDUP(Z85,0)) -> 13
A86: 192134 | B86: NSW | C86: Penrith | D86: Penrith | E86: Robert | F86: Marlow | G86: - None - | H86: 58 Ladbury Ave | I86: Penrith | J86: NSW | K86: 2750 | L86: Penrith | M86: NSW | N86: 2750 | O86: Penrith@mailplus.com.au | P86: Weekly | Q86: Current | R86: 425248676 | S86: 41334 | T86: 42063 | U86: 2 | V86: Yes | W86: No | X86: 80795717584 | Y86: =IF(S86="","",($Y$1-S86)/365) -> 6.9506849 | Z86: 6.9506849 | AA86: =IF(Z86="","",ROUNDUP(Z86,0)) -> 7
A87: 490139 | B87: WA | C87: Perth CBD | D87: Perth CBD | E87: Jobin | F87: Mathew Pathickal | G87: - None - | H87: 52 Fruit Tree Crescent | I87: Forrestfield | J87: WA | K87: 6058 | L87: Forrestfield | M87: WA | N87: 6058 | O87: perthcbd@mailplus.com.au | P87: Weekly | Q87: Current | R87: 410184034 | S87: 42887 | U87: 1 | V87: Yes | W87: No | X87: 42714637704 | Y87: =IF(S87="","",($Y$1-S87)/365) -> 2.6958904 | Z87: 2.6958904 | AA87: =IF(Z87="","",ROUNDUP(Z87,0)) -> 3
A88: 180312 | B88: VIC | C88: Port Melbourne Port Melbourne | D88: Port Melbourne | E88: Roger | F88: Smith | G88: - None - | H88: 22 Malvern Ave | I88: Glen Iris | J88: VIC | K88: 3146 | L88: Glen Iris | M88: VIC | N88: 3146 | O88: portmelbourne@mailplus.com.au | P88: Weekly | Q88: Current | R88: 433918518 | S88: 41030 | U88: 2 | V88: Yes | W88: No | X88: 12156284481 | Y88: =IF(S88="","",($Y$1-S88)/365) -> 7.7835616 | Z88: 7.7835616 | AA88: =IF(Z88="","",ROUNDUP(Z88,0)) -> 8
A89: 375597 | B89: VIC | C89: Preston | D89: Preston | E89: Michael | F89: Debnam | G89: 164 STATION STREET | H89: ASTENDELE | I89: MELBOURNE | J89: VIC | K89: 3195 | L89: MELBOURNE | M89: VIC | N89: 3195 | O89: Preston@mailplus.com.au | P89: Weekly | Q89: Current | R89: 413303978 | S89: 42491 | U89: 1 | V89: Yes | W89: No | X89: 42611258354 | Y89: =IF(S89="","",($Y$1-S89)/365) -> 3.7808219 | Z89: 3.7808219 | AA89: =IF(Z89="","",ROUNDUP(Z89,0)) -> 4
A90: 277 | B90: NSW | C90: Pyrmont | D90: Pyrmont | E90: Budi | F90: Nagi | G90: 17 Hawthorne St | H90: - None - | I90: Ramsgate Beach | J90: NSW | K90: 2217 | L90: Ramsgate Beach | M90: NSW | N90: 2217 | O90: Pyrmont@mailplus.com.au | P90: Weekly | Q90: Current | R90: 433232323 | S90: 38838 | T90: 42617 | U90: 4 | V90: Yes | W90: No | X90: 59028214631 | Y90: =IF(S90="","",($Y$1-S90)/365) -> 13.789041 | Z90: 13.789041 | AA90: =IF(Z90="","",ROUNDUP(Z90,0)) -> 14
A91: 39107 | B91: SA | C91: Regency | D91: Regency | E91: Ken | F91: Smith | G91: PO Box 85 | H91: - None - | I91: Brooklyn Park | J91: SA | K91: 5032 | L91: Underdale | M91: SA | N91: 5032 | O91: regency@mailplus.com.au | P91: Weekly | Q91: Current | R91: 0439 900 840 | S91: 40299 | T91: 43221 | U91: 3 | V91: Yes | W91: No | X91: 55246395694 | Y91: =IF(S91="","",($Y$1-S91)/365) -> 9.7863014 | Z91: 9.7863014 | AA91: =IF(Z91="","",ROUNDUP(Z91,0)) -> 10
A92: 184320 | B92: VIC | C92: Riverside | D92: Riverside | E92: Gary | F92: Jakubowicz | G92: Unit 5/307 | H92: New Street | I92: Brighton | J92: VIC | K92: 3186 | L92: Brighton | M92: VIC | N92: 3186 | O92: riverside@mailplus.com.au | P92: Weekly | Q92: Current | R92: 0425 765 270 | S92: 41122 | T92: 41365 | U92: 3 | V92: Yes | W92: No | X92: 25006340914 | Y92: =IF(S92="","",($Y$1-S92)/365) -> 7.5315068 | Z92: 7.5315068 | AA92: =IF(Z92="","",ROUNDUP(Z92,0)) -> 8
A93: 221718 | B93: QLD | C93: Rockhampton | D93: Rockhampton | E93: Don | F93: Atfield | G93: PO Box 1859 | H93: - None - | I93: Rockhampton city | J93: QLD | K93: 4700 | L93: Rockyview | M93: QLD | N93: 4701 | O93: rockhampton@mailplus.com.au | P93: Weekly | Q93: Current | R93: 416974480 | S93: 41760 | U93: 1 | V93: Yes | W93: No | X93: 52168769202 | Y93: =IF(S93="","",($Y$1-S93)/365) -> 5.7835616 | Z93: 5.7835616 | AA93: =IF(Z93="","",ROUNDUP(Z93,0)) -> 6
A94: 282 | B94: QLD | C94: Rocklea | D94: Rocklea | E94: Ross | F94: Smith | G94: Unit 6/ 6 Grenier Street | H94: - None - | I94: Tingalpa | J94: QLD | K94: 4173 | L94: Tingalpa | M94: QLD | N94: 4173 | O94: Rocklea@mailplus.com.au | P94: Weekly | Q94: Current | R94: 438821410 | S94: 39326 | T94: 42978 | U94: 5 | V94: Yes | W94: No | X94: 67371212100 | Y94: =IF(S94="","",($Y$1-S94)/365) -> 12.452055 | Z94: 12.452055 | AA94: =IF(Z94="","",ROUNDUP(Z94,0)) -> 13
A95: 700097 | B95: NSW | C95: Rosebery | D95: Rosebery | E95: Paul | F95: Lingwood | G95: GPO Box 586 | H95: - None - | I95: Sydney | J95: NSW | K95: 2001 | L95: Sydney | M95: NSW | N95: 2001 | O95: rosebery@mailplus.com.au | P95: - None - | Q95: Current | R95: 449700779 | S95: 42370 | U95: 0 | V95: No | W95: Yes | X95: 45609801194 | Y95: =IF(S95="","",($Y$1-S95)/365) -> 4.1123288 | AA95: =IF(Z95="","",ROUNDUP(Z95,0))
A96: 632438 | B96: NSW | C96: Rouse Hill | D96: Rouse Hill | E96: Animesh | F96: Castgir | G96: - None - | H96: 18 Townsend Rd | I96: North Richmond | J96: NSW | K96: 2754 | L96: North Richmond | M96: NSW | N96: 2754 | O96: RouseHill@mailplus.com.au | P96: Weekly | Q96: Current | R96: 404631721 | S96: 43405 | U96: 1 | V96: No | W96: No | X96: 94814228776 | Y96: =IF(S96="","",($Y$1-S96)/365) -> 1.2767123 | Z96: 1.2767123 | AA96: =IF(Z96="","",ROUNDUP(Z96,0)) -> 2
A97: 119988 | B97: NSW | C97: Ryde | D97: Ryde | E97: John | F97: Chan | G97: 3/14-16 Holley Road | H97: - None - | I97: Beverly Hills | J97: NSW | K97: 2209 | L97: Beverly Hills | M97: NSW | N97: 2209 | O97: ryde@mailplus.com.au | P97: Weekly | Q97: Current | R97: 0410 331 383 | S97: 40787 | T97: 43908 | U97: 4 | V97: Yes | W97: No | X97: 70727291650 | Y97: =IF(S97="","",($Y$1-S97)/365) -> 8.4493151 | Z97: 8.4493151 | AA97: =IF(Z97="","",ROUNDUP(Z97,0)) -> 9
A98: 486680 | B98: QLD | C98: Salisbury | D98: Salisbury | E98: James | F98: Yat Nam Ng | G98: - None - | H98: 1 Justora Street | I98: Rochedale South | J98: QLD | K98: 4123 | L98: Rochedale South | M98: QLD | N98: 4123 | O98: salisbury@mailplus.com.au | P98: End of Month | Q98: Current | R98: 421559588 | S98: 42887 | U98: 2 | V98: Yes | W98: No | X98: 95618396393 | Y98: =IF(S98="","",($Y$1-S98)/365) -> 2.6958904 | Z98: 2.6958904 | AA98: =IF(Z98="","",ROUNDUP(Z98,0)) -> 3
A99: 285 | B99: VIC | C99: Scoresby | D99: Scoresby | E99: David | F99: Kosky | G99: PO Box 392 | H99: - None - | I99: Ferntree Gully | J99: VIC | K99: 3156 | L99: Upper Ferntree Gully | M99: VIC | N99: 3156 | O99: Scoresby@mailplus.com.au | P99: Weekly | Q99: Current | R99: 0416 206 354 | S99: 38579 | T99: 39995 | U99: 4 | V99: Yes | W99: No | X99: 30131812372 | Y99: =IF(S99="","",($Y$1-S99)/365) -> 14.49863 | Z99: 14.49863 | AA99: =IF(Z99="","",ROUNDUP(Z99,0)) -> 15
A100: 656637 | B100: VIC | C100: Seaford | D100: Seaford | E100: Ian | F100: Kenna | G100: - None - | H100: 3 Homevale Drive | I100: Botanic Ridge | J100: VIC | K100: 3977 | L100: Botanic Ridge | M100: VIC | N100: 3977 | O100: seaford@mailplus.com.au | P100: Weekly | Q100: Current | R100: 402709140 | S100: 42370 | U100: 0 | V100: No | W100: No | X100: 77354387056 | Y100: =IF(S100="","",($Y$1-S100)/365) -> 4.1123288 | AA100: =IF(Z100="","",ROUNDUP(Z100,0))
...

Sheet Revenue @ Feb 2021
A1: Acacia Ridge | B1: 97298.54
A2: Adelaide CBD | B2: 161374.01
A3: Airport West | B3: 113990.49
A4: Albury | B4: 12981
A5: Alexandria | B5: 121031.34
A6: Altona | B6: 134658
A7: Arncliffe | B7: 107791.13
A8: Banyo | B8: 83599.26
A9: Barton | B9: 47125.17
A10: Baulkham Hills | B10: 183340.24
A11: Bayswater | B11: 59641.45
A12: Belmont | B12: 56049.27
... A132: Grand Total | B132: 15560889

Sheet Bondi 
A2: Franchisee | B2: Bondi Junction
A3: Franchisee Name | B3: Katy Brooks
A4: State | B4: NSW
A5: Profile
A6: Expiry Date | B6: 43909
A7: Ultimate Expiry Date (Including FY18 release) | B7: 47926
A8: Unlimted Term | B8: Yes
A9: Annual Turnover (service revenue) | B9: =VLOOKUP(B2,'[4]Revenue by Franchisee'!#REF!,2,0) -> #REF!
A10: Number of customers
A11: Number of customer using MPEX
A12: Digisitation | B12: YES
A13: Not in attendance at Roadshow | B13: NO
A14: Workshop Attendance | B14: YES
A15: Reading weekly bulletins(After final reminder) | B15: YES
A16: Customer Nomination | B16: NO
A17: MPEX allocation | B17: YES
A18: MPEX Usage % (as @ 08102019) | B18: =VLOOKUP(B2,'Franchisee Ranking'!#REF!,6,0) -> #REF!
A19: Late with completion of monthly invoicing | B19: NO
A20: Approved vehicle | B20: YES
A21: Vehicle signage (Past 4 years) | B21: YES
A22: Uniform (ordered in past 12months) | B22: ?
A23: HO Insurances | B23: YES
A24: 30th Sept action email (Feedback)

Sheet Scorecard summary
A1: Franchise | B1: Unlimited term candidated | C1: Franchisee Name | D1: State | E1: Profile | F1: Tenure | G1: Expiry Date | H1: FY22 Term candidate | I1: Ultimate Expiry Date (Including FY18 release) | J1: Unlimted Term | K1: Annual Turnover (service revenue) | L1: Digisitation | M1: Not in attendance at Roadshow | N1: Workshop Attendance | O1: Reading weekly bulletins(After final reminder) | P1: Customer Nomination | Q1: MPEX allocation | R1: MPEX Usage % (as @ 08102019) | S1: Late with completion of monthly invoicing | T1: Approved vehicle | U1: Vehicle signage (Past 4 years) | V1: Uniform (ordered in past 12months) | W1: HO Insurances | X1: 30th Sept action email (Feedback) | Y1: Terminated (mutually or otherwise) | Z1: Breach notice served | AA1: Written warning issued | AB1: commentary
A2: Coffs (HO Owned) | C2: MailPlus Head Office | D2: NSW | E2: N/A | F2: N/A | G2: N/A | I2: N/A | J2: HEAD OFFICE | K2: =VLOOKUP(A2,'Revenue @ Feb 2021'!A:B,2,0) -> #N/A | L2: YES | M2: YES | N2: YES | O2: YES | P2: NO | Q2: NO | S2: NO | T2: ? | U2: ? | V2: ? | W2: NO
A3: Devonport (HO Owned) | C3: MailPlus Head Office | D3: TAS | E3: N/A | F3: N/A | G3: N/A | I3: N/A | J3: HEAD OFFICE | K3: =VLOOKUP(A3,'Revenue @ Feb 2021'!A:B,2,0) -> #N/A | L3: YES | M3: YES | N3: YES | O3: YES | P3: NO | Q3: NO | S3: NO | T3: ? | U3: ? | V3: ? | W3: NO
A4: Epping (HO Owned) | C4: MailPlus Head Office | D4: NSW | E4: N/A | F4: N/A | G4: N/A | I4: N/A | J4: HEAD OFFICE | K4: =VLOOKUP(A4,'Revenue @ Feb 2021'!A:B,2,0) -> #N/A | L4: YES | M4: YES | N4: YES | O4: YES | P4: NO | Q4: NO | S4: NO | T4: ? | U4: ? | V4: ? | W4: NO
A5: Ipswich (HO Owned) | C5: MailPlus Head Office | D5: QLD | E5: N/A | F5: N/A | G5: N/A | I5: N/A | J5: HEAD OFFICE | K5: =VLOOKUP(A5,'Revenue @ Feb 2021'!A:B,2,0) -> #N/A | L5: YES | M5: YES | N5: YES | O5: YES | P5: NO | Q5: NO | S5: NO | T5: ? | U5: ? | V5: ? | W5: NO
A6: Mackay (HO Owned) | C6: MailPlus Head Office | D6: QLD | E6: N/A | F6: N/A | G6: N/A | I6: N/A | J6: HEAD OFFICE | K6: =VLOOKUP(A6,'Revenue @ Feb 2021'!A:B,2,0) -> #N/A | L6: YES | M6: YES | N6: YES | O6: YES | P6: NO | Q6: NO | S6: NO | T6: ? | U6: ? | V6: ? | W6: NO
A7: Townsville (HO Owned) | C7: MailPlus Head Office | D7: QLD | E7: N/A | F7: N/A | G7: N/A | I7: N/A | J7: HEAD OFFICE | K7: =VLOOKUP(A7,'Revenue @ Feb 2021'!A:B,2,0) -> #N/A | L7: YES | M7: YES | N7: YES | O7: YES | P7: NO | Q7: NO | S7: NO | T7: ? | U7: ? | V7: ? | W7: NO
A8: Rockhampton (HO Operated/owned) | C8: MailPlus Head Office | D8: QLD | E8: N/A | F8: N/A | G8: N/A | I8: N/A | J8: HEAD OFFICE | K8: =VLOOKUP(A8,'Revenue @ Feb 2021'!A:B,2,0) -> #N/A | L8: NO | M8: YES | N8: YES | O8: YES | P8: NO | Q8: NO | S8: NO | T8: ? | U8: ? | V8: ? | W8: YES
A9: Canberra CBD | C9: MailPlus Head Office | D9: ACT | E9: N/A | F9: N/A | G9: 43864 | I9: 45691 | J9: Yes | K9: =VLOOKUP(A9,'Revenue @ Feb 2021'!A:B,2,0) -> 81771.37 | L9: YES | M9: NO | N9: YES | O9: YES | P9: NO | Q9: YES | R9: =VLOOKUP(A9,'Franchisee Ranking'!B:G,6,0) -> 0 | S9: NO | T9: ? | U9: ? | V9: ? | W9: YES
A10: Waterloo | B10: Yes | C10: MailPlus Head Office | D10: NSW | E10: N/A | F10: N/A | G10: 44408 | I10: 48060 | J10: NO | K10: 120771 | L10: YES | M10: YES | N10: YES | O10: YES | P10: NO | Q10: YES | R10: =VLOOKUP(A10,'Franchisee Ranking'!B:H,6,0) -> 0.44736842 | S10: No | T10: Yes | U10: No | V10: Yes | W10: N/A | Y10: N/A | Z10: N/A | AA10: N/A | AB10: Engaged & professional operator
A11: Rosebery | C11: MailPlus Head Office | D11: NSW | E11: N/A | F11: N/A | G11: 44276 | I11: 47928 | J11: NO | K11: =VLOOKUP(A11,'Revenue @ Feb 2021'!A:B,2,0) -> 40915.75 | L11: YES | M11: YES | N11: YES | O11: YES | P11: NO | Q11: YES | R11: =VLOOKUP(A11,'Franchisee Ranking'!B:G,6,0) -> 0.16666667 | S11: NO | T11: ? | U11: ? | V11: ? | W11: YES
A12: Nerang | C12: MailPlus Head Office | D12: QLD | E12: N/A | F12: N/A | G12: 43649 | I12: 45476 | J12: Yes | K12: =VLOOKUP(A12,'Revenue @ Feb 2021'!A:B,2,0) -> 28649.89 | L12: NO | M12: NO | N12: NO | O12: YES | P12: NO | Q12: NO | R12: =VLOOKUP(A12,'Franchisee Ranking'!B:G,6,0) -> 0 | S12: NO | T12: ? | U12: ? | V12: Yes | W12: YES | Y12: Yes | Z12: Yes | AA12: Yes | AB12: Repeated unprofessional road conduct/manner
A13: Byron Bay | C13: MailPlus Head Office | D13: NSW | E13: N/A | F13: N/A | G13: 44287 | I13: 46113 | J13: NO | K13: =VLOOKUP(A13,'Revenue @ Feb 2021'!A:B,2,0) -> 5005.87 | L13: YES | M13: YES | N13: YES | O13: YES | P13: NO | Q13: YES | R13: =VLOOKUP(A13,'Franchisee Ranking'!B:G,6,0) -> 0 | S13: NO | T13: ? | U13: ? | V13: ? | W13: NO
A14: Bondi Junction | C14: Katy Brooks | D14: NSW | E14: Investor | F14: =VLOOKUP(A14,[3]ActiveFranchiseesResults465!$C:$AA,25,0) -> 19 | G14: 43909 | I14: 47926 | J14: Yes | K14: =VLOOKUP(A14,'Revenue @ Feb 2021'!A:B,2,0) -> 249625.42 | L14: YES | M14: NO | N14: YES | O14: YES | P14: NO | Q14: YES | R14: =VLOOKUP(A14,'Franchisee Ranking'!B:G,6,0) -> 0 | S14: NO | T14: YES | U14: YES | V14: ? | W14: YES
A15: Baulkham Hills | C15: Paul Harrison | D15: NSW | E15: Owner operator | F15: =VLOOKUP(A15,[3]ActiveFranchiseesResults465!$C:$AA,25,0) -> 19 | G15: 43994 | I15: 45820 | J15: Yes | K15: =VLOOKUP(A15,'Revenue @ Feb 2021'!A:B,2,0) -> 183340.24 | L15: YES | M15: YES | N15: YES | O15: YES | P15: NO | Q15: YES | R15: =VLOOKUP(A15,'Franchisee Ranking'!B:G,6,0) -> 0.19230769 | S15: NO | T15: ? | U15: ? | V15: ? | W15: YES | X15: Been waiting on sales support….....
A16: Blacktown | C16: Rodney Eastment | D16: NSW | E16: Owner operator | F16: =VLOOKUP(A16,[3]ActiveFranchiseesResults465!$C:$AA,25,0) -> 19 | G16: 43862 | I16: 46784 | J16: Yes | K16: =VLOOKUP(A16,'Revenue @ Feb 2021'!A:B,2,0) -> 170178.75 | L16: YES | M16: YES | N16: YES | O16: YES | P16: YES | Q16: YES | R16: =VLOOKUP(A16,'Franchisee Ranking'!B:H,6,0) -> 0.18032787 | S16: NO | T16: ? | U16: ? | V16: ? | W16: YES
A17: Wetherill Park | C17: Madhukar Prasad | D17: NSW | E17: Owner operator | F17: =VLOOKUP(A17,[3]ActiveFranchiseesResults465!$C:$AA,25,0) -> 19 | G17: 45455 | I17: 45820 | J17: Yes | K17: =VLOOKUP(A17,'Revenue @ Feb 2021'!A:B,2,0) -> 168688.02 | L17: YES | M17: YES | N17: YES | O17: YES | P17: NO | Q17: YES | R17: =VLOOKUP(A17,'Franchisee Ranking'!B:G,6,0) -> 0 | S17: NO | T17: YES | U17: YES | V17: ? | W17: YES | X17: Waiting on Stacey to provide feedback on his migration call down….
A18: Alexandria | C18: Hendry Kifa | D18: NSW | E18: Owner operator | F18: =VLOOKUP(A18,[3]ActiveFranchiseesResults465!$C:$AA,25,0) -> 19 | G18: 43845 | I18: 46767 | J18: Yes | K18: =VLOOKUP(A18,'Revenue @ Feb 2021'!A:B,2,0) -> 121031.34 | L18: YES | M18: YES | N18: YES | O18: YES | P18: NO | Q18: YES | R18: =VLOOKUP(A18,'Franchisee Ranking'!B:G,6,0) -> 0.3875 | S18: NO | T18: YES | U18: YES | V18: Yes | W18: YES
A19: Parramatta | C19: Simon Hoatson | D19: NSW | E19: Investor | F19: =VLOOKUP(A19,[3]ActiveFranchiseesResults465!$C:$AA,25,0) -> 18 | G19: 43738 | I19: 47026 | J19: Yes | K19: =VLOOKUP(A19,'Revenue @ Feb 2021'!A:B,2,0) -> 271059.75 | L19: YES | M19: YES | N19: YES | O19: YES | P19: YES | Q19: YES | R19: =VLOOKUP(A19,'Franchisee Ranking'!B:H,6,0) -> 0.21176471 | S19: NO | T19: ? | U19: ? | V19: ? | W19: YES
A20: Mascot | C20: Rohit Hegde | D20: NSW | E20: Owner operator | F20: =VLOOKUP(A20,[3]ActiveFranchiseesResults465!$C:$AA,25,0) -> 17 | G20: 44276 | H20: Yes | I20: 47928 | J20: NO | K20: =VLOOKUP(A20,'Revenue @ Feb 2021'!A:B,2,0) -> 120118.77 | L20: YES | M20: YES | N20: YES | O20: YES | P20: NO | Q20: YES | R20: =VLOOKUP(A20,'Franchisee Ranking'!B:G,6,0) -> 0.27118644 | S20: Yes | T20: YES | U20: YES | V20: ? | W20: NO
A21: Tappenden Tappenden | C21: Allison Tappenden | D21: QLD | E21: Owner operator | F21: =VLOOKUP(A21,[3]ActiveFranchiseesResults465!$C:$AA,25,0) -> 16 | G21: 43709 | I21: 46997 | J21: Yes | K21: =VLOOKUP(A21,'Revenue @ Feb 2021'!A:B,2,0) -> 195336.58 | L21: NO | M21: YES | N21: NO | O21: YES | P21: NO | Q21: NO | R21: =VLOOKUP(A21,'Franchisee Ranking'!B:G,6,0) -> 0 | S21: NO | T21: ? | U21: ? | V21: ? | W21: YES | X21: Hostile reply - blaming anyone & everyone
A22: Lane Lane | C22: Philip Lane | D22: QLD | E22: Owner operator | F22: =VLOOKUP(A22,[3]ActiveFranchiseesResults465!$C:$AA,25,0) -> 16 | G22: 44865 | I22: 45961 | J22: yes | K22: =VLOOKUP(A22,'Revenue @ Feb 2021'!A:B,2,0) -> 194972 | L22: YES | M22: YES | N22: NO | O22: YES | P22: YES | Q22: YES | R22: =VLOOKUP(A22,'Franchisee Ranking'!B:G,6,0) -> 0.02739726 | S22: NO | T22: ? | U22: ? | V22: ? | W22: YES | X22: Very difficult to manage - knocked back multiple DX points
A23: Dandenong | C23: Peter Sherer | D23: VIC | E23: Owner operator | F23: =VLOOKUP(A23,[3]ActiveFranchiseesResults465!$C:$AA,25,0) -> 16 | G23: 43897 | I23: 45723 | J23: Yes | K23: =VLOOKUP(A23,'Revenue @ Feb 2021'!A:B,2,0) -> 174421.39 | L23: YES | M23: YES | N23: YES | O23: YES | P23: YES | Q23: YES | R23: =VLOOKUP(A23,'Franchisee Ranking'!B:H,6,0) -> 0.14285714 | S23: NO | T23: YES | U23: YES | V23: ? | W23: YES
A24: Macquarie Park | C24: Sleiman Aoukar | D24: NSW | E24: Owner operator | F24: =VLOOKUP(A24,[3]ActiveFranchiseesResults465!$C:$AA,25,0) -> 16 | G24: 43862 | I24: 45689 | J24: yes | K24: =VLOOKUP(A24,'Revenue @ Feb 2021'!A:B,2,0) -> 167098.57 | L24: YES | M24: YES | N24: YES | O24: YES | P24: YES | Q24: YES | R24: =VLOOKUP(A24,'Franchisee Ranking'!B:H,6,0) -> 0.34285714 | S24: NO | T24: ? | U24: ? | V24: Yes | W24: YES
A25: Jones Jones | C25: Ellen Jones / Allan Jones | D25: QLD | E25: Owner operator | F25: =VLOOKUP(A25,[3]ActiveFranchiseesResults465!$C:$AA,25,0) -> 16 | G25: 43830 | I25: 47118 | J25: Yes | K25: =VLOOKUP(A25,'Revenue @ Feb 2021'!A:B,2,0) -> 148284.51 | L25: YES | M25: NO | N25: YES | O25: YES | P25: NO | Q25: YES | R25: =VLOOKUP(A25,'Franchisee Ranking'!B:G,6,0) -> 0.0125 | S25: NO | T25: ? | U25: ? | V25: ? | W25: YES | X25: Sales rep never called back to arrange customer call down
A26: Airport West | C26: Stebe Begeman | D26: VIC | E26: Owner operator | F26: =VLOOKUP(A26,[3]ActiveFranchiseesResults465!$C:$AA,25,0) -> 16 | G26: 43847 | I26: 45674 | J26: Yes | K26: =VLOOKUP(A26,'Revenue @ Feb 2021'!A:B,2,0) -> 113990.49 | L26: YES | M26: YES | N26: YES | O26: YES | P26: YES | Q26: YES | R26: =VLOOKUP(A26,'Franchisee Ranking'!B:H,6,0) -> 0.38596491 | S26: NO | T26: ? | U26: ? | V26: Yes | W26: YES
A27: Trinh TRINH | C27: Quan Trin | D27: QLD | E27: Owner operator | F27: =VLOOKUP(A27,[3]ActiveFranchiseesResults465!$C:$AA,25,0) -> 16 | G27: 43709 | H27: Yes | I27: 46997 | J27: NO | K27: =VLOOKUP(A27,'Revenue @ Feb 2021'!A:B,2,0) -> 110576.14 | L27: YES | M27: YES | N27: YES | O27: YES | P27: YES | Q27: YES | R27: =VLOOKUP(A27,'Franchisee Ranking'!B:G,6,0) -> 0 | S27: NO | T27: ? | U27: ? | V27: ? | W27: YES
A28: Braeside | C28: Sally Skomrlj | D28: VIC | E28: Owner operator | F28: =VLOOKUP(A28,[3]ActiveFranchiseesResults465!$C:$AA,25,0) -> 16 | G28: 45565 | H28: Yes | I28: 49217 | J28: NO | K28: =VLOOKUP(A28,'Revenue @ Feb 2021'!A:B,2,0) -> 102705.26 | L28: YES | M28: NO | N28: YES | O28: YES | P28: NO | Q28: YES | R28: =VLOOKUP(A28,'Franchisee Ranking'!B:H,6,0) -> 0.47222222 | S28: NO | T28: ? | U28: ? | V28: Yes | W28: YES
A29: St Kilda Road | C29: Zhao Yang Lin | D29: VIC | E29: Owner operator | F29: =VLOOKUP(A29,[3]ActiveFranchiseesResults465!$C:$AA,25,0) -> 16 | G29: 43847 | I29: 46769 | J29: Yes | K29: =VLOOKUP(A29,'Revenue @ Feb 2021'!A:B,2,0) -> 91613.22 | L29: YES | M29: YES | N29: YES | O29: YES | P29: YES | Q29: YES | R29: =VLOOKUP(A29,'Franchisee Ranking'!B:H,6,0) -> 0.22222222 | S29: NO | T29: ? | U29: ? | V29: Yes | W29: YES
A30: Liverpool | C30: Abbas Abou Abdallah | D30: NSW | E30: Owner operator | F30: =VLOOKUP(A30,[3]ActiveFranchiseesResults465!$C:$AA,25,0) -> 16 | G30: 43693 | I30: 45520 | J30: Yes | K30: =VLOOKUP(A30,'Revenue @ Feb 2021'!A:B,2,0) -> 72390.06 | L30: YES | M30: YES | N30: YES | O30: YES | P30: NO | Q30: YES | R30: =VLOOKUP(A30,'Franchisee Ranking'!B:G,6,0) -> 0.3125 | S30: NO | T30: YES | U30: YES | V30: ? | W30: YES | X30: 75% of customers have MPEX - usage still low
A31: Altona | C31: Rofel Del LaCerna | D31: VIC | E31: Investor | F31: =VLOOKUP(A31,[3]ActiveFranchiseesResults465!$C:$AA,25,0) -> 15 | G31: 43678 | H31: Yes | I31: 45505 | J31: NO | K31: =VLOOKUP(A31,'Revenue @ Feb 2021'!A:B,2,0) -> 134658 | L31: YES | M31: NO | N31: YES | O31: NO | P31: NO | Q31: YES | R31: =VLOOKUP(A31,'Franchisee Ranking'!B:G,6,0) -> 0.1025641 | S31: NO | T31: ? | U31: ? | V31: ? | W31: YES | X31: Reply email appears he's continuing to stall
A32: Scoresby | C32: David Kosky | D32: VIC | E32: Owner operator | F32: =VLOOKUP(A32,[3]ActiveFranchiseesResults465!$C:$AA,25,0) -> 15 | G32: 43692 | I32: 45519 | J32: Yes | K32: =VLOOKUP(A32,'Revenue @ Feb 2021'!A:B,2,0) -> 96589.66 | L32: YES | M32: YES | N32: YES | O32: YES | P32: NO | Q32: YES | R32: =VLOOKUP(A32,'Franchisee Ranking'!B:G,6,0) -> 0.60465116 | S32: NO | T32: YES | U32: YES | V32: Yes | W32: NO
A33: Mount Waverley | C33: Erik Kusnadi | D33: VIC | E33: Owner operator | F33: =VLOOKUP(A33,[3]ActiveFranchiseesResults465!$C:$AA,25,0) -> 15 | G33: 43897 | I33: 45723 | J33: Yes | K33: =VLOOKUP(A33,'Revenue @ Feb 2021'!A:B,2,0) -> 43450.17 | L33: YES | M33: YES | N33: YES | O33: YES | P33: YES | Q33: NO | R33: =VLOOKUP(A33,'Franchisee Ranking'!B:H,6,0) -> 0.40909091 | S33: NO | T33: ? | U33: ? | V33: ? | W33: YES
A34: Pyrmont | C34: Budi Nagi | D34: NSW | E34: Investor | F34: =VLOOKUP(A34,[3]ActiveFranchiseesResults465!$C:$AA,25,0) -> 14 | G34: 44442 | I34: 46268 | J34: Yes | K34: =VLOOKUP(A34,'Revenue @ Feb 2021'!A:B,2,0) -> 176495.12 | L34: NO | M34: YES | N34: YES | O34: YES | P34: YES | Q34: YES | R34: =VLOOKUP(A34,'Franchisee Ranking'!B:G,6,0) -> 0 | S34: NO | T34: ? | U34: ? | V34: ? | W34: YES | X34: No reply | Z34: Yes | AA34: Yes | AB34: non completion of digitization task
A35: Mount Gravatt | C35: Rick Zammit | D35: QLD | E35: Owner operator | F35: =VLOOKUP(A35,[3]ActiveFranchiseesResults465!$C:$AA,25,0) -> 14 | G35: 45139 | I35: 46977 | J35: yes | K35: =VLOOKUP(A35,'Revenue @ Feb 2021'!A:B,2,0) -> 139063.89 | L35: YES | M35: YES | N35: YES | O35: YES | P35: NO | Q35: NO | R35: =VLOOKUP(A35,'Franchisee Ranking'!B:G,6,0) -> 0.15151515 | S35: NO | T35: ? | U35: ? | V35: Yes | W35: NO
A36: Gosford Shire | C36: Scott Mercer | D36: NSW | E36: Owner operator | F36: =VLOOKUP(A36,[3]ActiveFranchiseesResults465!$C:$AA,25,0) -> 14 | G36: 44440 | I36: 44440 | J36: Yes | K36: =VLOOKUP(A36,'Revenue @ Feb 2021'!A:B,2,0) -> 138522.06 | L36: YES | M36: YES | N36: YES | O36: NO | P36: NO | Q36: YES | R36: =VLOOKUP(A36,'Franchisee Ranking'!B:G,6,0) -> 0.17910448 | S36: NO | T36: YES | U36: YES | V36: ? | W36: YES
A37: Northern Beaches | C37: Roger Turner | D37: NSW | E37: Owner operator | F37: =VLOOKUP(A37,[3]ActiveFranchiseesResults465!$C:$AA,25,0) -> 14 | G37: 43647 | I37: 46935 | J37: yes | K37: =VLOOKUP(A37,'Revenue @ Feb 2021'!A:B,2,0) -> 132551.44 | L37: YES | M37: YES | N37: YES | O37: YES | P37: YES | Q37: YES | R37: =VLOOKUP(A37,'Franchisee Ranking'!B:H,6,0) -> 0.35849057 | S37: NO | T37: YES | U37: YES | V37: Yes | W37: YES
A38: Acacia Ridge | C38: Rick Zammit | D38: QLD | E38: Owner operator | F38: =VLOOKUP(A38,[3]ActiveFranchiseesResults465!$C:$AA,25,0) -> 14 | G38: 45151 | I38: 46966 | J38: yes | K38: =VLOOKUP(A38,'Revenue @ Feb 2021'!A:B,2,0) -> 97298.54 | L38: YES | M38: YES | N38: YES | O38: YES | P38: NO | Q38: YES | R38: =VLOOKUP(A38,'Franchisee Ranking'!B:G,6,0) -> 0.098039216 | S38: NO | T38: ? | U38: ? | V38: Yes | W38: YES
A39: Botany Botany | C39: Richard Chang | D39: NSW | E39: Owner operator | F39: =VLOOKUP(A39,[3]ActiveFranchiseesResults465!$C:$AA,25,0) -> 13 | G39: 43709 | I39: 46997 | J39: Yes | K39: =VLOOKUP(A39,'Revenue @ Feb 2021'!A:B,2,0) -> 193802.5 | L39: YES | M39: YES | N39: YES | O39: YES | P39: YES | Q39: YES | R39: =VLOOKUP(A39,'Franchisee Ranking'!B:H,6,0) -> 0.13043478 | S39: NO | T39: YES | U39: YES | V39: ? | W39: YES | X39: Can't seem to get usage trending up despite doing all the right things
A40: South Bank | C40: Jason Baldwin | D40: QLD | E40: Owner operator | F40: =VLOOKUP(A40,[3]ActiveFranchiseesResults465!$C:$AA,25,0) -> 13 | G40: 44774 | I40: 45870 | J40: Yes | K40: =VLOOKUP(A40,'Revenue @ Feb 2021'!A:B,2,0) -> 175332.66 | L40: NO | M40: YES | N40: NO | O40: YES | P40: YES | Q40: YES | R40: =VLOOKUP(A40,'Franchisee Ranking'!B:G,6,0) -> 0.056818182 | S40: Yes | T40: ? | U40: ? | V40: ? | W40: YES | X40: No reply
A41: Homebush | C41: Ken Sealey | D41: NSW | E41: Investor | F41: =VLOOKUP(A41,[3]ActiveFranchiseesResults465!$C:$AA,25,0) -> 13 | G41: 43844 | I41: 45671 | J41: Yes | K41: =VLOOKUP(A41,'Revenue @ Feb 2021'!A:B,2,0) -> 152472.22 | L41: YES | M41: YES | N41: YES | O41: YES | P41: YES | Q41: YES | R41: =VLOOKUP(A41,'Franchisee Ranking'!B:G,6,0) -> 0.016666667 | S41: NO | T41: YES | U41: YES | V41: ? | W41: YES | X41: Didn't reply - seems very disengaged since selling his other franchises
A42: Geelong | C42: Trevor Nicol | D42: VIC | E42: Owner operator | F42: =VLOOKUP(A42,[3]ActiveFranchiseesResults465!$C:$AA,25,0) -> 13 | G42: 44695 | I42: 46521 | J42: Yes | K42: =VLOOKUP(A42,'Revenue @ Feb 2021'!A:B,2,0) -> 110751.73 | L42: YES | M42: YES | N42: YES | O42: YES | P42: NO | Q42: YES | R42: =VLOOKUP(A42,'Franchisee Ranking'!B:G,6,0) -> 0.016129032 | S42: NO | T42: ? | U42: ? | V42: ? | W42: YES | X42: Family health issues & APP dowload problems were reasons for delay
A43: Lalor | C43: Chris Sarbin | D43: VIC | E43: Owner operator | F43: =VLOOKUP(A43,[3]ActiveFranchiseesResults465!$C:$AA,25,0) -> 13 | G43: 44743 | I43: 46569 | J43: Yes | K43: =VLOOKUP(A43,'Revenue @ Feb 2021'!A:B,2,0) -> 92733.17 | L43: YES | M43: YES | N43: YES | O43: YES | P43: NO | Q43: YES | R43: =VLOOKUP(A43,'Franchisee Ranking'!B:G,6,0) -> 0.18367347 | S43: NO | T43: ? | U43: ? | V43: ? | W43: NO
A44: Rocklea | C44: Matthew Smith | D44: QLD | E44: Owner operator | F44: =VLOOKUP(A44,[3]ActiveFranchiseesResults465!$C:$AA,25,0) -> 13 | G44: 44803 | I44: 46629 | J44: Yes | K44: =VLOOKUP(A44,'Revenue @ Feb 2021'!A:B,2,0) -> 90218.85 | L44: YES | M44: YES | N44: YES | O44: YES | P44: NO | Q44: YES | R44: =VLOOKUP(A44,'Franchisee Ranking'!B:G,6,0) -> 0.17073171 | S44: NO | T44: ? | U44: ? | V44: Yes | W44: YES
A45: Hobart | C45: Greg Wells | D45: TAS | E45: Owner operator | F45: =VLOOKUP(A45,[3]ActiveFranchiseesResults465!$C:$AA,25,0) -> 13 | I45: 44774 | J45: Yes | K45: =VLOOKUP(A45,'Revenue @ Feb 2021'!A:B,2,0) -> 67417.5 | L45: NO | M45: NO | N45: YES | O45: YES | P45: NO | Q45: YES | R45: =VLOOKUP(A45,'Franchisee Ranking'!B:G,6,0) -> 0.024390244 | S45: NO | T45: ? | U45: ? | V45: ? | W45: NO | X45: Had van issues which delayed roll out but appears to be positive
A46: Launceston | C46: Brett Young | D46: TAS | E46: Owner operator | F46: =VLOOKUP(A46,[3]ActiveFranchiseesResults465!$C:$AA,25,0) -> 13 | I46: 44838 | J46: Yes | K46: =VLOOKUP(A46,'Revenue @ Feb 2021'!A:B,2,0) -> 52617.36 | L46: YES | M46: YES | N46: YES | O46: YES | P46: YES | Q46: YES | R46: =VLOOKUP(A46,'Franchisee Ranking'!B:H,6,0) -> 0.058823529 | S46: NO | T46: ? | U46: ? | V46: ? | W46: YES
A47: Peninsula | C47: Roger Turner | D47: NSW | E47: Owner operator | F47: =VLOOKUP(A47,[3]ActiveFranchiseesResults465!$C:$AA,25,0) -> 13 | G47: 43647 | I47: 46935 | J47: Yes | K47: =VLOOKUP(A47,'Revenue @ Feb 2021'!A:B,2,0) -> 29012.58 | L47: YES | M47: YES | N47: YES | O47: YES | P47: NO | Q47: YES | R47: =VLOOKUP(A47,'Franchisee Ranking'!B:G,6,0) -> 0.27272727 | S47: NO | T47: YES | U47: YES | V47: ? | W47: YES
A48: Springwood | C48: Rick Zammit | D48: QLD | E48: Owner operator | F48: =VLOOKUP(A48,[3]ActiveFranchiseesResults465!$C:$AA,25,0) -> 12 | G48: 45139 | I48: 46966 | J48: yes | K48: =VLOOKUP(A48,'Revenue @ Feb 2021'!A:B,2,0) -> 113282.92 | L48: YES | M48: YES | N48: YES | O48: YES | P48: NO | Q48: NO | R48: =VLOOKUP(A48,'Franchisee Ranking'!B:G,6,0) -> 0 | S48: NO | T48: ? | U48: ? | V48: ? | W48: YES
A49: Willoughby | C49: Peter Hayes | D49: NSW | E49: Owner operator | F49: =VLOOKUP(A49,[3]ActiveFranchiseesResults465!$C:$AA,25,0) -> 11 | G49: 43586 | I49: 45413 | J49: Yes | K49: =VLOOKUP(A49,'Revenue @ Feb 2021'!A:B,2,0) -> 167507.73 | L49: YES | M49: YES | N49: YES | O49: YES | P49: YES | Q49: YES | R49: =VLOOKUP(A49,'Franchisee Ranking'!B:H,6,0) -> 0.23611111 | S49: NO | T49: YES | U49: YES | V49: ? | W49: YES
A50: Osborne Park | C50: Nick Fahie | D50: WA | E50: Owner operator | F50: =VLOOKUP(A50,[3]ActiveFranchiseesResults465!$C:$AA,25,0) -> 11 | G50: 43800 | I50: 45627 | J50: Yes | K50: =VLOOKUP(A50,'Revenue @ Feb 2021'!A:B,2,0) -> 141260.31 | L50: YES | M50: YES | N50: YES | O50: YES | P50: YES | Q50: YES | R50: =VLOOKUP(A50,'Franchisee Ranking'!B:H,6,0) -> 0 | S50: NO | T50: ? | U50: ? | V50: ? | W50: YES
A51: St Marys | C51: Jeshnil Prasad | D51: NSW | E51: Owner operator | F51: =VLOOKUP(A51,[3]ActiveFranchiseesResults465!$C:$AA,25,0) -> 11 | G51: 43866 | I51: 45693 | J51: Yes | K51: =VLOOKUP(A51,'Revenue @ Feb 2021'!A:B,2,0) -> 124192.48 | L51: YES | M51: YES | N51: YES | O51: NO | P51: NO | Q51: YES | R51: =VLOOKUP(A51,'Franchisee Ranking'!B:G,6,0) -> 0.015384615 | S51: NO | T51: ? | U51: ? | V51: ? | W51: YES | X51: Looking to exit - postive about MPEX though
A52: Surry Hills | C52: Rodney Eastment | D52: NSW | E52: Owner operator | F52: =VLOOKUP(A52,[3]ActiveFranchiseesResults465!$C:$AA,25,0) -> 11 | G52: 43617 | I52: 46905 | J52: Yes | K52: =VLOOKUP(A52,'Revenue @ Feb 2021'!A:B,2,0) -> 98271.42 | L52: YES | M52: YES | N52: YES | O52: YES | P52: YES | Q52: NO | R52: =VLOOKUP(A52,'Franchisee Ranking'!B:H,6,0) -> 0.021276596 | S52: NO | T52: YES | U52: YES | V52: ? | W52: YES
A53: Brisbane CBD | C53: Michael Mikits | D53: QLD | E53: Investor | F53: 10 | G53: 44196 | I53: 48611 | J53: Yes | K53: =VLOOKUP(A53,'Revenue @ Feb 2021'!A:B,2,0) -> #N/A | L53: NO | M53: YES | N53: YES | O53: YES | P53: NO | Q53: YES | S53: NO | T53: YES | U53: YES | V53: ? | W53: YES
A54: Eagle Farm | C54: Michael Mikits | D54: QLD | E54: Investor | F54: 10 | G54: 44805 | I54: 48611 | J54: Yes | K54: =VLOOKUP(A54,'Revenue @ Feb 2021'!A:B,2,0) -> #N/A | L54: NO | M54: YES | N54: YES | O54: YES | P54: NO | Q54: YES | S54: NO | T54: ? | U54: ? | V54: ? | W54: NO
A55: Geebung | C55: Michael Mikits | D55: QLD | E55: Investor | F55: 10 | G55: 44256 | I55: 48611 | J55: Yes | K55: =VLOOKUP(A55,'Revenue @ Feb 2021'!A:B,2,0) -> #N/A | L55: NO | M55: YES | N55: YES | O55: YES | P55: NO | Q55: YES | S55: NO | T55: ? | U55: ? | V55: ? | W55: NO
A56: Hamilton | C56: Michael Mikits | D56: QLD | E56: Investor | F56: 10 | G56: 44256 | I56: 48611 | J56: Yes | K56: =VLOOKUP(A56,'Revenue @ Feb 2021'!A:B,2,0) -> #N/A | L56: NO | M56: YES | N56: YES | O56: YES | P56: NO | Q56: YES | S56: NO | T56: ? | U56: ? | V56: ? | W56: NO
A57: Spring Hill | C57: Michael Mikits | D57: QLD | E57: Investor | F57: 10 | G57: 44621 | I57: 48611 | J57: Yes | K57: =VLOOKUP(A57,'Revenue @ Feb 2021'!A:B,2,0) -> #N/A | L57: NO | M57: YES | N57: YES | O57: YES | P57: NO | Q57: YES | S57: NO | T57: ? | U57: ? | V57: Yes | W57: NO
A58: Stafford | C58: Michael Mikits | D58: QLD | E58: Investor | F58: 10 | G58: 44256 | I58: 48611 | J58: Yes | K58: =VLOOKUP(A58,'Revenue @ Feb 2021'!A:B,2,0) -> #N/A | L58: NO | M58: YES | N58: YES | O58: YES | P58: NO | Q58: YES | S58: NO | T58: ? | U58: ? | V58: ? | W58: NO
A59: Yatala | C59: Michael Mikits | D59: QLD | E59: Investor | F59: 10 | G59: 45323 | I59: 48976 | J59: Yes | K59: =VLOOKUP(A59,'Revenue @ Feb 2021'!A:B,2,0) -> #N/A | L59: YES | M59: YES | N59: YES | O59: YES | P59: NO | Q59: YES | S59: NO | T59: ? | U59: ? | V59: ? | W59: YES
A60: Brisbane Airport | C60: Michael Mikits | D60: QLD | E60: Investor | F60: 10 | G60: 44256 | I60: 48611 | J60: Yes | K60: =VLOOKUP(A60,'Revenue @ Feb 2021'!A:B,2,0) -> #N/A | L60: NO | M60: YES | N60: YES | O60: YES | P60: NO | Q60: YES | S60: NO | T60: YES | U60: YES | V60: ? | W60: NO
A61: Arncliffe | C61: Ali Gasham | D61: NSW | E61: Investor | F61: =VLOOKUP(A61,[3]ActiveFranchiseesResults465!$C:$AA,25,0) -> 10 | G61: 43891 | H61: Yes | I61: 48274 | J61: NO | K61: =VLOOKUP(A61,'Revenue @ Feb 2021'!A:B,2,0) -> 107791.13 | L61: YES | M61: YES | N61: YES | O61: YES | P61: YES | Q61: YES | R61: =VLOOKUP(A61,'Franchisee Ranking'!B:H,6,0) -> 0.12048193 | S61: NO | T61: YES | U61: YES | V61: Yes | W61: YES
A62: Taren Point | C62: Miljenko Ivanic | D62: NSW | E62: Owner operator | F62: =VLOOKUP(A62,[3]ActiveFranchiseesResults465!$C:$AA,25,0) -> 10 | G62: 43891 | I62: 46447 | J62: yes | K62: =VLOOKUP(A62,'Revenue @ Feb 2021'!A:B,2,0) -> 99485.92 | L62: YES | M62: YES | N62: YES | O62: YES | P62: YES | Q62: YES | R62: =VLOOKUP(A62,'Franchisee Ranking'!B:H,6,0) -> 0.33333333 | S62: NO | T62: ? | U62: ? | V62: ? | W62: YES
A63: Banyo | C63: Bob Schroeder | D63: QLD | E63: Owner operator | F63: =VLOOKUP(A63,[3]ActiveFranchiseesResults465!$C:$AA,25,0) -> 10 | G63: 44165 | I63: 47087 | J63: yes | K63: =VLOOKUP(A63,'Revenue @ Feb 2021'!A:B,2,0) -> 83599.26 | L63: YES | M63: YES | N63: YES | O63: YES | P63: YES | Q63: YES | R63: =VLOOKUP(A63,'Franchisee Ranking'!B:H,6,0) -> 0.11904762 | S63: NO | T63: ? | U63: ? | V63: ? | W63: YES
A64: Regency | C64: Ken Smith / Liz Smith | D64: SA | E64: Owner operator | F64: =VLOOKUP(A64,[3]ActiveFranchiseesResults465!$C:$AA,25,0) -> 10 | G64: 43952 | H64: Yes | I64: 43952 | J64: Yes | K64: =VLOOKUP(A64,'Revenue @ Feb 2021'!A:B,2,0) -> 55950.5 | L64: YES | M64: NO | N64: YES | O64: NO | P64: NO | Q64: NO | R64: =VLOOKUP(A64,'Franchisee Ranking'!B:G,6,0) -> 0 | S64: NO | T64: ? | U64: ? | V64: Yes | W64: YES
A65: Sunshine | C65: Peter Bournouisouzis | D65: VIC | E65: Owner operator | F65: =VLOOKUP(A65,[3]ActiveFranchiseesResults465!$C:$AA,25,0) -> 10 | G65: 43951 | H65: Yes | I65: 46873 | J65: NO | K65: =VLOOKUP(A65,'Revenue @ Feb 2021'!A:B,2,0) -> 51169.69 | L65: YES | M65: YES | N65: YES | O65: NO | P65: NO | Q65: YES | R65: =VLOOKUP(A65,'Franchisee Ranking'!B:G,6,0) -> 0.096774194 | S65: NO | T65: ? | U65: ? | V65: ? | W65: YES
A66: Ryde | C66: John Chan | D66: NSW | E66: Owner operator | F66: =VLOOKUP(A66,[3]ActiveFranchiseesResults465!$C:$AA,25,0) -> 9 | G66: 43909 | I66: 46831 | J66: yes | K66: =VLOOKUP(A66,'Revenue @ Feb 2021'!A:B,2,0) -> 212340.88 | L66: YES | M66: YES | N66: YES | O66: YES | P66: NO | Q66: YES | R66: =VLOOKUP(A66,'Franchisee Ranking'!B:G,6,0) -> 0.24210526 | S66: NO | T66: ? | U66: ? | V66: ? | W66: YES
A67: Sydney - South East B Sydney - South East B | C67: Ali Gasham | D67: NSW | E67: Investor | F67: =VLOOKUP(A67,[3]ActiveFranchiseesResults465!$C:$AA,25,0) -> 9 | G67: 44470 | I67: 46296 | J67: Yes | K67: =VLOOKUP(A67,'Revenue @ Feb 2021'!A:B,2,0) -> 208210.4 | L67: YES | M67: YES | N67: YES | O67: YES | P67: NO | Q67: YES | R67: =VLOOKUP(A67,'Franchisee Ranking'!B:G,6,0) -> 0.074626866 | S67: NO | T67: ? | U67: ? | V67: Yes | W67: YES | X67: Never had big product sales in CBD with AP
A68: Silverwater | C68: Paul Harrison | D68: NSW | E68: Investor | F68: =VLOOKUP(A68,[3]ActiveFranchiseesResults465!$C:$AA,25,0) -> 9 | G68: 43994 | I68: 45820 | J68: Yes | K68: =VLOOKUP(A68,'Revenue @ Feb 2021'!A:B,2,0) -> 90340.22 | L68: YES | M68: YES | N68: YES | O68: YES | P68: NO | Q68: YES | R68: =VLOOKUP(A68,'Franchisee Ranking'!B:G,6,0) -> 0.13333333 | S68: NO | T68: ? | U68: ? | V68: ? | W68: YES | X68: Been waiting on sales support….....
A69: Port Melbourne Port Melbourne | C69: Jonathan Mawer | D69: VIC | E69: Investor | F69: =VLOOKUP(A69,[3]ActiveFranchiseesResults465!$C:$AA,25,0) -> 8 | G69: 43707 | I69: 45534 | J69: Yes | K69: =VLOOKUP(A69,'Revenue @ Feb 2021'!A:B,2,0) -> 248966.93 | L69: NO | M69: YES | N69: YES | O69: NO | P69: NO | Q69: YES | R69: =VLOOKUP(A69,'Franchisee Ranking'!B:G,6,0) -> 0.22807018 | S69: NO | T69: YES | U69: YES | V69: ? | W69: YES
A70: Sydney - South East A Sydney - South East A | C70: Ali Gasham | D70: NSW | E70: Investor | F70: =VLOOKUP(A70,[3]ActiveFranchiseesResults465!$C:$AA,25,0) -> 8 | G70: 42916 | I70: 46568 | J70: Yes | K70: =VLOOKUP(A70,'Revenue @ Feb 2021'!A:B,2,0) -> 186746.07 | L70: YES | M70: YES | N70: YES | O70: YES | P70: NO | Q70: YES | R70: =VLOOKUP(A70,'Franchisee Ranking'!B:G,6,0) -> 0.028985507 | S70: NO | T70: ? | U70: ? | V70: Yes | W70: YES | X70: Never had big product sales in CBD with AP
A71: Milperra | C71: Sam Li | D71: NSW | E71: Owner operator | F71: =VLOOKUP(A71,[3]ActiveFranchiseesResults465!$C:$AA,25,0) -> 8 | G71: 44835 | H71: Yes | I71: 47026 | J71: NO | K71: =VLOOKUP(A71,'Revenue @ Feb 2021'!A:B,2,0) -> 127034.64 | L71: YES | M71: YES | N71: YES | O71: YES | P71: NO | Q71: YES | R71: =VLOOKUP(A71,'Franchisee Ranking'!B:G,6,0) -> 0.13043478 | S71: NO | T71: ? | U71: ? | V71: Yes | W71: YES
A72: South Melbourne | C72: Dane McGreevy | D72: VIC | E72: Owner operator | F72: =VLOOKUP(A72,[3]ActiveFranchiseesResults465!$C:$AA,25,0) -> 8 | G72: 43738 | H72: Yes | I72: 45534 | J72: NO | K72: =VLOOKUP(A72,'Revenue @ Feb 2021'!A:B,2,0) -> 89442.62 | L72: YES | M72: YES | N72: YES | O72: YES | P72: NO | Q72: YES | R72: =VLOOKUP(A72,'Franchisee Ranking'!B:G,6,0) -> 0.054545455 | S72: NO | T72: ? | U72: ? | V72: ? | W72: YES
A73: Riverside | C73: Gary Jakubowicz | D73: VIC | E73: Owner operator | F73: =VLOOKUP(A73,[3]ActiveFranchiseesResults465!$C:$AA,25,0) -> 8 | G73: 44572 | I73: 44562 | J73: Yes | K73: =VLOOKUP(A73,'Revenue @ Feb 2021'!A:B,2,0) -> 76344.03 | L73: YES | M73: YES | N73: YES | O73: YES | P73: NO | Q73: YES | R73: =VLOOKUP(A73,'Franchisee Ranking'!B:G,6,0) -> 0.27906977 | S73: NO | T73: ? | U73: ? | V73: ? | W73: YES
A74: Hunter Valley | C74: Jason Doricott | D74: NSW | E74: Owner operator | F74: =VLOOKUP(A74,[3]ActiveFranchiseesResults465!$C:$AA,25,0) -> 8 | G74: 42978 | I74: 44786 | J74: NO | K74: =VLOOKUP(A74,'Revenue @ Feb 2021'!A:B,2,0) -> 70946.17 | L74: YES | M74: NO | N74: NO | O74: YES | P74: YES | Q74: YES | R74: =VLOOKUP(A74,'Franchisee Ranking'!B:G,6,0) -> 0.021276596 | S74: NO | T74: ? | U74: ? | V74: ? | W74: NO | X74: Positive response but does not have many product purchasing customers
A75: Newcastle | C75: Craig Goodsir | D75: NSW | E75: Owner operator | F75: =VLOOKUP(A75,[3]ActiveFranchiseesResults465!$C:$AA,25,0) -> 7 | G75: 43830 | I75: 47483 | J75: yes | K75: =VLOOKUP(A75,'Revenue @ Feb 2021'!A:B,2,0) -> 273830.42 | L75: NO | M75: NO | N75: YES | O75: NO | P75: NO | Q75: YES | R75: =VLOOKUP(A75,'Franchisee Ranking'!B:G,6,0) -> 0.0097087379 | S75: NO | T75: ? | U75: ? | V75: Yes | W75: YES | X75: Not postive on MPEX may have a side arrangment we are not aware of. | Z75: Drafted but not served | AA75: Yes | AB75: Lack of engagment on MPEX rollout
A76: Browns Plains | C76: David Connor | D76: QLD | E76: Owner operator | F76: =VLOOKUP(A76,[3]ActiveFranchiseesResults465!$C:$AA,25,0) -> 7 | G76: 45138 | I76: 45138 | J76: Yes | K76: =VLOOKUP(A76,'Revenue @ Feb 2021'!A:B,2,0) -> 99578.49 | L76: YES | M76: NO | N76: YES | O76: YES | P76: YES | Q76: YES | R76: =VLOOKUP(A76,'Franchisee Ranking'!B:H,6,0) -> 0.25862069 | S76: NO | T76: YES | U76: YES | V76: ? | W76: YES
A77: Penrith | C77: Robert Marlow | D77: NSW | E77: Owner operator | F77: =VLOOKUP(A77,[3]ActiveFranchiseesResults465!$C:$AA,25,0) -> 7 | G77: 43891 | H77: Yes | I77: 45717 | J77: NO | K77: =VLOOKUP(A77,'Revenue @ Feb 2021'!A:B,2,0) -> 95429.23 | L77: YES | M77: YES | N77: YES | O77: YES | P77: YES | Q77: YES | R77: =VLOOKUP(A77,'Franchisee Ranking'!B:G,6,0) -> 0.013513514 | S77: NO | T77: YES | U77: YES | V77: ? | W77: YES | X77: Done all the right things but can't get usage
A78: Mulgrave | C78: Jason Knight | D78: VIC | E78: Owner operator | F78: =VLOOKUP(A78,[3]ActiveFranchiseesResults465!$C:$AA,25,0) -> 7 | G78: 44166 | I78: 44166 | J78: Yes | K78: =VLOOKUP(A78,'Revenue @ Feb 2021'!A:B,2,0) -> 86459.09 | L78: YES | M78: YES | N78: YES | O78: YES | P78: NO | Q78: YES | R78: =VLOOKUP(A78,'Franchisee Ranking'!B:G,6,0) -> 0.46 | S78: NO | T78: YES | U78: YES | V78: ? | W78: YES
A79: Ermington | C79: Adel Chowna | D79: NSW | E79: Owner operator | F79: =VLOOKUP(A79,[3]ActiveFranchiseesResults465!$C:$AA,25,0) -> 7 | G79: 44852 | H79: Yes | I79: 44851 | J79: NO | K79: =VLOOKUP(A79,'Revenue @ Feb 2021'!A:B,2,0) -> 61776.63 | L79: YES | M79: YES | N79: YES | O79: YES | P79: NO | Q79: YES | R79: =VLOOKUP(A79,'Franchisee Ranking'!B:G,6,0) -> 0.27272727 | S79: NO | T79: ? | U79: ? | V79: ? | W79: YES
A80: Melbourne CBD | C80: Alistair Wright | D80: VIC | E80: Investor | F80: =VLOOKUP(A80,[3]ActiveFranchiseesResults465!$C:$AA,25,0) -> 6 | G80: 43709 | I80: 46631 | J80: Yes | K80: =VLOOKUP(A80,'Revenue @ Feb 2021'!A:B,2,0) -> 546410.96 | L80: YES | M80: YES | N80: YES | O80: YES | P80: NO | Q80: YES | R80: =VLOOKUP(A80,'Franchisee Ranking'!B:G,6,0) -> 0.14375 | S80: NO | T80: ? | U80: ? | V80: Yes | W80: YES
A81: Moorabbin | C81: David Hicks | D81: VIC | E81: Owner operator | F81: =VLOOKUP(A81,[3]ActiveFranchiseesResults465!$C:$AA,25,0) -> 6 | G81: 43889 | I81: 46081 | J81: Yes | K81: =VLOOKUP(A81,'Revenue @ Feb 2021'!A:B,2,0) -> 80744.45 | L81: YES | M81: YES | N81: YES | O81: NO | P81: NO | Q81: YES | R81: =VLOOKUP(A81,'Franchisee Ranking'!B:G,6,0) -> 0.34883721 | S81: NO | T81: YES | U81: YES | V81: Yes | W81: YES
A82: Canning Vale | C82: Todd Ingram | D82: WA | E82: Owner operator | F82: =VLOOKUP(A82,[3]ActiveFranchiseesResults465!$C:$AA,25,0) -> 6 | G82: 44639 | H82: Yes | I82: 45352 | J82: NO | K82: =VLOOKUP(A82,'Revenue @ Feb 2021'!A:B,2,0) -> 76747.09 | L82: YES | M82: YES | N82: YES | O82: YES | P82: NO | Q82: NO | R82: =VLOOKUP(A82,'Franchisee Ranking'!B:G,6,0) -> 0 | S82: NO | T82: ? | U82: ? | V82: ? | W82: YES | X82: No reply
A83: Darlinghurst | C83: John Rodao | D83: NSW | E83: Owner operator | F83: =VLOOKUP(A83,[3]ActiveFranchiseesResults465!$C:$AA,25,0) -> 6 | G83: 43800 | H83: Yes | I83: 47453 | J83: NO | K83: =VLOOKUP(A83,'Revenue @ Feb 2021'!A:B,2,0) -> 72543.24 | L83: YES | M83: NO | N83: YES | O83: NO | P83: NO | Q83: YES | R83: =VLOOKUP(A83,'Franchisee Ranking'!B:G,6,0) -> 0.125 | S83: Yes | T83: ? | U83: ? | V83: ? | W83: YES | X83: No reply
A84: Burleigh | C84: Bruce Hamilton / Maria Hamilton | D84: QLD | E84: Owner operator | F84: =VLOOKUP(A84,[3]ActiveFranchiseesResults465!$C:$AA,25,0) -> 6 | G84: 44448 | I84: 45544 | J84: Yes | K84: =VLOOKUP(A84,'Revenue @ Feb 2021'!A:B,2,0) -> 70735.73 | L84: YES | M84: YES | N84: YES | O84: NO | P84: NO | Q84: YES | R84: =VLOOKUP(A84,'Franchisee Ranking'!B:G,6,0) -> 0.34042553 | S84: NO | T84: YES | U84: YES | V84: ? | W84: YES
A85: Hallam | C85: Stan Cichorski | D85: VIC | E85: Owner operator | F85: =VLOOKUP(A85,[3]ActiveFranchiseesResults465!$C:$AA,25,0) -> 6 | G85: 43769 | I85: 45596 | J85: Yes | K85: =VLOOKUP(A85,'Revenue @ Feb 2021'!A:B,2,0) -> 66244.34 | L85: YES | M85: YES | N85: YES | O85: YES | P85: YES | Q85: YES | R85: =VLOOKUP(A85,'Franchisee Ranking'!B:H,6,0) -> 0.11111111 | S85: NO | T85: ? | U85: ? | V85: ? | W85: YES
A86: Hawthorn | C86: Jeff Hall | D86: VIC | E86: Owner operator | F86: =VLOOKUP(A86,[3]ActiveFranchiseesResults465!$C:$AA,25,0) -> 6 | G86: 45018 | I86: 45018 | J86: Yes | K86: =VLOOKUP(A86,'Revenue @ Feb 2021'!A:B,2,0) -> 59941.75 | L86: YES | M86: YES | N86: YES | O86: NO | P86: NO | Q86: YES | R86: =VLOOKUP(A86,'Franchisee Ranking'!B:G,6,0) -> 0.4047619 | S86: NO | T86: ? | U86: ? | V86: ? | W86: YES
A87: Barton | C87: Saffat Riad | D87: ACT | E87: Investor | F87: =VLOOKUP(A87,[3]ActiveFranchiseesResults465!$C:$AA,25,0) -> 6 | G87: 43861 | H87: Yes | I87: 47514 | J87: NO | K87: =VLOOKUP(A87,'Revenue @ Feb 2021'!A:B,2,0) -> 47125.17 | L87: NO | M87: NO | N87: YES | O87: YES | P87: YES | Q87: NO | R87: =VLOOKUP(A87,'Franchisee Ranking'!B:G,6,0) -> 0 | S87: Yes | T87: ? | U87: ? | V87: ? | W87: YES | X87: Needs sales support to migrate usage behaviour
A88: Brookvale | C88: Frank Huang | D88: NSW | E88: Owner operator | F88: =VLOOKUP(A88,[3]ActiveFranchiseesResults465!$C:$AA,25,0) -> 5 | G88: 43647 | I88: 47300 | J88: Yes | K88: =VLOOKUP(A88,'Revenue @ Feb 2021'!A:B,2,0) -> 133613.26 | L88: YES | M88: YES | N88: YES | O88: YES | P88: YES | Q88: YES | R88: =VLOOKUP(A88,'Franchisee Ranking'!B:H,6,0) -> 0.17741935 | S88: NO | T88: YES | U88: YES | V88: Yes | W88: YES
A89: Clayton | C89: Devinder Singh | D89: VIC | E89: Owner operator | F89: =VLOOKUP(A89,[3]ActiveFranchiseesResults465!$C:$AA,25,0) -> 5 | G89: 43719 | I89: 45546 | J89: Yes | K89: =VLOOKUP(A89,'Revenue @ Feb 2021'!A:B,2,0) -> 112186.73 | L89: YES | M89: YES | N89: YES | O89: YES | P89: NO | Q89: YES | R89: =VLOOKUP(A89,'Franchisee Ranking'!B:G,6,0) -> 0.3125 | S89: NO | T89: ? | U89: ? | V89: ? | W89: YES
A90: Welshpool | C90: Roque Bautista | D90: WA | E90: Owner operator | F90: =VLOOKUP(A90,[3]ActiveFranchiseesResults465!$C:$AA,25,0) -> 5 | G90: 44652 | H90: Yes | I90: 48305 | J90: Yes | K90: =VLOOKUP(A90,'Revenue @ Feb 2021'!A:B,2,0) -> 77895.59 | L90: YES | M90: YES | N90: YES | O90: YES | P90: NO | Q90: YES | R90: =VLOOKUP(A90,'Franchisee Ranking'!B:G,6,0) -> 0.23076923 | S90: NO | T90: ? | U90: ? | V90: ? | W90: YES
A91: Seven Hills | C91: Nhi (David) Lam | D91: NSW | E91: Owner operator | F91: =VLOOKUP(A91,[3]ActiveFranchiseesResults465!$C:$AA,25,0) -> 5 | G91: 44470 | I91: 48122 | J91: Yes | K91: =VLOOKUP(A91,'Revenue @ Feb 2021'!A:B,2,0) -> 68161.14 | L91: YES | M91: NO | N91: YES | O91: NO | P91: NO | Q91: YES | R91: =VLOOKUP(A91,'Franchisee Ranking'!B:G,6,0) -> 0.1025641 | S91: NO | T91: ? | U91: ? | V91: Yes | W91: YES
A92: Hoppers Crossing | C92: Meral Murgoski | D92: VIC | E92: Owner operator | F92: =VLOOKUP(A92,[3]ActiveFranchiseesResults465!$C:$AA,25,0) -> 5 | G92: 44013 | I92: 45839 | J92: Yes | K92: =VLOOKUP(A92,'Revenue @ Feb 2021'!A:B,2,0) -> 60110.11 | L92: YES | M92: YES | N92: YES | O92: YES | P92: NO | Q92: YES | R92: =VLOOKUP(A92,'Franchisee Ranking'!B:G,6,0) -> 0.2195122 | S92: NO | T92: ? | U92: ? | V92: ? | W92: YES
A93: Fairfield | C93: Francis Bautista | D93: NSW | E93: Owner operator | F93: =VLOOKUP(A93,[3]ActiveFranchiseesResults465!$C:$AA,25,0) -> 4 | G93: 44803 | I93: 45901 | J93: Yes | K93: =VLOOKUP(A93,'Revenue @ Feb 2021'!A:B,2,0) -> 105834.83 | L93: YES | M93: YES | N93: YES | O93: YES | P93: NO | Q93: YES | R93: =VLOOKUP(A93,'Franchisee Ranking'!B:G,6,0) -> 0.18181818 | S93: NO | T93: YES | U93: YES | V93: ? | W93: YES
A94: Booval | C94: Kiely Prendergast | D94: QLD | E94: Investor | F94: 4 | G94: 44439 | I94: 46265 | J94: NO | K94: =VLOOKUP(A94,'Revenue @ Feb 2021'!A:B,2,0) -> 95087.98 | L94: NO | M94: YES | N94: YES | O94: YES | P94: YES | Q94: YES | R94: =VLOOKUP(A94,'Franchisee Ranking'!B:H,6,0) -> 0.18918919 | S94: NO | T94: YES | U94: YES | V94: Yes | W94: NO
A95: Preston | C95: Michael Debnam | D95: VIC | E95: Owner operator | F95: =VLOOKUP(A95,[3]ActiveFranchiseesResults465!$C:$AA,25,0) -> 4 | G95: 45017 | I95: 47209 | J95: Yes | K95: =VLOOKUP(A95,'Revenue @ Feb 2021'!A:B,2,0) -> 82793.06 | L95: YES | M95: YES | N95: YES | O95: YES | P95: NO | Q95: YES | R95: =VLOOKUP(A95,'Franchisee Ranking'!B:G,6,0) -> 0.081632653 | S95: NO | T95: ? | U95: ? | V95: ? | W95: YES
A96: Wyong | C96: Dennis Kinchela | D96: NSW | E96: Owner operator | F96: 4 | G96: 44311 | I96: 47963 | J96: Yes | K96: =VLOOKUP(A96,'Revenue @ Feb 2021'!A:B,2,0) -> 64243.24 | L96: YES | M96: YES | N96: YES | O96: YES | P96: NO | Q96: YES | R96: =VLOOKUP(A96,'Franchisee Ranking'!B:G,6,0) -> 0 | S96: NO | T96: YES | U96: YES | V96: ? | W96: YES | X96: Had some personal relationship issues but motivated to get MPEX into his customers
A97: Bayswater | C97: Jayna Vakil / Jaydeep Vakil | D97: VIC | E97: Owner operator | F97: =VLOOKUP(A97,[3]ActiveFranchiseesResults465!$C:$AA,25,0) -> 4 | G97: 44228 | I97: 47150 | J97: Yes | K97: =VLOOKUP(A97,'Revenue @ Feb 2021'!A:B,2,0) -> 59641.45 | L97: YES | M97: YES | N97: YES | O97: YES | P97: NO | Q97: YES | R97: =VLOOKUP(A97,'Franchisee Ranking'!B:G,6,0) -> 0.19444444 | S97: NO | T97: ? | U97: ? | V97: ? | W97: YES
A98: Belmont | C98: Roberto Bautista | D98: WA | E98: Investor | F98: =VLOOKUP(A98,[3]ActiveFranchiseesResults465!$C:$AA,25,0) -> 4 | G98: 45327 | I98: 45327 | J98: yes | K98: =VLOOKUP(A98,'Revenue @ Feb 2021'!A:B,2,0) -> 56049.27 | L98: YES | M98: YES | N98: YES | O98: YES | P98: YES | Q98: YES | R98: =VLOOKUP(A98,'Franchisee Ranking'!B:H,6,0) -> 0.46428571 | S98: NO | T98: ? | U98: ? | V98: ? | W98: YES
A99: Cairns | C99: Gary Chapman | D99: QLD | E99: Owner operator | F99: =VLOOKUP(A99,[3]ActiveFranchiseesResults465!$C:$AA,25,0) -> 4 | G99: 44317 | I99: 47969 | J99: NO | K99: =VLOOKUP(A99,'Revenue @ Feb 2021'!A:B,2,0) -> 36256.9 | L99: YES | M99: YES | N99: YES | O99: YES | P99: YES | Q99: YES | R99: =VLOOKUP(A99,'Franchisee Ranking'!B:H,6,0) -> 0.060606061 | S99: NO | T99: ? | U99: ? | V99: ? | W99: YES | Z99: Yes | AA99: Yes | AB99: Missing customer cash deposits
A100: Sydney - 2N3 | C100: Gavin Ye | D100: NSW | E100: Investor | F100: =VLOOKUP(A100,[3]ActiveFranchiseesResults465!$C:$AA,25,0) -> 3 | G100: 44470 | H100: Yes | I100: 48580 | J100: NO | K100: =VLOOKUP(A100,'Revenue @ Feb 2021'!A:B,2,0) -> 332842.65 | L100: YES | M100: NO | N100: YES | O100: YES | P100: NO | Q100: YES | R100: =VLOOKUP(A100,'Franchisee Ranking'!B:G,6,0) -> 0.062068966 | S100: Yes | T100: ? | U100: ? | V100: Yes | W100: YES | X100: Overseas & not readings comms. | Z100: Yes | AA100: Yes | AB100: Statutory contractor obligations not being met
...

Sheet Altona
B2: Franchisee | C2: Altona
B3: Franchisee Name | C3: Rofel Del LaCerna
B4: State | C4: VIC
B5: Profile | C5: Owner operator
B6: Expiry Date | C6: 43678
B7: Ultimate Expiry Date (Including FY18 release) | C7: 45505
B8: Unlimted Term | C8: NO
B9: Annual Turnover (service revenue) | C9: ='Scorecard matrix'!J2 -> #N/A
B10: Number of customers | C10: ='Busse''s DATA'!C42 -> 39
B11: Number of customers using MPEX | C11: 7
B12: Digitalisation | C12: YES
B13: In attendance at Roadshow | C13: NO
B14: Workshop Attendance | C14: YES
B15: Reading weekly bulletins(After final reminder) | C15: NO
B16: Customer Nomination | C16: NO
B17: MPEX allocation | C17: YES
B18: MPEX Usage % | C18: =C11/C10 -> 0.17948718
B19: Late with completion of monthly invoicing | C19: NO
B20: HO Insurances | C20: YES
B21: 30th Sept action email (Feedback) | C21: Reply email appears he's continuing to stall
B23: Notes:
B24: I don't remember any major issues with him. However it appears he never provided updated contact details on the spreadsheet I sent him for mpex.
B26: I had sent him 2 emails regarding Mpex he didn't reply. I would have called him at some stage but I cannot remember.

Sheet Pyrmont
B2: Franchisee | C2: Pyrmont
B3: Franchisee Name | C3: Budi Nagi
B4: State | C4: NSW
B5: Profile | C5: Investor
B6: Expiry Date | C6: 44442
B7: Ultimate Expiry Date (Including FY18 release) | C7: 46268
B8: Unlimted Term | C8: Yes
B9: Annual Turnover (service revenue) | C9: ='Scorecard matrix'!J13 -> 195336.58
B10: Number of customer | C10: ='Busse''s DATA'!C21 -> 93
B11: Number of customer using MPEX | C11: 2
B12: Digisitation | C12: NO
B13: In attendance at Roadshow | C13: YES
B14: Workshop Attendance | C14: YES
B15: Reading weekly bulletins(After final reminder) | C15: YES
B16: Customer Nomination | C16: YES
B17: MPEX allocation to ZZ date | C17: 15th Sept
B18: MPEX allocation to customer | C18: 10th Oct
B19: MPEX Usage % | C19: =C11/C10 -> 0.021505376
B20: Late with completion of monthly invoicing | C20: NO
B21: HO Insurances | C21: YES
B22: 30th Sept action email (Feedback) | C22: No reply
B24: Notes:
B25: He never completed the spreadsheet I sent him originally. I made contact with him several times via phone and email in regards to this.
B26: He told me to call another guy cant remember his name I think he is the actual owner and gave me his mobile number. I did that and left voicemail messages but never got a call back.

Sheet Sheet1
B2: Franchise | C2: Investor
B3: Brisbane CBD | C3: Michael Mikits
B4: Arncliffe | C4: Ali Gasham
B5: Belmont | C5: Roberto Bautista
B6: Parramatta | C6: Simon Hoatson
B7: Melbourne CBD | C7: Alistair Wright
B10: Franchise | C10: Owner Operator
B11: Braeside | C11: Sally Skomrlj
B12: Illawarra | C12: Mathew Barnes
B13: Airport West | C13: Stebe Begeman
B14: Banyo | C14: Bob Schroeder
B15: Botany Botany | C15: Richard Chang
... B25: Willoughby | C25: Peter Hayes

Sheet Barton
B2: Franchisee | C2: Barton
B3: Franchisee Name | C3: Saffat Riad
B4: State | C4: ACT
B5: Expiry Date | C5: 43861
B6: Ultimate Expiry Date (Including FY18 release) | C6: 47514
B7: Unlimted Term | C7: NO
B8: Annual Turnover (service revenue) | C8: ='Scorecard matrix'!J3 -> 64243.24
B9: Number of customers | C9: ='Busse''s DATA'!C3 -> 36
B10: Number of customers using | C10: 1
B11: Digisitation | C11: NO
B12: In attendance at Roadshow | C12: NO
B13: Workshop Attendance | C13: YES
B14: Reading weekly bulletins(After final reminder) | C14: YES
B15: Customer Nomination | C15: YES
B16: MPEX allocation | C16: YES
B17: MPEX Usage % | C17: =C10/C9 -> 0.027777778
B18: Late with completion of monthly invoicing | C18: Yes
B19: HO Insurances | C19: YES
B20: 30th Sept action email (Feedback) | C20: Needs sales support to migrate usage behaviour

Sheet Canberra Airport
B2: Franchisee | C2: Canberra Airport
B3: Franchisee Name | C3: Abul Hassan Syed
B4: State | C4: ACT
B5: Expiry Date | C5: 43862
B6: Ultimate Expiry Date (Including FY18 release) | C6: 47515
B7: Unlimted Term | C7: Yes
B8: Annual Turnover (service revenue) | C8: ='Scorecard matrix'!J22 -> 124192.48
B9: Number of customers | C9: ='Busse''s DATA'!C5 -> 51
B10: Number of customers using MPEX | C10: 2
B11: Digisitation | C11: YES
B12: In attendance at Roadshow | C12: NO
B13: Workshop Attendance | C13: YES
B14: Reading weekly bulletins(After final reminder) | C14: YES
B15: Customer Nomination | C15: YES
B16: MPEX allocation | C16: YES
B17: MPEX Usage % | C17: =C10/C9 -> 0.039215686
B18: Late with completion of monthly invoicing | C18: Yes
B19: HO Insurances | C19: YES
B20: 30th Sept action email (Feedback) | C20: Simply hasn't understood any HO comms - language barrier is a major concern

Sheet Newcastle
B2: Franchisee | C2: Newcastle
B3: Franchisee Name | C3: Craig Goodsir
B4: State | C4: NSW
B5: Expiry Date | C5: 43830
B6: Ultimate Expiry Date (Including FY18 release) | C6: 47483
B7: Unlimted Term | C7: NO
B8: Annual Turnover (service revenue) | C8: ='Scorecard matrix'!J11 -> 149881.33
B9: Customer number | C9: 103
B10: Customer number using MPEX | C10: 2
B11: Digisitation | C11: NO
B12: In attendance at Roadshow | C12: NO
B13: Workshop Attendance | C13: YES
B14: Reading weekly bulletins(After final reminder) | C14: NO
B15: Customer Nomination | C15: NO
B16: MPEX allocation | C16: YES
B17: MPEX Usage % | C17: =C10/C9 -> 0.019417476
B18: Late with completion of monthly invoicing | C18: NO
B19: Uniform (ordered in past 12months) | C19: Yes
B20: HO Insurances | C20: YES
B21: 30th Sept action email (Feedback) | C21: Not postive on MPEX

Sheet Jason Yang
B2: Franchisee | C2: North Sydney | D2: Lane Cove | E2: Sydney - North West
B3: Franchisee Name | C3: Jason Yang | D3: Jason Yang | E3: Jason Yang
B4: State | C4: NSW | D4: NSW | E4: NSW
B5: Expiry Date | C5: 43994 | D5: 43786 | E5: 44470
B6: Ultimate Expiry Date (Including FY18 release) | C6: 45820 | D6: 45613 | E6: 46296
B7: Customer Count | C7: ='Busse''s DATA'!C59 -> 112 | D7: ='Busse''s DATA'!C55 -> 76 | E7: ='Busse''s DATA'!C61 -> 127
B8: Customers using MPEX | C8: 8 | D8: 6 | E8: 11
B9: Annual Turnover | C9: ='Scorecard matrix'!J6 -> 40896.48 | D9: ='Scorecard matrix'!J25 -> #N/A | E9: ='Scorecard matrix'!J18 -> 98271.42
B10: Unlimted Term | C10: Yes | D10: Yes | E10: Yes
B11: Digisitation | C11: NO | D11: NO | E11: NO
B12: In attendance at Roadshow | C12: YES | D12: YES | E12: YES
B13: Workshop Attendance | C13: YES | D13: YES | E13: YES
B14: Reading weekly bulletins(After final reminder) | C14: YES | D14: YES | E14: YES
B15: Customer Nomination | C15: NO | D15: NO | E15: NO
B16: MPEX allocation | C16: YES | D16: YES | E16: YES
B17: MPEX Usage % | C17: =C8/C7 -> 0.071428571 | D17: =D8/D7 -> 0.078947368 | E17: =E8/E7 -> 0.086614173
B18: Late with completion of monthly invoicing | C18: Yes | D18: Yes | E18: Yes
B19: Uniform (ordered in past 12months) | C19: Yes | D19: Yes | E19: Yes
B20: HO Insurances | C20: YES | D20: NO | E20: YES
B22: Notes
B23: North Sydney - Refused to be of any assistance in providing details for his territories. to NetSuite".
B24: Had a lot of negative things to say and pretty much told me all details I would need are in NetSuite already. So I took details from NetSuite for his territories and they were added into the spreadsheet as "According to NS.

Sheet Budi
B2: Franchisee | C2: Pyrmont
B3: Franchisee Name | C3: Budi Nagi
B4: State | C4: NSW
B5: Expiry Date | C5: 44442
B6: Ultimate Expiry Date (Including FY18 release) | C6: 46268
B7: Unlimted Term | C7: Yes
B8: Annual Turnover (service revenue) | C8: ='Scorecard matrix'!J13 -> 195336.58
B9: Customer count | C9: ='Busse''s DATA'!C21 -> 93
B10: Customers using MPEX | C10: 1
B11: Digisitation | C11: NO
B12: In attendance at Roadshow | C12: YES
B13: Workshop Attendance | C13: YES
B14: Reading weekly bulletins(After final reminder) | C14: YES
B15: Customer Nomination | C15: YES
B16: MPEX allocation | C16: YES
B17: MPEX Usage % | C17: =C10/C9 -> 0.010752688
B18: Late with completion of monthly invoicing | C18: NO
B19: HO Insurances | C19: YES
B20: 30th Sept action email (Feedback) | C20: No reply
B22: Notes:
B23: Pyrmont - I called and emailed Budi many times, until he finally told me to call (I think it was Jason) and provided me with his mobile number, which I did call and left messages about three times. I eventually gave up.
B25: However leads were provided for the nominated mp express.

Sheet Rick Zammit
B2: Franchisee | C2: Acacia Ridge | D2: Mount Gravatt | E2: Springwood
B3: Franchisee Name | C3: Rick Zammit | D3: Rick Zammit | E3: Rick Zammit
B4: State | C4: QLD | D4: QLD | E4: QLD
B5: Expiry Date | C5: 45151 | D5: 45139 | E5: 45139
B6: Ultimate Expiry Date (Including FY18 release) | C6: 46966 | D6: 46977 | E6: 46966
B7: Unlimted Term | C7: NO | D7: NO | E7: NO
B8: Annual Turnover (service revenue) | C8: ='Scorecard matrix'!J21 -> #N/A | D8: ='Scorecard matrix'!J97 -> 76747.09 | E8: ='Scorecard matrix'!J113 -> 95087.98
B9: Customer count | C9: 51 | D9: 65 | E9: 65
B10: Customers using MPEX | C10: 5 | D10: 11 | E10: 0
B11: Digisitation | C11: YES | D11: YES | E11: YES
B12: In attendance at Roadshow | C12: YES | D12: YES | E12: YES
B13: Workshop Attendance | C13: YES | D13: YES | E13: YES
B14: Reading weekly bulletins(After final reminder) | C14: YES | D14: YES | E14: YES
B15: Customer Nomination | C15: NO | D15: NO | E15: NO
B16: MPEX allocation | C16: YES | D16: YES | E16: YES
B17: MPEX Usage % | C17: =C10/C9 -> 0.098039216 | D17: =D10/D9 -> 0.16923077 | E17: =E10/E9 -> 0
B18: Late with completion of monthly invoicing | C18: NO | D18: NO | E18: NO
B19: Uniform (ordered in past 12months) | C19: Yes | D19: Yes | E19: ?
B20: HO Insurances | C20: YES | D20: NO | E20: YES
B22: Notes:
B23: Rick Zammit - MP Acacia Ridge, Mt Gravatt & Springwood - Took awhile to get data to me for one of his areas. But managed to get it to me at the last minute.
B24: Said he had some problems with lodgement points. But was always polite to deal with.

Sheet Jones
B2: Franchisee | C2: Jones Jones
B3: Franchisee Name | C3: Ellen Jones / Allan Jones
B4: State | C4: QLD
B5: Expiry Date | C5: 43830
B6: Ultimate Expiry Date (Including FY18 release) | C6: 47118
B7: Unlimted Term | C7: NO
B8: Annual Turnover (service revenue) | C8: ='Scorecard matrix'!J9 -> 110576.14
B9: Customer count | C9: 81
B10: Customers using MPEX | C10: 5
B11: Digisitation | C11: YES
B12: In attendance at Roadshow | C12: NO
B13: Workshop Attendance | C13: YES
B14: Reading weekly bulletins(After final reminder) | C14: YES
B15: Customer Nomination | C15: NO
B16: MPEX allocation | C16: YES
B17: MPEX Usage % | C17: =C10/C9 -> 0.061728395
B18: Late with completion of monthly invoicing | C18: NO
B19: HO Insurances | C19: YES
B20: 30th Sept action email (Feedback) | C20: Sales rep never called back to arrange customer call down
B22: Notes:
B23: Allen & Ellen Jones - MP Jones - No issue here but this one was put on hold a bit. Then they ended up saying they would take care of this one themselves.

Sheet Tappenden
B2: Franchisee | C2: Tappenden Tappenden
B3: Franchisee Name | C3: Allison Tappenden
B4: State | C4: QLD
B5: Expiry Date | C5: 43709
B6: Ultimate Expiry Date (Including FY18 release) | C6: 46997
B7: Unlimted Term | C7: NO
B8: Annual Turnover (service revenue) | C8: ='Scorecard matrix'!J19 -> 147084
B9: Customer count | C9: 99
B10: Customers using MPEX | C10: 0
B11: Digisitation | C11: NO
B12: In attendance at Roadshow | C12: YES
B13: Workshop Attendance | C13: NO
B14: Reading weekly bulletins(After final reminder) | C14: YES
B15: Customer Nomination | C15: NO
B16: MPEX allocation | C16: NO
B17: MPEX Usage % (as @ 08102019) | C17: =C10 -> 0
B18: Late with completion of monthly invoicing | C18: NO
B19: HO Insurances | C19: YES
B20: 30th Sept action email (Feedback) | C20: Hostile reply - blaming anyone & everyone
B23: Notes:
B24: Allisson Tappenden - MP Tappenden - I wouldn't be upset if I didn't have to speak with her again. Had a very unpleasant phone call with her.
B26: She was very negative and made sure I knew that she had no faith in the sales team or MailPlus Kept mentioning how she has received no support from MailPlus in the past etc etc. I tired to steer away from that and focus on how things are now.
B29: No mater how positive or reassuring I was she just kept shutting me down

Sheet Franchisee Ranking
B2: Franchisee | C2: Active(customers) | D2: Unlimited term | E2: Used | F2: Allocated | G2: Used % | H2: Allocated % | M2: Used | P2: Row Labels | Q2: Allocated
B3: Albury | C3: 8 | E3: 0 | F3: 0 | G3: 0 | H3: =IF(F3="","",F3/C3) -> 0 | I3: 0 | L3: Acacia Ridge | M3: 5 | P3: Acacia Ridge | Q3: 1
B4: Barton | C4: 36 | E4: 0 | F4: 0 | G4: 0 | H4: =IF(F4="","",F4/C4) -> 0 | I4: 0 | L4: Adelaide CBD | M4: 9 | P4: Adelaide CBD | Q4: 33
B5: Bondi Junction | C5: 91 | E5: 0 | F5: 0 | G5: 0 | H5: =IF(F5="","",F5/C5) -> 0 | I5: 0 | L5: Airport West | M5: 22 | P5: Airport West | Q5: 29
B6: Canberra Airport | C6: 51 | E6: 0 | F6: 0 | G6: 0 | H6: =IF(F6="","",F6/C6) -> 0 | I6: 0 | L6: Alexandria | M6: 31 | P6: Alexandria | Q6: 48
B7: Canberra CBD | C7: 38 | E7: 0 | F7: 0 | G7: 0 | H7: =IF(F7="","",F7/C7) -> 0 | I7: 0 | L7: Altona | M7: 4 | P7: Altona | Q7: 7
B8: Canning Vale | C8: 37 | D8: NO | E8: 0 | F8: 0 | G8: 0 | H8: =IF(F8="","",F8/C8) -> 0 | I8: 0 | L8: Arncliffe | M8: 10 | P8: Arncliffe | Q8: 24
B9: Cleveland | C9: 19 | E9: 0 | F9: 0 | G9: 0 | H9: =IF(F9="","",F9/C9) -> 0 | I9: 0 | L9: Banyo | M9: 5 | P9: Banyo | Q9: 17
B10: Coffs Harbour | C10: 2 | E10: 0 | F10: 0 | G10: 0 | H10: =IF(F10="","",F10/C10) -> 0 | I10: 0 | L10: Baulkham Hills | M10: 15 | P10: Baulkham Hills | Q10: 24
B11: Darwin | C11: 75 | E11: 0 | F11: 0 | G11: 0 | H11: =IF(F11="","",F11/C11) -> 0 | I11: 0 | L11: Bayswater | M11: 7 | P11: Bayswater | Q11: 12
B12: Devonport | C12: 5 | E12: 0 | F12: 0 | G12: 0 | H12: =IF(F12="","",F12/C12) -> 0 | I12: 0 | L12: Belmont | M12: 13 | P12: Belmont | Q12: 10
B13: Epping | C13: 33 | E13: 0 | F13: 0 | G13: 0 | H13: =IF(F13="","",F13/C13) -> 0 | I13: 0 | L13: Blacktown | M13: 11 | P13: Blacktown | Q13: 32
B14: Ipswich | C14: 20 | E14: 0 | F14: 0 | G14: 0 | H14: =IF(F14="","",F14/C14) -> 0 | I14: 0 | L14: Booval | M14: 7 | P14: Booval | Q14: 11
B15: Mackay | C15: 13 | E15: 0 | F15: 0 | G15: 0 | H15: =IF(F15="","",F15/C15) -> 0 | I15: 0 | L15: Botany Botany | M15: 9 | P15: Botany Botany | Q15: 25
B16: Mailplus Unassigned | C16: 3 | E16: 0 | F16: 0 | G16: 0 | H16: =IF(F16="","",F16/C16) -> 0 | I16: 0 | L16: Bowen Hills | M16: 12 | P16: Bowen Hills | Q16: 28
B17: Nerang | C17: 72 | E17: 0 | F17: 0 | G17: 0 | H17: =IF(F17="","",F17/C17) -> 0 | I17: 0 | L17: Box Hill | M17: 5 | P17: Box Hill | Q17: 6
B18: Osborne Park | C18: 63 | D18: YES | E18: 0 | F18: 0 | G18: 0 | H18: =IF(F18="","",F18/C18) -> 0 | I18: 0 | L18: Braeside | M18: 17 | P18: Braeside | Q18: 22
B19: Perth CBD | C19: 26 | E19: 0 | F19: 0 | G19: 0 | H19: =IF(F19="","",F19/C19) -> 0 | I19: 0 | L19: Brendale | M19: 2 | P19: Brendale | Q19: 2
B20: Regency | C20: 33 | E20: 0 | F20: 0 | G20: 0 | H20: =IF(F20="","",F20/C20) -> 0 | I20: 0 | L20: Brisbane | M20: 115 | P20: Brisbane | Q20: 173
B21: Springwood | C21: 65 | E21: 0 | F21: 0 | G21: 0 | H21: =IF(F21="","",F21/C21) -> 0 | I21: 0 | L21: Brookvale | M21: 11 | P21: Brookvale | Q21: 23
B22: Tappenden Tappenden | C22: 99 | E22: 0 | F22: 0 | G22: 0 | H22: =IF(F22="","",F22/C22) -> 0 | I22: 0 | L22: Browns Plains | M22: 15 | P22: Browns Plains | Q22: 31
B23: Townsville | C23: 20 | E23: 0 | F23: 0 | G23: 0 | H23: =IF(F23="","",F23/C23) -> 0 | I23: 0 | L23: Burleigh | M23: 16 | P23: Burleigh | Q23: 14
B24: West Perth | C24: 21 | E24: 0 | F24: 0 | G24: 0 | H24: =IF(F24="","",F24/C24) -> 0 | I24: 0 | L24: Cairns | M24: 2 | P24: Byron Bay | Q24: 3
B25: Wetherill Park | C25: 73 | E25: 0 | F25: 0 | G25: 0 | H25: =IF(F25="","",F25/C25) -> 0 | I25: 0 | L25: Campbellfield | M25: 8 | P25: Cairns | Q25: 4
B26: Rosebery | C26: 18 | E26: 3 | F26: 0 | G26: =IF(E26="","",E26/C26) -> 0.16666667 | H26: =IF(F26="","",F26/C26) -> 0 | I26: 0 | L26: Campbelltown | M26: 16 | P26: Campbellfield | Q26: 20
B27: Bowen Hills | C27: 36 | E27: 12 | F27: 28 | G27: =IF(E27="","",E27/C27) -> 0.33333333 | H27: =IF(F27="","",F27/C27) -> 0.77777778 | L27: Clayton | M27: 15 | P27: Campbelltown | Q27: 24
B28: Mount Waverley | C28: 22 | E28: 9 | F28: 15 | G28: =IF(E28="","",E28/C28) -> 0.40909091 | H28: =IF(F28="","",F28/C28) -> 0.68181818 | L28: Crows Nest | M28: 6 | P28: Clayton | Q28: 22
B29: Milperra | C29: 46 | E29: 6 | F29: 30 | G29: =IF(E29="","",E29/C29) -> 0.13043478 | H29: =IF(F29="","",F29/C29) -> 0.65217391 | L29: Dandenong | M29: 12 | P29: Crows Nest | Q29: 12
B30: Scoresby | C30: 43 | D30: YES | E30: 26 | F30: 28 | G30: =IF(E30="","",E30/C30) -> 0.60465116 | H30: =IF(F30="","",F30/C30) -> 0.65116279 | L30: Darlinghurst | M30: 3 | P30: Dandenong | Q30: 26
B31: Mulgrave | C31: 50 | D31: YES | E31: 23 | F31: 31 | G31: =IF(E31="","",E31/C31) -> 0.46 | H31: =IF(F31="","",F31/C31) -> 0.62 | L31: Ermington | M31: 12 | P31: Darlinghurst | Q31: 5
B32: Braeside | C32: 36 | E32: 17 | F32: 22 | G32: =IF(E32="","",E32/C32) -> 0.47222222 | H32: =IF(F32="","",F32/C32) -> 0.61111111 | L32: Fairfield | M32: 8 | P32: Ermington | Q32: 21
B33: Alexandria | C33: 80 | E33: 31 | F33: 48 | G33: =IF(E33="","",E33/C33) -> 0.3875 | H33: =IF(F33="","",F33/C33) -> 0.6 | L33: Geelong | M33: 1 | P33: Fairfield | Q33: 9
B34: Waterloo | C34: 38 | E34: 17 | F34: 22 | G34: =IF(E34="","",E34/C34) -> 0.44736842 | H34: =IF(F34="","",F34/C34) -> 0.57894737 | L34: Gold Coast | M34: 14 | P34: Geelong | Q34: 4
B35: Willoughby | C35: 72 | E35: 17 | F35: 41 | G35: =IF(E35="","",E35/C35) -> 0.23611111 | H35: =IF(F35="","",F35/C35) -> 0.56944444 | L35: Gosford Shire | M35: 12 | P35: Gold Coast | Q35: 19
B36: Browns Plains | C36: 58 | E36: 15 | F36: 31 | G36: =IF(E36="","",E36/C36) -> 0.25862069 | H36: =IF(F36="","",F36/C36) -> 0.53448276 | L36: Hallam | M36: 4 | P36: Gosford Shire | Q36: 13
B37: Moorebank | C37: 45 | D37: NO | E37: 10 | F37: 24 | G37: =IF(E37="","",E37/C37) -> 0.22222222 | H37: =IF(F37="","",F37/C37) -> 0.53333333 | L37: Hawthorn | M37: 17 | P37: Hallam | Q37: 7
B38: Blacktown | C38: 61 | E38: 11 | F38: 32 | G38: =IF(E38="","",E38/C38) -> 0.18032787 | H38: =IF(F38="","",F38/C38) -> 0.52459016 | L38: Hemmant | M38: 2 | P38: Hawthorn | Q38: 19
B39: Airport West | C39: 57 | E39: 22 | F39: 29 | G39: =IF(E39="","",E39/C39) -> 0.38596491 | H39: =IF(F39="","",F39/C39) -> 0.50877193 | L39: Hobart | M39: 1 | P39: Hemmant | Q39: 10
B40: Mascot | C40: 59 | E40: 16 | F40: 30 | G40: =IF(E40="","",E40/C40) -> 0.27118644 | H40: =IF(F40="","",F40/C40) -> 0.50847458 | L40: Homebush | M40: 1 | P40: Hobart | Q40: 1
B41: Peninsula | C41: 22 | E41: 6 | F41: 11 | G41: =IF(E41="","",E41/C41) -> 0.27272727 | H41: =IF(F41="","",F41/C41) -> 0.5 | L41: Hoppers Crossing | M41: 9 | P41: Homebush | Q41: 1
B42: Ermington | C42: 44 | E42: 12 | F42: 21 | G42: =IF(E42="","",E42/C42) -> 0.27272727 | H42: =IF(F42="","",F42/C42) -> 0.47727273 | L42: Hunter Valley | M42: 1 | P42: Hoppers Crossing | Q42: 9
B43: Macquarie Park | C43: 70 | E43: 24 | F43: 33 | G43: =IF(E43="","",E43/C43) -> 0.34285714 | H43: =IF(F43="","",F43/C43) -> 0.47142857 | L43: Illawarra | M43: 3 | P43: Hunter Valley | Q43: 3
B44: Clayton | C44: 48 | D44: YES | E44: 15 | F44: 22 | G44: =IF(E44="","",E44/C44) -> 0.3125 | H44: =IF(F44="","",F44/C44) -> 0.45833333 | L44: Jones Jones | M44: 1 | P44: Illawarra | Q44: 6
B45: Hawthorn | C45: 42 | D45: YES | E45: 17 | F45: 19 | G45: =IF(E45="","",E45/C45) -> 0.4047619 | H45: =IF(F45="","",F45/C45) -> 0.45238095 | L45: Kewdale | M45: 7 | P45: Jones Jones | Q45: 4
B46: Ryde | C46: 95 | D46: NO | E46: 23 | F46: 41 | G46: =IF(E46="","",E46/C46) -> 0.24210526 | H46: =IF(F46="","",F46/C46) -> 0.43157895 | L46: Lalor | M46: 9 | P46: Kewdale | Q46: 11
B47: Moorabbin | C47: 43 | D47: YES | E47: 15 | F47: 18 | G47: =IF(E47="","",E47/C47) -> 0.34883721 | H47: =IF(F47="","",F47/C47) -> 0.41860465 | L47: Lane Cove | M47: 4 | P47: Lalor | Q47: 19
B48: Banyo | C48: 42 | E48: 5 | F48: 17 | G48: =IF(E48="","",E48/C48) -> 0.11904762 | H48: =IF(F48="","",F48/C48) -> 0.4047619 | L48: Lane Lane | M48: 2 | P48: Lane Cove | Q48: 3
B49: Northern Beaches | C49: 53 | E49: 19 | F49: 21 | G49: =IF(E49="","",E49/C49) -> 0.35849057 | H49: =IF(F49="","",F49/C49) -> 0.39622642 | L49: Launceston | M49: 2 | P49: Lane Lane | Q49: 7
B50: Murarrie | C50: 41 | D50: NO | E50: 10 | F50: 16 | G50: =IF(E50="","",E50/C50) -> 0.24390244 | H50: =IF(F50="","",F50/C50) -> 0.3902439 | L50: Liverpool | M50: 10 | P50: Launceston | Q50: 4
B51: Lalor | C51: 49 | E51: 9 | F51: 19 | G51: =IF(E51="","",E51/C51) -> 0.18367347 | H51: =IF(F51="","",F51/C51) -> 0.3877551 | L51: Macquarie Park | M51: 24 | P51: Liverpool | Q51: 10
B52: Campbelltown | C52: 62 | E52: 16 | F52: 24 | G52: =IF(E52="","",E52/C52) -> 0.25806452 | H52: =IF(F52="","",F52/C52) -> 0.38709677 | L52: Mascot | M52: 16 | P52: Macquarie Park | Q52: 33
B53: Campbellfield | C53: 53 | E53: 8 | F53: 20 | G53: =IF(E53="","",E53/C53) -> 0.1509434 | H53: =IF(F53="","",F53/C53) -> 0.37735849 | L53: Melbourne CBD | M53: 23 | P53: Mascot | Q53: 30
B54: Seaford | C54: 51 | E54: 10 | F54: 19 | G54: =IF(E54="","",E54/C54) -> 0.19607843 | H54: =IF(F54="","",F54/C54) -> 0.37254902 | L54: Milperra | M54: 6 | P54: Melbourne CBD | Q54: 50
B55: Brookvale | C55: 62 | E55: 11 | F55: 23 | G55: =IF(E55="","",E55/C55) -> 0.17741935 | H55: =IF(F55="","",F55/C55) -> 0.37096774 | L55: Moorabbin | M55: 15 | P55: Milperra | Q55: 30
B56: Botany Botany | C56: 69 | D56: NO | E56: 9 | F56: 25 | G56: =IF(E56="","",E56/C56) -> 0.13043478 | H56: =IF(F56="","",F56/C56) -> 0.36231884 | L56: Moorebank | M56: 10 | P56: Moorabbin | Q56: 18
B57: Belmont | C57: 28 | E57: 13 | F57: 10 | G57: =IF(E57="","",E57/C57) -> 0.46428571 | H57: =IF(F57="","",F57/C57) -> 0.35714286 | L57: Morningside | M57: 2 | P57: Moorebank | Q57: 24
B58: Brisbane | C58: 485 | D58: YES | E58: 115 | F58: 173 | G58: =IF(E58="","",E58/C58) -> 0.2371134 | H58: =IF(F58="","",F58/C58) -> 0.35670103 | L58: Mount Gravatt | M58: 10 | P58: Morningside | Q58: 6
B59: Rocklea | C59: 41 | D59: YES | E59: 7 | F59: 14 | G59: =IF(E59="","",E59/C59) -> 0.17073171 | H59: =IF(F59="","",F59/C59) -> 0.34146341 | L59: Mount Waverley | M59: 9 | P59: Mount Gravatt | Q59: 11
B60: Taren Point | C60: 24 | E60: 8 | F60: 8 | G60: =IF(E60="","",E60/C60) -> 0.33333333 | H60: =IF(F60="","",F60/C60) -> 0.33333333 | L60: Mulgrave | M60: 23 | P60: Mount Waverley | Q60: 15
B61: Rouse Hill | C61: 21 | E61: 5 | F61: 7 | G61: =IF(E61="","",E61/C61) -> 0.23809524 | H61: =IF(F61="","",F61/C61) -> 0.33333333 | L61: Murarrie | M61: 10 | P61: Mulgrave | Q61: 31
B62: Bayswater | C62: 36 | E62: 7 | F62: 12 | G62: =IF(E62="","",E62/C62) -> 0.19444444 | H62: =IF(F62="","",F62/C62) -> 0.33333333 | L62: Newcastle | M62: 1 | P62: Murarrie | Q62: 16
B63: Liverpool | C63: 32 | E63: 10 | F63: 10 | G63: =IF(E63="","",E63/C63) -> 0.3125 | H63: =IF(F63="","",F63/C63) -> 0.3125 | L63: North Ipswich | M63: 1 | P63: Newcastle | Q63: 1
B64: Melbourne CBD | C64: 160 | D64: YES | E64: 23 | F64: 50 | G64: =IF(E64="","",E64/C64) -> 0.14375 | H64: =IF(F64="","",F64/C64) -> 0.3125 | L64: North Lakes | M64: 1 | P64: North Ipswich | Q64: 2
B65: St Kilda Road | C65: 45 | E65: 10 | F65: 14 | G65: =IF(E65="","",E65/C65) -> 0.22222222 | H65: =IF(F65="","",F65/C65) -> 0.31111111 | L65: North Melbourne | M65: 8 | P65: North Lakes | Q65: 1
B66: Dandenong | C66: 84 | E66: 12 | F66: 26 | G66: =IF(E66="","",E66/C66) -> 0.14285714 | H66: =IF(F66="","",F66/C66) -> 0.30952381 | L66: North Sydney | M66: 5 | P66: North Melbourne | Q66: 12
B67: Baulkham Hills | C67: 78 | E67: 15 | F67: 24 | G67: =IF(E67="","",E67/C67) -> 0.19230769 | H67: =IF(F67="","",F67/C67) -> 0.30769231 | L67: Northern Beaches | M67: 19 | P67: North Sydney | Q67: 24
B68: Seven Hills | C68: 39 | E68: 4 | F68: 12 | G68: =IF(E68="","",E68/C68) -> 0.1025641 | H68: =IF(F68="","",F68/C68) -> 0.30769231 | L68: Parramatta | M68: 18 | P68: Northern Beaches | Q68: 21
B69: Riverside | C69: 43 | E69: 12 | F69: 13 | G69: =IF(E69="","",E69/C69) -> 0.27906977 | H69: =IF(F69="","",F69/C69) -> 0.30232558 | L69: Peninsula | M69: 6 | P69: Parramatta | Q69: 25
B70: Byron Bay | C70: 10 | F70: 3 | H70: =IF(F70="","",F70/C70) -> 0.3 | L70: Penrith | M70: 1 | P70: Peninsula | Q70: 11
B71: Port Melbourne Port Melbourne | C71: 114 | E71: 26 | F71: 34 | G71: =IF(E71="","",E71/C71) -> 0.22807018 | H71: =IF(F71="","",F71/C71) -> 0.29824561 | L71: Port Melbourne Port Melbourne | M71: 26 | P71: Penrith | Q71: 2
